Workbook

Sheet Amazon Books Inventory Team

Sheet Sources >>

Sheet Stock
A1: =IFERROR(__xludf.DUMMYFUNCTION("IMPORTRANGE(""https://docs.google.com/spreadsheets/d/1yOpZnyZ5ouw2C51zn4VNSNmNNrizgIE5YAyno7ltBiE/edit"",""stock!A:Z"")"),"product_id") -> product_id | B1: =IFERROR(__xludf.DUMMYFUNCTION("""COMPUTED_VALUE"""),"new") -> new | C1: =IFERROR(__xludf.DUMMYFUNCTION("""COMPUTED_VALUE"""),"forecast_stock") -> forecast_stock | D1: =IFERROR(__xludf.DUMMYFUNCTION("""COMPUTED_VALUE"""),"stock") -> stock
A2: =IFERROR(__xludf.DUMMYFUNCTION("""COMPUTED_VALUE"""),112463.0) -> 112463 | B2: =IFERROR(__xludf.DUMMYFUNCTION("""COMPUTED_VALUE"""),0.0) -> 0 | C2: =IFERROR(__xludf.DUMMYFUNCTION("""COMPUTED_VALUE"""),320.0) -> 320 | D2: =IFERROR(__xludf.DUMMYFUNCTION("""COMPUTED_VALUE"""),320.0) -> 320
A3: =IFERROR(__xludf.DUMMYFUNCTION("""COMPUTED_VALUE"""),112481.0) -> 112481 | B3: =IFERROR(__xludf.DUMMYFUNCTION("""COMPUTED_VALUE"""),0.0) -> 0 | C3: =IFERROR(__xludf.DUMMYFUNCTION("""COMPUTED_VALUE"""),0.0) -> 0 | D3: =IFERROR(__xludf.DUMMYFUNCTION("""COMPUTED_VALUE"""),0.0) -> 0
A4: =IFERROR(__xludf.DUMMYFUNCTION("""COMPUTED_VALUE"""),13346.0) -> 13346 | B4: =IFERROR(__xludf.DUMMYFUNCTION("""COMPUTED_VALUE"""),1.0) -> 1 | C4: =IFERROR(__xludf.DUMMYFUNCTION("""COMPUTED_VALUE"""),100.0) -> 100 | D4: =IFERROR(__xludf.DUMMYFUNCTION("""COMPUTED_VALUE"""),100.0) -> 100
A5: =IFERROR(__xludf.DUMMYFUNCTION("""COMPUTED_VALUE"""),112454.0) -> 112454 | B5: =IFERROR(__xludf.DUMMYFUNCTION("""COMPUTED_VALUE"""),0.0) -> 0 | C5: =IFERROR(__xludf.DUMMYFUNCTION("""COMPUTED_VALUE"""),277.0) -> 277 | D5: =IFERROR(__xludf.DUMMYFUNCTION("""COMPUTED_VALUE"""),268.0) -> 268
A6: =IFERROR(__xludf.DUMMYFUNCTION("""COMPUTED_VALUE"""),112461.0) -> 112461 | B6: =IFERROR(__xludf.DUMMYFUNCTION("""COMPUTED_VALUE"""),0.0) -> 0 | C6: =IFERROR(__xludf.DUMMYFUNCTION("""COMPUTED_VALUE"""),971.0) -> 971 | D6: =IFERROR(__xludf.DUMMYFUNCTION("""COMPUTED_VALUE"""),472.0) -> 472
A7: =IFERROR(__xludf.DUMMYFUNCTION("""COMPUTED_VALUE"""),106532.0) -> 106532 | B7: =IFERROR(__xludf.DUMMYFUNCTION("""COMPUTED_VALUE"""),0.0) -> 0 | C7: =IFERROR(__xludf.DUMMYFUNCTION("""COMPUTED_VALUE"""),63.0) -> 63 | D7: =IFERROR(__xludf.DUMMYFUNCTION("""COMPUTED_VALUE"""),63.0) -> 63
A8: =IFERROR(__xludf.DUMMYFUNCTION("""COMPUTED_VALUE"""),121135.0) -> 121135 | B8: =IFERROR(__xludf.DUMMYFUNCTION("""COMPUTED_VALUE"""),1.0) -> 1 | C8: =IFERROR(__xludf.DUMMYFUNCTION("""COMPUTED_VALUE"""),40.0) -> 40 | D8: =IFERROR(__xludf.DUMMYFUNCTION("""COMPUTED_VALUE"""),33.0) -> 33
A9: =IFERROR(__xludf.DUMMYFUNCTION("""COMPUTED_VALUE"""),128362.0) -> 128362 | B9: =IFERROR(__xludf.DUMMYFUNCTION("""COMPUTED_VALUE"""),1.0) -> 1 | C9: =IFERROR(__xludf.DUMMYFUNCTION("""COMPUTED_VALUE"""),269.0) -> 269 | D9: =IFERROR(__xludf.DUMMYFUNCTION("""COMPUTED_VALUE"""),104.0) -> 104
A10: =IFERROR(__xludf.DUMMYFUNCTION("""COMPUTED_VALUE"""),71200.0) -> 71200 | B10: =IFERROR(__xludf.DUMMYFUNCTION("""COMPUTED_VALUE"""),0.0) -> 0 | C10: =IFERROR(__xludf.DUMMYFUNCTION("""COMPUTED_VALUE"""),164.0) -> 164 | D10: =IFERROR(__xludf.DUMMYFUNCTION("""COMPUTED_VALUE"""),152.0) -> 152
A11: =IFERROR(__xludf.DUMMYFUNCTION("""COMPUTED_VALUE"""),19812.0) -> 19812 | B11: =IFERROR(__xludf.DUMMYFUNCTION("""COMPUTED_VALUE"""),0.0) -> 0 | C11: =IFERROR(__xludf.DUMMYFUNCTION("""COMPUTED_VALUE"""),489.0) -> 489 | D11: =IFERROR(__xludf.DUMMYFUNCTION("""COMPUTED_VALUE"""),393.0) -> 393
A12: =IFERROR(__xludf.DUMMYFUNCTION("""COMPUTED_VALUE"""),122259.0) -> 122259 | B12: =IFERROR(__xludf.DUMMYFUNCTION("""COMPUTED_VALUE"""),1.0) -> 1 | C12: =IFERROR(__xludf.DUMMYFUNCTION("""COMPUTED_VALUE"""),104.0) -> 104 | D12: =IFERROR(__xludf.DUMMYFUNCTION("""COMPUTED_VALUE"""),104.0) -> 104
A13: =IFERROR(__xludf.DUMMYFUNCTION("""COMPUTED_VALUE"""),199526.0) -> 199526 | B13: =IFERROR(__xludf.DUMMYFUNCTION("""COMPUTED_VALUE"""),0.0) -> 0 | C13: =IFERROR(__xludf.DUMMYFUNCTION("""COMPUTED_VALUE"""),63.0) -> 63 | D13: =IFERROR(__xludf.DUMMYFUNCTION("""COMPUTED_VALUE"""),60.0) -> 60
A14: =IFERROR(__xludf.DUMMYFUNCTION("""COMPUTED_VALUE"""),140581.0) -> 140581 | B14: =IFERROR(__xludf.DUMMYFUNCTION("""COMPUTED_VALUE"""),0.0) -> 0 | C14: =IFERROR(__xludf.DUMMYFUNCTION("""COMPUTED_VALUE"""),14.0) -> 14 | D14: =IFERROR(__xludf.DUMMYFUNCTION("""COMPUTED_VALUE"""),9.0) -> 9
A15: =IFERROR(__xludf.DUMMYFUNCTION("""COMPUTED_VALUE"""),118383.0) -> 118383 | B15: =IFERROR(__xludf.DUMMYFUNCTION("""COMPUTED_VALUE"""),0.0) -> 0 | C15: =IFERROR(__xludf.DUMMYFUNCTION("""COMPUTED_VALUE"""),256.0) -> 256 | D15: =IFERROR(__xludf.DUMMYFUNCTION("""COMPUTED_VALUE"""),256.0) -> 256
A16: =IFERROR(__xludf.DUMMYFUNCTION("""COMPUTED_VALUE"""),122262.0) -> 122262 | B16: =IFERROR(__xludf.DUMMYFUNCTION("""COMPUTED_VALUE"""),0.0) -> 0 | C16: =IFERROR(__xludf.DUMMYFUNCTION("""COMPUTED_VALUE"""),326.0) -> 326 | D16: =IFERROR(__xludf.DUMMYFUNCTION("""COMPUTED_VALUE"""),326.0) -> 326
A17: =IFERROR(__xludf.DUMMYFUNCTION("""COMPUTED_VALUE"""),141879.0) -> 141879 | B17: =IFERROR(__xludf.DUMMYFUNCTION("""COMPUTED_VALUE"""),0.0) -> 0 | C17: =IFERROR(__xludf.DUMMYFUNCTION("""COMPUTED_VALUE"""),11.0) -> 11 | D17: =IFERROR(__xludf.DUMMYFUNCTION("""COMPUTED_VALUE"""),11.0) -> 11
A18: =IFERROR(__xludf.DUMMYFUNCTION("""COMPUTED_VALUE"""),19826.0) -> 19826 | B18: =IFERROR(__xludf.DUMMYFUNCTION("""COMPUTED_VALUE"""),0.0) -> 0 | C18: =IFERROR(__xludf.DUMMYFUNCTION("""COMPUTED_VALUE"""),210.0) -> 210 | D18: =IFERROR(__xludf.DUMMYFUNCTION("""COMPUTED_VALUE"""),103.0) -> 103
A19: =IFERROR(__xludf.DUMMYFUNCTION("""COMPUTED_VALUE"""),93039.0) -> 93039 | B19: =IFERROR(__xludf.DUMMYFUNCTION("""COMPUTED_VALUE"""),0.0) -> 0 | C19: =IFERROR(__xludf.DUMMYFUNCTION("""COMPUTED_VALUE"""),68.0) -> 68 | D19: =IFERROR(__xludf.DUMMYFUNCTION("""COMPUTED_VALUE"""),68.0) -> 68
A20: =IFERROR(__xludf.DUMMYFUNCTION("""COMPUTED_VALUE"""),128213.0) -> 128213 | B20: =IFERROR(__xludf.DUMMYFUNCTION("""COMPUTED_VALUE"""),0.0) -> 0 | C20: =IFERROR(__xludf.DUMMYFUNCTION("""COMPUTED_VALUE"""),318.0) -> 318 | D20: =IFERROR(__xludf.DUMMYFUNCTION("""COMPUTED_VALUE"""),162.0) -> 162
A21: =IFERROR(__xludf.DUMMYFUNCTION("""COMPUTED_VALUE"""),83797.0) -> 83797 | B21: =IFERROR(__xludf.DUMMYFUNCTION("""COMPUTED_VALUE"""),0.0) -> 0 | C21: =IFERROR(__xludf.DUMMYFUNCTION("""COMPUTED_VALUE"""),43.0) -> 43 | D21: =IFERROR(__xludf.DUMMYFUNCTION("""COMPUTED_VALUE"""),43.0) -> 43
A22: =IFERROR(__xludf.DUMMYFUNCTION("""COMPUTED_VALUE"""),19831.0) -> 19831 | B22: =IFERROR(__xludf.DUMMYFUNCTION("""COMPUTED_VALUE"""),0.0) -> 0 | C22: =IFERROR(__xludf.DUMMYFUNCTION("""COMPUTED_VALUE"""),185.0) -> 185 | D22: =IFERROR(__xludf.DUMMYFUNCTION("""COMPUTED_VALUE"""),134.0) -> 134
A23: =IFERROR(__xludf.DUMMYFUNCTION("""COMPUTED_VALUE"""),93025.0) -> 93025 | B23: =IFERROR(__xludf.DUMMYFUNCTION("""COMPUTED_VALUE"""),0.0) -> 0 | C23: =IFERROR(__xludf.DUMMYFUNCTION("""COMPUTED_VALUE"""),305.0) -> 305 | D23: =IFERROR(__xludf.DUMMYFUNCTION("""COMPUTED_VALUE"""),305.0) -> 305
A24: =IFERROR(__xludf.DUMMYFUNCTION("""COMPUTED_VALUE"""),81624.0) -> 81624 | B24: =IFERROR(__xludf.DUMMYFUNCTION("""COMPUTED_VALUE"""),1.0) -> 1 | C24: =IFERROR(__xludf.DUMMYFUNCTION("""COMPUTED_VALUE"""),84.0) -> 84 | D24: =IFERROR(__xludf.DUMMYFUNCTION("""COMPUTED_VALUE"""),84.0) -> 84
A25: =IFERROR(__xludf.DUMMYFUNCTION("""COMPUTED_VALUE"""),92913.0) -> 92913 | B25: =IFERROR(__xludf.DUMMYFUNCTION("""COMPUTED_VALUE"""),0.0) -> 0 | C25: =IFERROR(__xludf.DUMMYFUNCTION("""COMPUTED_VALUE"""),96.0) -> 96 | D25: =IFERROR(__xludf.DUMMYFUNCTION("""COMPUTED_VALUE"""),96.0) -> 96
A26: =IFERROR(__xludf.DUMMYFUNCTION("""COMPUTED_VALUE"""),126983.0) -> 126983 | B26: =IFERROR(__xludf.DUMMYFUNCTION("""COMPUTED_VALUE"""),0.0) -> 0 | C26: =IFERROR(__xludf.DUMMYFUNCTION("""COMPUTED_VALUE"""),176.0) -> 176 | D26: =IFERROR(__xludf.DUMMYFUNCTION("""COMPUTED_VALUE"""),71.0) -> 71
A27: =IFERROR(__xludf.DUMMYFUNCTION("""COMPUTED_VALUE"""),118226.0) -> 118226 | B27: =IFERROR(__xludf.DUMMYFUNCTION("""COMPUTED_VALUE"""),0.0) -> 0 | C27: =IFERROR(__xludf.DUMMYFUNCTION("""COMPUTED_VALUE"""),130.0) -> 130 | D27: =IFERROR(__xludf.DUMMYFUNCTION("""COMPUTED_VALUE"""),130.0) -> 130
A28: =IFERROR(__xludf.DUMMYFUNCTION("""COMPUTED_VALUE"""),48618.0) -> 48618 | B28: =IFERROR(__xludf.DUMMYFUNCTION("""COMPUTED_VALUE"""),1.0) -> 1 | C28: =IFERROR(__xludf.DUMMYFUNCTION("""COMPUTED_VALUE"""),84.0) -> 84 | D28: =IFERROR(__xludf.DUMMYFUNCTION("""COMPUTED_VALUE"""),84.0) -> 84
A29: =IFERROR(__xludf.DUMMYFUNCTION("""COMPUTED_VALUE"""),93037.0) -> 93037 | B29: =IFERROR(__xludf.DUMMYFUNCTION("""COMPUTED_VALUE"""),0.0) -> 0 | C29: =IFERROR(__xludf.DUMMYFUNCTION("""COMPUTED_VALUE"""),604.0) -> 604 | D29: =IFERROR(__xludf.DUMMYFUNCTION("""COMPUTED_VALUE"""),604.0) -> 604
A30: =IFERROR(__xludf.DUMMYFUNCTION("""COMPUTED_VALUE"""),126984.0) -> 126984 | B30: =IFERROR(__xludf.DUMMYFUNCTION("""COMPUTED_VALUE"""),0.0) -> 0 | C30: =IFERROR(__xludf.DUMMYFUNCTION("""COMPUTED_VALUE"""),26.0) -> 26 | D30: =IFERROR(__xludf.DUMMYFUNCTION("""COMPUTED_VALUE"""),6.0) -> 6
A31: =IFERROR(__xludf.DUMMYFUNCTION("""COMPUTED_VALUE"""),47393.0) -> 47393 | B31: =IFERROR(__xludf.DUMMYFUNCTION("""COMPUTED_VALUE"""),0.0) -> 0 | C31: =IFERROR(__xludf.DUMMYFUNCTION("""COMPUTED_VALUE"""),982.0) -> 982 | D31: =IFERROR(__xludf.DUMMYFUNCTION("""COMPUTED_VALUE"""),609.0) -> 609
A32: =IFERROR(__xludf.DUMMYFUNCTION("""COMPUTED_VALUE"""),128214.0) -> 128214 | B32: =IFERROR(__xludf.DUMMYFUNCTION("""COMPUTED_VALUE"""),0.0) -> 0 | C32: =IFERROR(__xludf.DUMMYFUNCTION("""COMPUTED_VALUE"""),79.0) -> 79 | D32: =IFERROR(__xludf.DUMMYFUNCTION("""COMPUTED_VALUE"""),79.0) -> 79
A33: =IFERROR(__xludf.DUMMYFUNCTION("""COMPUTED_VALUE"""),83802.0) -> 83802 | B33: =IFERROR(__xludf.DUMMYFUNCTION("""COMPUTED_VALUE"""),0.0) -> 0 | C33: =IFERROR(__xludf.DUMMYFUNCTION("""COMPUTED_VALUE"""),31.0) -> 31 | D33: =IFERROR(__xludf.DUMMYFUNCTION("""COMPUTED_VALUE"""),23.0) -> 23
A34: =IFERROR(__xludf.DUMMYFUNCTION("""COMPUTED_VALUE"""),48625.0) -> 48625 | B34: =IFERROR(__xludf.DUMMYFUNCTION("""COMPUTED_VALUE"""),1.0) -> 1 | C34: =IFERROR(__xludf.DUMMYFUNCTION("""COMPUTED_VALUE"""),96.0) -> 96 | D34: =IFERROR(__xludf.DUMMYFUNCTION("""COMPUTED_VALUE"""),96.0) -> 96
A35: =IFERROR(__xludf.DUMMYFUNCTION("""COMPUTED_VALUE"""),83602.0) -> 83602 | B35: =IFERROR(__xludf.DUMMYFUNCTION("""COMPUTED_VALUE"""),0.0) -> 0 | C35: =IFERROR(__xludf.DUMMYFUNCTION("""COMPUTED_VALUE"""),79.0) -> 79 | D35: =IFERROR(__xludf.DUMMYFUNCTION("""COMPUTED_VALUE"""),79.0) -> 79
A36: =IFERROR(__xludf.DUMMYFUNCTION("""COMPUTED_VALUE"""),98867.0) -> 98867 | B36: =IFERROR(__xludf.DUMMYFUNCTION("""COMPUTED_VALUE"""),0.0) -> 0 | C36: =IFERROR(__xludf.DUMMYFUNCTION("""COMPUTED_VALUE"""),186.0) -> 186 | D36: =IFERROR(__xludf.DUMMYFUNCTION("""COMPUTED_VALUE"""),186.0) -> 186
A37: =IFERROR(__xludf.DUMMYFUNCTION("""COMPUTED_VALUE"""),127042.0) -> 127042 | B37: =IFERROR(__xludf.DUMMYFUNCTION("""COMPUTED_VALUE"""),0.0) -> 0 | C37: =IFERROR(__xludf.DUMMYFUNCTION("""COMPUTED_VALUE"""),418.0) -> 418 | D37: =IFERROR(__xludf.DUMMYFUNCTION("""COMPUTED_VALUE"""),418.0) -> 418
A38: =IFERROR(__xludf.DUMMYFUNCTION("""COMPUTED_VALUE"""),127241.0) -> 127241 | B38: =IFERROR(__xludf.DUMMYFUNCTION("""COMPUTED_VALUE"""),0.0) -> 0 | C38: =IFERROR(__xludf.DUMMYFUNCTION("""COMPUTED_VALUE"""),98.0) -> 98 | D38: =IFERROR(__xludf.DUMMYFUNCTION("""COMPUTED_VALUE"""),98.0) -> 98
A39: =IFERROR(__xludf.DUMMYFUNCTION("""COMPUTED_VALUE"""),118220.0) -> 118220 | B39: =IFERROR(__xludf.DUMMYFUNCTION("""COMPUTED_VALUE"""),0.0) -> 0 | C39: =IFERROR(__xludf.DUMMYFUNCTION("""COMPUTED_VALUE"""),34.0) -> 34 | D39: =IFERROR(__xludf.DUMMYFUNCTION("""COMPUTED_VALUE"""),34.0) -> 34
A40: =IFERROR(__xludf.DUMMYFUNCTION("""COMPUTED_VALUE"""),128216.0) -> 128216 | B40: =IFERROR(__xludf.DUMMYFUNCTION("""COMPUTED_VALUE"""),0.0) -> 0 | C40: =IFERROR(__xludf.DUMMYFUNCTION("""COMPUTED_VALUE"""),141.0) -> 141 | D40: =IFERROR(__xludf.DUMMYFUNCTION("""COMPUTED_VALUE"""),141.0) -> 141
A41: =IFERROR(__xludf.DUMMYFUNCTION("""COMPUTED_VALUE"""),93049.0) -> 93049 | B41: =IFERROR(__xludf.DUMMYFUNCTION("""COMPUTED_VALUE"""),0.0) -> 0 | C41: =IFERROR(__xludf.DUMMYFUNCTION("""COMPUTED_VALUE"""),34.0) -> 34 | D41: =IFERROR(__xludf.DUMMYFUNCTION("""COMPUTED_VALUE"""),34.0) -> 34
A42: =IFERROR(__xludf.DUMMYFUNCTION("""COMPUTED_VALUE"""),118216.0) -> 118216 | B42: =IFERROR(__xludf.DUMMYFUNCTION("""COMPUTED_VALUE"""),0.0) -> 0 | C42: =IFERROR(__xludf.DUMMYFUNCTION("""COMPUTED_VALUE"""),0.0) -> 0 | D42: =IFERROR(__xludf.DUMMYFUNCTION("""COMPUTED_VALUE"""),0.0) -> 0
A43: =IFERROR(__xludf.DUMMYFUNCTION("""COMPUTED_VALUE"""),118221.0) -> 118221 | B43: =IFERROR(__xludf.DUMMYFUNCTION("""COMPUTED_VALUE"""),1.0) -> 1 | C43: =IFERROR(__xludf.DUMMYFUNCTION("""COMPUTED_VALUE"""),99.0) -> 99 | D43: =IFERROR(__xludf.DUMMYFUNCTION("""COMPUTED_VALUE"""),99.0) -> 99
A44: =IFERROR(__xludf.DUMMYFUNCTION("""COMPUTED_VALUE"""),92900.0) -> 92900 | B44: =IFERROR(__xludf.DUMMYFUNCTION("""COMPUTED_VALUE"""),0.0) -> 0 | C44: =IFERROR(__xludf.DUMMYFUNCTION("""COMPUTED_VALUE"""),167.0) -> 167 | D44: =IFERROR(__xludf.DUMMYFUNCTION("""COMPUTED_VALUE"""),131.0) -> 131
A45: =IFERROR(__xludf.DUMMYFUNCTION("""COMPUTED_VALUE"""),118215.0) -> 118215 | B45: =IFERROR(__xludf.DUMMYFUNCTION("""COMPUTED_VALUE"""),1.0) -> 1 | C45: =IFERROR(__xludf.DUMMYFUNCTION("""COMPUTED_VALUE"""),100.0) -> 100 | D45: =IFERROR(__xludf.DUMMYFUNCTION("""COMPUTED_VALUE"""),46.0) -> 46
A46: =IFERROR(__xludf.DUMMYFUNCTION("""COMPUTED_VALUE"""),19832.0) -> 19832 | B46: =IFERROR(__xludf.DUMMYFUNCTION("""COMPUTED_VALUE"""),1.0) -> 1 | C46: =IFERROR(__xludf.DUMMYFUNCTION("""COMPUTED_VALUE"""),594.0) -> 594 | D46: =IFERROR(__xludf.DUMMYFUNCTION("""COMPUTED_VALUE"""),558.0) -> 558
A47: =IFERROR(__xludf.DUMMYFUNCTION("""COMPUTED_VALUE"""),93071.0) -> 93071 | B47: =IFERROR(__xludf.DUMMYFUNCTION("""COMPUTED_VALUE"""),1.0) -> 1 | C47: =IFERROR(__xludf.DUMMYFUNCTION("""COMPUTED_VALUE"""),199.0) -> 199 | D47: =IFERROR(__xludf.DUMMYFUNCTION("""COMPUTED_VALUE"""),19.0) -> 19
A48: =IFERROR(__xludf.DUMMYFUNCTION("""COMPUTED_VALUE"""),122395.0) -> 122395 | B48: =IFERROR(__xludf.DUMMYFUNCTION("""COMPUTED_VALUE"""),1.0) -> 1 | C48: =IFERROR(__xludf.DUMMYFUNCTION("""COMPUTED_VALUE"""),76.0) -> 76 | D48: =IFERROR(__xludf.DUMMYFUNCTION("""COMPUTED_VALUE"""),2.0) -> 2
A49: =IFERROR(__xludf.DUMMYFUNCTION("""COMPUTED_VALUE"""),116946.0) -> 116946 | B49: =IFERROR(__xludf.DUMMYFUNCTION("""COMPUTED_VALUE"""),1.0) -> 1 | C49: =IFERROR(__xludf.DUMMYFUNCTION("""COMPUTED_VALUE"""),144.0) -> 144 | D49: =IFERROR(__xludf.DUMMYFUNCTION("""COMPUTED_VALUE"""),85.0) -> 85
A50: =IFERROR(__xludf.DUMMYFUNCTION("""COMPUTED_VALUE"""),97538.0) -> 97538 | B50: =IFERROR(__xludf.DUMMYFUNCTION("""COMPUTED_VALUE"""),1.0) -> 1 | C50: =IFERROR(__xludf.DUMMYFUNCTION("""COMPUTED_VALUE"""),135.0) -> 135 | D50: =IFERROR(__xludf.DUMMYFUNCTION("""COMPUTED_VALUE"""),82.0) -> 82
A51: =IFERROR(__xludf.DUMMYFUNCTION("""COMPUTED_VALUE"""),127238.0) -> 127238 | B51: =IFERROR(__xludf.DUMMYFUNCTION("""COMPUTED_VALUE"""),1.0) -> 1 | C51: =IFERROR(__xludf.DUMMYFUNCTION("""COMPUTED_VALUE"""),147.0) -> 147 | D51: =IFERROR(__xludf.DUMMYFUNCTION("""COMPUTED_VALUE"""),88.0) -> 88
A52: =IFERROR(__xludf.DUMMYFUNCTION("""COMPUTED_VALUE"""),81646.0) -> 81646 | B52: =IFERROR(__xludf.DUMMYFUNCTION("""COMPUTED_VALUE"""),1.0) -> 1 | C52: =IFERROR(__xludf.DUMMYFUNCTION("""COMPUTED_VALUE"""),399.0) -> 399 | D52: =IFERROR(__xludf.DUMMYFUNCTION("""COMPUTED_VALUE"""),159.0) -> 159
A53: =IFERROR(__xludf.DUMMYFUNCTION("""COMPUTED_VALUE"""),81643.0) -> 81643 | B53: =IFERROR(__xludf.DUMMYFUNCTION("""COMPUTED_VALUE"""),1.0) -> 1 | C53: =IFERROR(__xludf.DUMMYFUNCTION("""COMPUTED_VALUE"""),927.0) -> 927 | D53: =IFERROR(__xludf.DUMMYFUNCTION("""COMPUTED_VALUE"""),301.0) -> 301
A54: =IFERROR(__xludf.DUMMYFUNCTION("""COMPUTED_VALUE"""),128215.0) -> 128215 | B54: =IFERROR(__xludf.DUMMYFUNCTION("""COMPUTED_VALUE"""),1.0) -> 1 | C54: =IFERROR(__xludf.DUMMYFUNCTION("""COMPUTED_VALUE"""),389.0) -> 389 | D54: =IFERROR(__xludf.DUMMYFUNCTION("""COMPUTED_VALUE"""),243.0) -> 243
A55: =IFERROR(__xludf.DUMMYFUNCTION("""COMPUTED_VALUE"""),108022.0) -> 108022 | B55: =IFERROR(__xludf.DUMMYFUNCTION("""COMPUTED_VALUE"""),1.0) -> 1 | C55: =IFERROR(__xludf.DUMMYFUNCTION("""COMPUTED_VALUE"""),455.0) -> 455 | D55: =IFERROR(__xludf.DUMMYFUNCTION("""COMPUTED_VALUE"""),285.0) -> 285
A56: =IFERROR(__xludf.DUMMYFUNCTION("""COMPUTED_VALUE"""),81647.0) -> 81647 | B56: =IFERROR(__xludf.DUMMYFUNCTION("""COMPUTED_VALUE"""),0.0) -> 0 | C56: =IFERROR(__xludf.DUMMYFUNCTION("""COMPUTED_VALUE"""),547.0) -> 547 | D56: =IFERROR(__xludf.DUMMYFUNCTION("""COMPUTED_VALUE"""),227.0) -> 227
A57: =IFERROR(__xludf.DUMMYFUNCTION("""COMPUTED_VALUE"""),83603.0) -> 83603 | B57: =IFERROR(__xludf.DUMMYFUNCTION("""COMPUTED_VALUE"""),1.0) -> 1 | C57: =IFERROR(__xludf.DUMMYFUNCTION("""COMPUTED_VALUE"""),870.0) -> 870 | D57: =IFERROR(__xludf.DUMMYFUNCTION("""COMPUTED_VALUE"""),105.0) -> 105
A58: =IFERROR(__xludf.DUMMYFUNCTION("""COMPUTED_VALUE"""),118219.0) -> 118219 | B58: =IFERROR(__xludf.DUMMYFUNCTION("""COMPUTED_VALUE"""),1.0) -> 1 | C58: =IFERROR(__xludf.DUMMYFUNCTION("""COMPUTED_VALUE"""),397.0) -> 397 | D58: =IFERROR(__xludf.DUMMYFUNCTION("""COMPUTED_VALUE"""),207.0) -> 207
A59: =IFERROR(__xludf.DUMMYFUNCTION("""COMPUTED_VALUE"""),120952.0) -> 120952 | B59: =IFERROR(__xludf.DUMMYFUNCTION("""COMPUTED_VALUE"""),1.0) -> 1 | C59: =IFERROR(__xludf.DUMMYFUNCTION("""COMPUTED_VALUE"""),134.0) -> 134 | D59: =IFERROR(__xludf.DUMMYFUNCTION("""COMPUTED_VALUE"""),78.0) -> 78
A60: =IFERROR(__xludf.DUMMYFUNCTION("""COMPUTED_VALUE"""),81658.0) -> 81658 | B60: =IFERROR(__xludf.DUMMYFUNCTION("""COMPUTED_VALUE"""),1.0) -> 1 | C60: =IFERROR(__xludf.DUMMYFUNCTION("""COMPUTED_VALUE"""),685.0) -> 685 | D60: =IFERROR(__xludf.DUMMYFUNCTION("""COMPUTED_VALUE"""),42.0) -> 42
A61: =IFERROR(__xludf.DUMMYFUNCTION("""COMPUTED_VALUE"""),93047.0) -> 93047 | B61: =IFERROR(__xludf.DUMMYFUNCTION("""COMPUTED_VALUE"""),0.0) -> 0 | C61: =IFERROR(__xludf.DUMMYFUNCTION("""COMPUTED_VALUE"""),525.0) -> 525 | D61: =IFERROR(__xludf.DUMMYFUNCTION("""COMPUTED_VALUE"""),306.0) -> 306
A62: =IFERROR(__xludf.DUMMYFUNCTION("""COMPUTED_VALUE"""),83807.0) -> 83807 | B62: =IFERROR(__xludf.DUMMYFUNCTION("""COMPUTED_VALUE"""),1.0) -> 1 | C62: =IFERROR(__xludf.DUMMYFUNCTION("""COMPUTED_VALUE"""),596.0) -> 596 | D62: =IFERROR(__xludf.DUMMYFUNCTION("""COMPUTED_VALUE"""),321.0) -> 321
A63: =IFERROR(__xludf.DUMMYFUNCTION("""COMPUTED_VALUE"""),92915.0) -> 92915 | B63: =IFERROR(__xludf.DUMMYFUNCTION("""COMPUTED_VALUE"""),0.0) -> 0 | C63: =IFERROR(__xludf.DUMMYFUNCTION("""COMPUTED_VALUE"""),861.0) -> 861 | D63: =IFERROR(__xludf.DUMMYFUNCTION("""COMPUTED_VALUE"""),576.0) -> 576
A64: =IFERROR(__xludf.DUMMYFUNCTION("""COMPUTED_VALUE"""),81653.0) -> 81653 | B64: =IFERROR(__xludf.DUMMYFUNCTION("""COMPUTED_VALUE"""),0.0) -> 0 | C64: =IFERROR(__xludf.DUMMYFUNCTION("""COMPUTED_VALUE"""),64.0) -> 64 | D64: =IFERROR(__xludf.DUMMYFUNCTION("""COMPUTED_VALUE"""),31.0) -> 31
A65: =IFERROR(__xludf.DUMMYFUNCTION("""COMPUTED_VALUE"""),81618.0) -> 81618 | B65: =IFERROR(__xludf.DUMMYFUNCTION("""COMPUTED_VALUE"""),1.0) -> 1 | C65: =IFERROR(__xludf.DUMMYFUNCTION("""COMPUTED_VALUE"""),124.0) -> 124 | D65: =IFERROR(__xludf.DUMMYFUNCTION("""COMPUTED_VALUE"""),37.0) -> 37
A66: =IFERROR(__xludf.DUMMYFUNCTION("""COMPUTED_VALUE"""),118241.0) -> 118241 | B66: =IFERROR(__xludf.DUMMYFUNCTION("""COMPUTED_VALUE"""),1.0) -> 1 | C66: =IFERROR(__xludf.DUMMYFUNCTION("""COMPUTED_VALUE"""),897.0) -> 897 | D66: =IFERROR(__xludf.DUMMYFUNCTION("""COMPUTED_VALUE"""),1.0) -> 1
A67: =IFERROR(__xludf.DUMMYFUNCTION("""COMPUTED_VALUE"""),48634.0) -> 48634 | B67: =IFERROR(__xludf.DUMMYFUNCTION("""COMPUTED_VALUE"""),1.0) -> 1 | C67: =IFERROR(__xludf.DUMMYFUNCTION("""COMPUTED_VALUE"""),832.0) -> 832 | D67: =IFERROR(__xludf.DUMMYFUNCTION("""COMPUTED_VALUE"""),180.0) -> 180
A68: =IFERROR(__xludf.DUMMYFUNCTION("""COMPUTED_VALUE"""),48636.0) -> 48636 | B68: =IFERROR(__xludf.DUMMYFUNCTION("""COMPUTED_VALUE"""),1.0) -> 1 | C68: =IFERROR(__xludf.DUMMYFUNCTION("""COMPUTED_VALUE"""),37.0) -> 37 | D68: =IFERROR(__xludf.DUMMYFUNCTION("""COMPUTED_VALUE"""),10.0) -> 10
A69: =IFERROR(__xludf.DUMMYFUNCTION("""COMPUTED_VALUE"""),48629.0) -> 48629 | B69: =IFERROR(__xludf.DUMMYFUNCTION("""COMPUTED_VALUE"""),1.0) -> 1 | C69: =IFERROR(__xludf.DUMMYFUNCTION("""COMPUTED_VALUE"""),935.0) -> 935 | D69: =IFERROR(__xludf.DUMMYFUNCTION("""COMPUTED_VALUE"""),635.0) -> 635
A70: =IFERROR(__xludf.DUMMYFUNCTION("""COMPUTED_VALUE"""),47400.0) -> 47400 | B70: =IFERROR(__xludf.DUMMYFUNCTION("""COMPUTED_VALUE"""),1.0) -> 1 | C70: =IFERROR(__xludf.DUMMYFUNCTION("""COMPUTED_VALUE"""),868.0) -> 868 | D70: =IFERROR(__xludf.DUMMYFUNCTION("""COMPUTED_VALUE"""),396.0) -> 396
A71: =IFERROR(__xludf.DUMMYFUNCTION("""COMPUTED_VALUE"""),111237.0) -> 111237 | B71: =IFERROR(__xludf.DUMMYFUNCTION("""COMPUTED_VALUE"""),0.0) -> 0 | C71: =IFERROR(__xludf.DUMMYFUNCTION("""COMPUTED_VALUE"""),445.0) -> 445 | D71: =IFERROR(__xludf.DUMMYFUNCTION("""COMPUTED_VALUE"""),128.0) -> 128
A72: =IFERROR(__xludf.DUMMYFUNCTION("""COMPUTED_VALUE"""),18042.0) -> 18042 | B72: =IFERROR(__xludf.DUMMYFUNCTION("""COMPUTED_VALUE"""),0.0) -> 0 | C72: =IFERROR(__xludf.DUMMYFUNCTION("""COMPUTED_VALUE"""),232.0) -> 232 | D72: =IFERROR(__xludf.DUMMYFUNCTION("""COMPUTED_VALUE"""),214.0) -> 214
A73: =IFERROR(__xludf.DUMMYFUNCTION("""COMPUTED_VALUE"""),114978.0) -> 114978 | B73: =IFERROR(__xludf.DUMMYFUNCTION("""COMPUTED_VALUE"""),0.0) -> 0 | C73: =IFERROR(__xludf.DUMMYFUNCTION("""COMPUTED_VALUE"""),315.0) -> 315 | D73: =IFERROR(__xludf.DUMMYFUNCTION("""COMPUTED_VALUE"""),278.0) -> 278
A74: =IFERROR(__xludf.DUMMYFUNCTION("""COMPUTED_VALUE"""),82980.0) -> 82980 | B74: =IFERROR(__xludf.DUMMYFUNCTION("""COMPUTED_VALUE"""),1.0) -> 1 | C74: =IFERROR(__xludf.DUMMYFUNCTION("""COMPUTED_VALUE"""),356.0) -> 356 | D74: =IFERROR(__xludf.DUMMYFUNCTION("""COMPUTED_VALUE"""),164.0) -> 164
A75: =IFERROR(__xludf.DUMMYFUNCTION("""COMPUTED_VALUE"""),83093.0) -> 83093 | B75: =IFERROR(__xludf.DUMMYFUNCTION("""COMPUTED_VALUE"""),0.0) -> 0 | C75: =IFERROR(__xludf.DUMMYFUNCTION("""COMPUTED_VALUE"""),442.0) -> 442 | D75: =IFERROR(__xludf.DUMMYFUNCTION("""COMPUTED_VALUE"""),385.0) -> 385
A76: =IFERROR(__xludf.DUMMYFUNCTION("""COMPUTED_VALUE"""),18134.0) -> 18134 | B76: =IFERROR(__xludf.DUMMYFUNCTION("""COMPUTED_VALUE"""),0.0) -> 0 | C76: =IFERROR(__xludf.DUMMYFUNCTION("""COMPUTED_VALUE"""),492.0) -> 492 | D76: =IFERROR(__xludf.DUMMYFUNCTION("""COMPUTED_VALUE"""),381.0) -> 381
A77: =IFERROR(__xludf.DUMMYFUNCTION("""COMPUTED_VALUE"""),107857.0) -> 107857 | B77: =IFERROR(__xludf.DUMMYFUNCTION("""COMPUTED_VALUE"""),0.0) -> 0 | C77: =IFERROR(__xludf.DUMMYFUNCTION("""COMPUTED_VALUE"""),645.0) -> 645 | D77: =IFERROR(__xludf.DUMMYFUNCTION("""COMPUTED_VALUE"""),327.0) -> 327
A78: =IFERROR(__xludf.DUMMYFUNCTION("""COMPUTED_VALUE"""),18136.0) -> 18136 | B78: =IFERROR(__xludf.DUMMYFUNCTION("""COMPUTED_VALUE"""),1.0) -> 1 | C78: =IFERROR(__xludf.DUMMYFUNCTION("""COMPUTED_VALUE"""),863.0) -> 863 | D78: =IFERROR(__xludf.DUMMYFUNCTION("""COMPUTED_VALUE"""),821.0) -> 821
A79: =IFERROR(__xludf.DUMMYFUNCTION("""COMPUTED_VALUE"""),69138.0) -> 69138 | B79: =IFERROR(__xludf.DUMMYFUNCTION("""COMPUTED_VALUE"""),1.0) -> 1 | C79: =IFERROR(__xludf.DUMMYFUNCTION("""COMPUTED_VALUE"""),43.0) -> 43 | D79: =IFERROR(__xludf.DUMMYFUNCTION("""COMPUTED_VALUE"""),27.0) -> 27
A80: =IFERROR(__xludf.DUMMYFUNCTION("""COMPUTED_VALUE"""),74828.0) -> 74828 | B80: =IFERROR(__xludf.DUMMYFUNCTION("""COMPUTED_VALUE"""),0.0) -> 0 | C80: =IFERROR(__xludf.DUMMYFUNCTION("""COMPUTED_VALUE"""),654.0) -> 654 | D80: =IFERROR(__xludf.DUMMYFUNCTION("""COMPUTED_VALUE"""),613.0) -> 613
A81: =IFERROR(__xludf.DUMMYFUNCTION("""COMPUTED_VALUE"""),74884.0) -> 74884 | B81: =IFERROR(__xludf.DUMMYFUNCTION("""COMPUTED_VALUE"""),1.0) -> 1 | C81: =IFERROR(__xludf.DUMMYFUNCTION("""COMPUTED_VALUE"""),2.0) -> 2 | D81: =IFERROR(__xludf.DUMMYFUNCTION("""COMPUTED_VALUE"""),2.0) -> 2
A82: =IFERROR(__xludf.DUMMYFUNCTION("""COMPUTED_VALUE"""),127232.0) -> 127232 | B82: =IFERROR(__xludf.DUMMYFUNCTION("""COMPUTED_VALUE"""),1.0) -> 1 | C82: =IFERROR(__xludf.DUMMYFUNCTION("""COMPUTED_VALUE"""),705.0) -> 705 | D82: =IFERROR(__xludf.DUMMYFUNCTION("""COMPUTED_VALUE"""),648.0) -> 648
A83: =IFERROR(__xludf.DUMMYFUNCTION("""COMPUTED_VALUE"""),82979.0) -> 82979 | B83: =IFERROR(__xludf.DUMMYFUNCTION("""COMPUTED_VALUE"""),1.0) -> 1 | C83: =IFERROR(__xludf.DUMMYFUNCTION("""COMPUTED_VALUE"""),774.0) -> 774 | D83: =IFERROR(__xludf.DUMMYFUNCTION("""COMPUTED_VALUE"""),723.0) -> 723
A84: =IFERROR(__xludf.DUMMYFUNCTION("""COMPUTED_VALUE"""),18138.0) -> 18138 | B84: =IFERROR(__xludf.DUMMYFUNCTION("""COMPUTED_VALUE"""),0.0) -> 0 | C84: =IFERROR(__xludf.DUMMYFUNCTION("""COMPUTED_VALUE"""),571.0) -> 571 | D84: =IFERROR(__xludf.DUMMYFUNCTION("""COMPUTED_VALUE"""),353.0) -> 353
A85: =IFERROR(__xludf.DUMMYFUNCTION("""COMPUTED_VALUE"""),127003.0) -> 127003 | B85: =IFERROR(__xludf.DUMMYFUNCTION("""COMPUTED_VALUE"""),0.0) -> 0 | C85: =IFERROR(__xludf.DUMMYFUNCTION("""COMPUTED_VALUE"""),735.0) -> 735 | D85: =IFERROR(__xludf.DUMMYFUNCTION("""COMPUTED_VALUE"""),384.0) -> 384
A86: =IFERROR(__xludf.DUMMYFUNCTION("""COMPUTED_VALUE"""),6036.0) -> 6036 | B86: =IFERROR(__xludf.DUMMYFUNCTION("""COMPUTED_VALUE"""),1.0) -> 1 | C86: =IFERROR(__xludf.DUMMYFUNCTION("""COMPUTED_VALUE"""),429.0) -> 429 | D86: =IFERROR(__xludf.DUMMYFUNCTION("""COMPUTED_VALUE"""),420.0) -> 420
A87: =IFERROR(__xludf.DUMMYFUNCTION("""COMPUTED_VALUE"""),6046.0) -> 6046 | B87: =IFERROR(__xludf.DUMMYFUNCTION("""COMPUTED_VALUE"""),0.0) -> 0 | C87: =IFERROR(__xludf.DUMMYFUNCTION("""COMPUTED_VALUE"""),732.0) -> 732 | D87: =IFERROR(__xludf.DUMMYFUNCTION("""COMPUTED_VALUE"""),319.0) -> 319
A88: =IFERROR(__xludf.DUMMYFUNCTION("""COMPUTED_VALUE"""),6037.0) -> 6037 | B88: =IFERROR(__xludf.DUMMYFUNCTION("""COMPUTED_VALUE"""),0.0) -> 0 | C88: =IFERROR(__xludf.DUMMYFUNCTION("""COMPUTED_VALUE"""),271.0) -> 271 | D88: =IFERROR(__xludf.DUMMYFUNCTION("""COMPUTED_VALUE"""),227.0) -> 227
A89: =IFERROR(__xludf.DUMMYFUNCTION("""COMPUTED_VALUE"""),6026.0) -> 6026 | B89: =IFERROR(__xludf.DUMMYFUNCTION("""COMPUTED_VALUE"""),1.0) -> 1 | C89: =IFERROR(__xludf.DUMMYFUNCTION("""COMPUTED_VALUE"""),111.0) -> 111 | D89: =IFERROR(__xludf.DUMMYFUNCTION("""COMPUTED_VALUE"""),23.0) -> 23
A90: =IFERROR(__xludf.DUMMYFUNCTION("""COMPUTED_VALUE"""),47431.0) -> 47431 | B90: =IFERROR(__xludf.DUMMYFUNCTION("""COMPUTED_VALUE"""),0.0) -> 0 | C90: =IFERROR(__xludf.DUMMYFUNCTION("""COMPUTED_VALUE"""),81.0) -> 81 | D90: =IFERROR(__xludf.DUMMYFUNCTION("""COMPUTED_VALUE"""),6.0) -> 6
A91: =IFERROR(__xludf.DUMMYFUNCTION("""COMPUTED_VALUE"""),82914.0) -> 82914 | B91: =IFERROR(__xludf.DUMMYFUNCTION("""COMPUTED_VALUE"""),1.0) -> 1 | C91: =IFERROR(__xludf.DUMMYFUNCTION("""COMPUTED_VALUE"""),486.0) -> 486 | D91: =IFERROR(__xludf.DUMMYFUNCTION("""COMPUTED_VALUE"""),345.0) -> 345
A92: =IFERROR(__xludf.DUMMYFUNCTION("""COMPUTED_VALUE"""),6044.0) -> 6044 | B92: =IFERROR(__xludf.DUMMYFUNCTION("""COMPUTED_VALUE"""),1.0) -> 1 | C92: =IFERROR(__xludf.DUMMYFUNCTION("""COMPUTED_VALUE"""),197.0) -> 197 | D92: =IFERROR(__xludf.DUMMYFUNCTION("""COMPUTED_VALUE"""),167.0) -> 167
A93: =IFERROR(__xludf.DUMMYFUNCTION("""COMPUTED_VALUE"""),82913.0) -> 82913 | B93: =IFERROR(__xludf.DUMMYFUNCTION("""COMPUTED_VALUE"""),1.0) -> 1 | C93: =IFERROR(__xludf.DUMMYFUNCTION("""COMPUTED_VALUE"""),196.0) -> 196 | D93: =IFERROR(__xludf.DUMMYFUNCTION("""COMPUTED_VALUE"""),116.0) -> 116
A94: =IFERROR(__xludf.DUMMYFUNCTION("""COMPUTED_VALUE"""),82922.0) -> 82922 | B94: =IFERROR(__xludf.DUMMYFUNCTION("""COMPUTED_VALUE"""),1.0) -> 1 | C94: =IFERROR(__xludf.DUMMYFUNCTION("""COMPUTED_VALUE"""),783.0) -> 783 | D94: =IFERROR(__xludf.DUMMYFUNCTION("""COMPUTED_VALUE"""),107.0) -> 107
A95: =IFERROR(__xludf.DUMMYFUNCTION("""COMPUTED_VALUE"""),6045.0) -> 6045 | B95: =IFERROR(__xludf.DUMMYFUNCTION("""COMPUTED_VALUE"""),1.0) -> 1 | C95: =IFERROR(__xludf.DUMMYFUNCTION("""COMPUTED_VALUE"""),0.0) -> 0 | D95: =IFERROR(__xludf.DUMMYFUNCTION("""COMPUTED_VALUE"""),0.0) -> 0
A96: =IFERROR(__xludf.DUMMYFUNCTION("""COMPUTED_VALUE"""),6027.0) -> 6027 | B96: =IFERROR(__xludf.DUMMYFUNCTION("""COMPUTED_VALUE"""),0.0) -> 0 | C96: =IFERROR(__xludf.DUMMYFUNCTION("""COMPUTED_VALUE"""),282.0) -> 282 | D96: =IFERROR(__xludf.DUMMYFUNCTION("""COMPUTED_VALUE"""),174.0) -> 174
A97: =IFERROR(__xludf.DUMMYFUNCTION("""COMPUTED_VALUE"""),97088.0) -> 97088 | B97: =IFERROR(__xludf.DUMMYFUNCTION("""COMPUTED_VALUE"""),1.0) -> 1 | C97: =IFERROR(__xludf.DUMMYFUNCTION("""COMPUTED_VALUE"""),356.0) -> 356 | D97: =IFERROR(__xludf.DUMMYFUNCTION("""COMPUTED_VALUE"""),290.0) -> 290
A98: =IFERROR(__xludf.DUMMYFUNCTION("""COMPUTED_VALUE"""),122235.0) -> 122235 | B98: =IFERROR(__xludf.DUMMYFUNCTION("""COMPUTED_VALUE"""),1.0) -> 1 | C98: =IFERROR(__xludf.DUMMYFUNCTION("""COMPUTED_VALUE"""),941.0) -> 941 | D98: =IFERROR(__xludf.DUMMYFUNCTION("""COMPUTED_VALUE"""),126.0) -> 126
A99: =IFERROR(__xludf.DUMMYFUNCTION("""COMPUTED_VALUE"""),119887.0) -> 119887 | B99: =IFERROR(__xludf.DUMMYFUNCTION("""COMPUTED_VALUE"""),1.0) -> 1 | C99: =IFERROR(__xludf.DUMMYFUNCTION("""COMPUTED_VALUE"""),732.0) -> 732 | D99: =IFERROR(__xludf.DUMMYFUNCTION("""COMPUTED_VALUE"""),498.0) -> 498
A100: =IFERROR(__xludf.DUMMYFUNCTION("""COMPUTED_VALUE"""),97980.0) -> 97980 | B100: =IFERROR(__xludf.DUMMYFUNCTION("""COMPUTED_VALUE"""),0.0) -> 0 | C100: =IFERROR(__xludf.DUMMYFUNCTION("""COMPUTED_VALUE"""),366.0) -> 366 | D100: =IFERROR(__xludf.DUMMYFUNCTION("""COMPUTED_VALUE"""),344.0) -> 344
...

Sheet Sales from Stock
A1: =IFERROR(__xludf.DUMMYFUNCTION("IMPORTRANGE(""https://docs.google.com/spreadsheets/d/1yOpZnyZ5ouw2C51zn4VNSNmNNrizgIE5YAyno7ltBiE/edit"",""stock!A:Z"")"),"product_id") -> product_id | B1: =IFERROR(__xludf.DUMMYFUNCTION("""COMPUTED_VALUE"""),"new") -> new | C1: =IFERROR(__xludf.DUMMYFUNCTION("""COMPUTED_VALUE"""),"forecast_stock") -> forecast_stock | D1: =IFERROR(__xludf.DUMMYFUNCTION("""COMPUTED_VALUE"""),"stock") -> stock
A2: =IFERROR(__xludf.DUMMYFUNCTION("""COMPUTED_VALUE"""),112463.0) -> 112463 | B2: =IFERROR(__xludf.DUMMYFUNCTION("""COMPUTED_VALUE"""),0.0) -> 0 | C2: =IFERROR(__xludf.DUMMYFUNCTION("""COMPUTED_VALUE"""),320.0) -> 320 | D2: =IFERROR(__xludf.DUMMYFUNCTION("""COMPUTED_VALUE"""),320.0) -> 320
A3: =IFERROR(__xludf.DUMMYFUNCTION("""COMPUTED_VALUE"""),112481.0) -> 112481 | B3: =IFERROR(__xludf.DUMMYFUNCTION("""COMPUTED_VALUE"""),0.0) -> 0 | C3: =IFERROR(__xludf.DUMMYFUNCTION("""COMPUTED_VALUE"""),0.0) -> 0 | D3: =IFERROR(__xludf.DUMMYFUNCTION("""COMPUTED_VALUE"""),0.0) -> 0
A4: =IFERROR(__xludf.DUMMYFUNCTION("""COMPUTED_VALUE"""),13346.0) -> 13346 | B4: =IFERROR(__xludf.DUMMYFUNCTION("""COMPUTED_VALUE"""),1.0) -> 1 | C4: =IFERROR(__xludf.DUMMYFUNCTION("""COMPUTED_VALUE"""),100.0) -> 100 | D4: =IFERROR(__xludf.DUMMYFUNCTION("""COMPUTED_VALUE"""),100.0) -> 100
A5: =IFERROR(__xludf.DUMMYFUNCTION("""COMPUTED_VALUE"""),112454.0) -> 112454 | B5: =IFERROR(__xludf.DUMMYFUNCTION("""COMPUTED_VALUE"""),0.0) -> 0 | C5: =IFERROR(__xludf.DUMMYFUNCTION("""COMPUTED_VALUE"""),277.0) -> 277 | D5: =IFERROR(__xludf.DUMMYFUNCTION("""COMPUTED_VALUE"""),268.0) -> 268
A6: =IFERROR(__xludf.DUMMYFUNCTION("""COMPUTED_VALUE"""),112461.0) -> 112461 | B6: =IFERROR(__xludf.DUMMYFUNCTION("""COMPUTED_VALUE"""),0.0) -> 0 | C6: =IFERROR(__xludf.DUMMYFUNCTION("""COMPUTED_VALUE"""),971.0) -> 971 | D6: =IFERROR(__xludf.DUMMYFUNCTION("""COMPUTED_VALUE"""),472.0) -> 472
A7: =IFERROR(__xludf.DUMMYFUNCTION("""COMPUTED_VALUE"""),106532.0) -> 106532 | B7: =IFERROR(__xludf.DUMMYFUNCTION("""COMPUTED_VALUE"""),0.0) -> 0 | C7: =IFERROR(__xludf.DUMMYFUNCTION("""COMPUTED_VALUE"""),63.0) -> 63 | D7: =IFERROR(__xludf.DUMMYFUNCTION("""COMPUTED_VALUE"""),63.0) -> 63
A8: =IFERROR(__xludf.DUMMYFUNCTION("""COMPUTED_VALUE"""),121135.0) -> 121135 | B8: =IFERROR(__xludf.DUMMYFUNCTION("""COMPUTED_VALUE"""),1.0) -> 1 | C8: =IFERROR(__xludf.DUMMYFUNCTION("""COMPUTED_VALUE"""),40.0) -> 40 | D8: =IFERROR(__xludf.DUMMYFUNCTION("""COMPUTED_VALUE"""),33.0) -> 33
A9: =IFERROR(__xludf.DUMMYFUNCTION("""COMPUTED_VALUE"""),128362.0) -> 128362 | B9: =IFERROR(__xludf.DUMMYFUNCTION("""COMPUTED_VALUE"""),1.0) -> 1 | C9: =IFERROR(__xludf.DUMMYFUNCTION("""COMPUTED_VALUE"""),269.0) -> 269 | D9: =IFERROR(__xludf.DUMMYFUNCTION("""COMPUTED_VALUE"""),104.0) -> 104
A10: =IFERROR(__xludf.DUMMYFUNCTION("""COMPUTED_VALUE"""),71200.0) -> 71200 | B10: =IFERROR(__xludf.DUMMYFUNCTION("""COMPUTED_VALUE"""),0.0) -> 0 | C10: =IFERROR(__xludf.DUMMYFUNCTION("""COMPUTED_VALUE"""),164.0) -> 164 | D10: =IFERROR(__xludf.DUMMYFUNCTION("""COMPUTED_VALUE"""),152.0) -> 152
A11: =IFERROR(__xludf.DUMMYFUNCTION("""COMPUTED_VALUE"""),19812.0) -> 19812 | B11: =IFERROR(__xludf.DUMMYFUNCTION("""COMPUTED_VALUE"""),0.0) -> 0 | C11: =IFERROR(__xludf.DUMMYFUNCTION("""COMPUTED_VALUE"""),489.0) -> 489 | D11: =IFERROR(__xludf.DUMMYFUNCTION("""COMPUTED_VALUE"""),393.0) -> 393
A12: =IFERROR(__xludf.DUMMYFUNCTION("""COMPUTED_VALUE"""),122259.0) -> 122259 | B12: =IFERROR(__xludf.DUMMYFUNCTION("""COMPUTED_VALUE"""),1.0) -> 1 | C12: =IFERROR(__xludf.DUMMYFUNCTION("""COMPUTED_VALUE"""),104.0) -> 104 | D12: =IFERROR(__xludf.DUMMYFUNCTION("""COMPUTED_VALUE"""),104.0) -> 104
A13: =IFERROR(__xludf.DUMMYFUNCTION("""COMPUTED_VALUE"""),199526.0) -> 199526 | B13: =IFERROR(__xludf.DUMMYFUNCTION("""COMPUTED_VALUE"""),0.0) -> 0 | C13: =IFERROR(__xludf.DUMMYFUNCTION("""COMPUTED_VALUE"""),63.0) -> 63 | D13: =IFERROR(__xludf.DUMMYFUNCTION("""COMPUTED_VALUE"""),60.0) -> 60
A14: =IFERROR(__xludf.DUMMYFUNCTION("""COMPUTED_VALUE"""),140581.0) -> 140581 | B14: =IFERROR(__xludf.DUMMYFUNCTION("""COMPUTED_VALUE"""),0.0) -> 0 | C14: =IFERROR(__xludf.DUMMYFUNCTION("""COMPUTED_VALUE"""),14.0) -> 14 | D14: =IFERROR(__xludf.DUMMYFUNCTION("""COMPUTED_VALUE"""),9.0) -> 9
A15: =IFERROR(__xludf.DUMMYFUNCTION("""COMPUTED_VALUE"""),118383.0) -> 118383 | B15: =IFERROR(__xludf.DUMMYFUNCTION("""COMPUTED_VALUE"""),0.0) -> 0 | C15: =IFERROR(__xludf.DUMMYFUNCTION("""COMPUTED_VALUE"""),256.0) -> 256 | D15: =IFERROR(__xludf.DUMMYFUNCTION("""COMPUTED_VALUE"""),256.0) -> 256
A16: =IFERROR(__xludf.DUMMYFUNCTION("""COMPUTED_VALUE"""),122262.0) -> 122262 | B16: =IFERROR(__xludf.DUMMYFUNCTION("""COMPUTED_VALUE"""),0.0) -> 0 | C16: =IFERROR(__xludf.DUMMYFUNCTION("""COMPUTED_VALUE"""),326.0) -> 326 | D16: =IFERROR(__xludf.DUMMYFUNCTION("""COMPUTED_VALUE"""),326.0) -> 326
A17: =IFERROR(__xludf.DUMMYFUNCTION("""COMPUTED_VALUE"""),141879.0) -> 141879 | B17: =IFERROR(__xludf.DUMMYFUNCTION("""COMPUTED_VALUE"""),0.0) -> 0 | C17: =IFERROR(__xludf.DUMMYFUNCTION("""COMPUTED_VALUE"""),11.0) -> 11 | D17: =IFERROR(__xludf.DUMMYFUNCTION("""COMPUTED_VALUE"""),11.0) -> 11
A18: =IFERROR(__xludf.DUMMYFUNCTION("""COMPUTED_VALUE"""),19826.0) -> 19826 | B18: =IFERROR(__xludf.DUMMYFUNCTION("""COMPUTED_VALUE"""),0.0) -> 0 | C18: =IFERROR(__xludf.DUMMYFUNCTION("""COMPUTED_VALUE"""),210.0) -> 210 | D18: =IFERROR(__xludf.DUMMYFUNCTION("""COMPUTED_VALUE"""),103.0) -> 103
A19: =IFERROR(__xludf.DUMMYFUNCTION("""COMPUTED_VALUE"""),93039.0) -> 93039 | B19: =IFERROR(__xludf.DUMMYFUNCTION("""COMPUTED_VALUE"""),0.0) -> 0 | C19: =IFERROR(__xludf.DUMMYFUNCTION("""COMPUTED_VALUE"""),68.0) -> 68 | D19: =IFERROR(__xludf.DUMMYFUNCTION("""COMPUTED_VALUE"""),68.0) -> 68
A20: =IFERROR(__xludf.DUMMYFUNCTION("""COMPUTED_VALUE"""),128213.0) -> 128213 | B20: =IFERROR(__xludf.DUMMYFUNCTION("""COMPUTED_VALUE"""),0.0) -> 0 | C20: =IFERROR(__xludf.DUMMYFUNCTION("""COMPUTED_VALUE"""),318.0) -> 318 | D20: =IFERROR(__xludf.DUMMYFUNCTION("""COMPUTED_VALUE"""),162.0) -> 162
A21: =IFERROR(__xludf.DUMMYFUNCTION("""COMPUTED_VALUE"""),83797.0) -> 83797 | B21: =IFERROR(__xludf.DUMMYFUNCTION("""COMPUTED_VALUE"""),0.0) -> 0 | C21: =IFERROR(__xludf.DUMMYFUNCTION("""COMPUTED_VALUE"""),43.0) -> 43 | D21: =IFERROR(__xludf.DUMMYFUNCTION("""COMPUTED_VALUE"""),43.0) -> 43
A22: =IFERROR(__xludf.DUMMYFUNCTION("""COMPUTED_VALUE"""),19831.0) -> 19831 | B22: =IFERROR(__xludf.DUMMYFUNCTION("""COMPUTED_VALUE"""),0.0) -> 0 | C22: =IFERROR(__xludf.DUMMYFUNCTION("""COMPUTED_VALUE"""),185.0) -> 185 | D22: =IFERROR(__xludf.DUMMYFUNCTION("""COMPUTED_VALUE"""),134.0) -> 134
A23: =IFERROR(__xludf.DUMMYFUNCTION("""COMPUTED_VALUE"""),93025.0) -> 93025 | B23: =IFERROR(__xludf.DUMMYFUNCTION("""COMPUTED_VALUE"""),0.0) -> 0 | C23: =IFERROR(__xludf.DUMMYFUNCTION("""COMPUTED_VALUE"""),305.0) -> 305 | D23: =IFERROR(__xludf.DUMMYFUNCTION("""COMPUTED_VALUE"""),305.0) -> 305
A24: =IFERROR(__xludf.DUMMYFUNCTION("""COMPUTED_VALUE"""),81624.0) -> 81624 | B24: =IFERROR(__xludf.DUMMYFUNCTION("""COMPUTED_VALUE"""),1.0) -> 1 | C24: =IFERROR(__xludf.DUMMYFUNCTION("""COMPUTED_VALUE"""),84.0) -> 84 | D24: =IFERROR(__xludf.DUMMYFUNCTION("""COMPUTED_VALUE"""),84.0) -> 84
A25: =IFERROR(__xludf.DUMMYFUNCTION("""COMPUTED_VALUE"""),92913.0) -> 92913 | B25: =IFERROR(__xludf.DUMMYFUNCTION("""COMPUTED_VALUE"""),0.0) -> 0 | C25: =IFERROR(__xludf.DUMMYFUNCTION("""COMPUTED_VALUE"""),96.0) -> 96 | D25: =IFERROR(__xludf.DUMMYFUNCTION("""COMPUTED_VALUE"""),96.0) -> 96
A26: =IFERROR(__xludf.DUMMYFUNCTION("""COMPUTED_VALUE"""),126983.0) -> 126983 | B26: =IFERROR(__xludf.DUMMYFUNCTION("""COMPUTED_VALUE"""),0.0) -> 0 | C26: =IFERROR(__xludf.DUMMYFUNCTION("""COMPUTED_VALUE"""),176.0) -> 176 | D26: =IFERROR(__xludf.DUMMYFUNCTION("""COMPUTED_VALUE"""),71.0) -> 71
A27: =IFERROR(__xludf.DUMMYFUNCTION("""COMPUTED_VALUE"""),118226.0) -> 118226 | B27: =IFERROR(__xludf.DUMMYFUNCTION("""COMPUTED_VALUE"""),0.0) -> 0 | C27: =IFERROR(__xludf.DUMMYFUNCTION("""COMPUTED_VALUE"""),130.0) -> 130 | D27: =IFERROR(__xludf.DUMMYFUNCTION("""COMPUTED_VALUE"""),130.0) -> 130
A28: =IFERROR(__xludf.DUMMYFUNCTION("""COMPUTED_VALUE"""),48618.0) -> 48618 | B28: =IFERROR(__xludf.DUMMYFUNCTION("""COMPUTED_VALUE"""),1.0) -> 1 | C28: =IFERROR(__xludf.DUMMYFUNCTION("""COMPUTED_VALUE"""),84.0) -> 84 | D28: =IFERROR(__xludf.DUMMYFUNCTION("""COMPUTED_VALUE"""),84.0) -> 84
A29: =IFERROR(__xludf.DUMMYFUNCTION("""COMPUTED_VALUE"""),93037.0) -> 93037 | B29: =IFERROR(__xludf.DUMMYFUNCTION("""COMPUTED_VALUE"""),0.0) -> 0 | C29: =IFERROR(__xludf.DUMMYFUNCTION("""COMPUTED_VALUE"""),604.0) -> 604 | D29: =IFERROR(__xludf.DUMMYFUNCTION("""COMPUTED_VALUE"""),604.0) -> 604
A30: =IFERROR(__xludf.DUMMYFUNCTION("""COMPUTED_VALUE"""),126984.0) -> 126984 | B30: =IFERROR(__xludf.DUMMYFUNCTION("""COMPUTED_VALUE"""),0.0) -> 0 | C30: =IFERROR(__xludf.DUMMYFUNCTION("""COMPUTED_VALUE"""),26.0) -> 26 | D30: =IFERROR(__xludf.DUMMYFUNCTION("""COMPUTED_VALUE"""),6.0) -> 6
A31: =IFERROR(__xludf.DUMMYFUNCTION("""COMPUTED_VALUE"""),47393.0) -> 47393 | B31: =IFERROR(__xludf.DUMMYFUNCTION("""COMPUTED_VALUE"""),0.0) -> 0 | C31: =IFERROR(__xludf.DUMMYFUNCTION("""COMPUTED_VALUE"""),982.0) -> 982 | D31: =IFERROR(__xludf.DUMMYFUNCTION("""COMPUTED_VALUE"""),609.0) -> 609
A32: =IFERROR(__xludf.DUMMYFUNCTION("""COMPUTED_VALUE"""),128214.0) -> 128214 | B32: =IFERROR(__xludf.DUMMYFUNCTION("""COMPUTED_VALUE"""),0.0) -> 0 | C32: =IFERROR(__xludf.DUMMYFUNCTION("""COMPUTED_VALUE"""),79.0) -> 79 | D32: =IFERROR(__xludf.DUMMYFUNCTION("""COMPUTED_VALUE"""),79.0) -> 79
A33: =IFERROR(__xludf.DUMMYFUNCTION("""COMPUTED_VALUE"""),83802.0) -> 83802 | B33: =IFERROR(__xludf.DUMMYFUNCTION("""COMPUTED_VALUE"""),0.0) -> 0 | C33: =IFERROR(__xludf.DUMMYFUNCTION("""COMPUTED_VALUE"""),31.0) -> 31 | D33: =IFERROR(__xludf.DUMMYFUNCTION("""COMPUTED_VALUE"""),23.0) -> 23
A34: =IFERROR(__xludf.DUMMYFUNCTION("""COMPUTED_VALUE"""),48625.0) -> 48625 | B34: =IFERROR(__xludf.DUMMYFUNCTION("""COMPUTED_VALUE"""),1.0) -> 1 | C34: =IFERROR(__xludf.DUMMYFUNCTION("""COMPUTED_VALUE"""),96.0) -> 96 | D34: =IFERROR(__xludf.DUMMYFUNCTION("""COMPUTED_VALUE"""),96.0) -> 96
A35: =IFERROR(__xludf.DUMMYFUNCTION("""COMPUTED_VALUE"""),83602.0) -> 83602 | B35: =IFERROR(__xludf.DUMMYFUNCTION("""COMPUTED_VALUE"""),0.0) -> 0 | C35: =IFERROR(__xludf.DUMMYFUNCTION("""COMPUTED_VALUE"""),79.0) -> 79 | D35: =IFERROR(__xludf.DUMMYFUNCTION("""COMPUTED_VALUE"""),79.0) -> 79
A36: =IFERROR(__xludf.DUMMYFUNCTION("""COMPUTED_VALUE"""),98867.0) -> 98867 | B36: =IFERROR(__xludf.DUMMYFUNCTION("""COMPUTED_VALUE"""),0.0) -> 0 | C36: =IFERROR(__xludf.DUMMYFUNCTION("""COMPUTED_VALUE"""),186.0) -> 186 | D36: =IFERROR(__xludf.DUMMYFUNCTION("""COMPUTED_VALUE"""),186.0) -> 186
A37: =IFERROR(__xludf.DUMMYFUNCTION("""COMPUTED_VALUE"""),127042.0) -> 127042 | B37: =IFERROR(__xludf.DUMMYFUNCTION("""COMPUTED_VALUE"""),0.0) -> 0 | C37: =IFERROR(__xludf.DUMMYFUNCTION("""COMPUTED_VALUE"""),418.0) -> 418 | D37: =IFERROR(__xludf.DUMMYFUNCTION("""COMPUTED_VALUE"""),418.0) -> 418
A38: =IFERROR(__xludf.DUMMYFUNCTION("""COMPUTED_VALUE"""),127241.0) -> 127241 | B38: =IFERROR(__xludf.DUMMYFUNCTION("""COMPUTED_VALUE"""),0.0) -> 0 | C38: =IFERROR(__xludf.DUMMYFUNCTION("""COMPUTED_VALUE"""),98.0) -> 98 | D38: =IFERROR(__xludf.DUMMYFUNCTION("""COMPUTED_VALUE"""),98.0) -> 98
A39: =IFERROR(__xludf.DUMMYFUNCTION("""COMPUTED_VALUE"""),118220.0) -> 118220 | B39: =IFERROR(__xludf.DUMMYFUNCTION("""COMPUTED_VALUE"""),0.0) -> 0 | C39: =IFERROR(__xludf.DUMMYFUNCTION("""COMPUTED_VALUE"""),34.0) -> 34 | D39: =IFERROR(__xludf.DUMMYFUNCTION("""COMPUTED_VALUE"""),34.0) -> 34
A40: =IFERROR(__xludf.DUMMYFUNCTION("""COMPUTED_VALUE"""),128216.0) -> 128216 | B40: =IFERROR(__xludf.DUMMYFUNCTION("""COMPUTED_VALUE"""),0.0) -> 0 | C40: =IFERROR(__xludf.DUMMYFUNCTION("""COMPUTED_VALUE"""),141.0) -> 141 | D40: =IFERROR(__xludf.DUMMYFUNCTION("""COMPUTED_VALUE"""),141.0) -> 141
A41: =IFERROR(__xludf.DUMMYFUNCTION("""COMPUTED_VALUE"""),93049.0) -> 93049 | B41: =IFERROR(__xludf.DUMMYFUNCTION("""COMPUTED_VALUE"""),0.0) -> 0 | C41: =IFERROR(__xludf.DUMMYFUNCTION("""COMPUTED_VALUE"""),34.0) -> 34 | D41: =IFERROR(__xludf.DUMMYFUNCTION("""COMPUTED_VALUE"""),34.0) -> 34
A42: =IFERROR(__xludf.DUMMYFUNCTION("""COMPUTED_VALUE"""),118216.0) -> 118216 | B42: =IFERROR(__xludf.DUMMYFUNCTION("""COMPUTED_VALUE"""),0.0) -> 0 | C42: =IFERROR(__xludf.DUMMYFUNCTION("""COMPUTED_VALUE"""),0.0) -> 0 | D42: =IFERROR(__xludf.DUMMYFUNCTION("""COMPUTED_VALUE"""),0.0) -> 0
A43: =IFERROR(__xludf.DUMMYFUNCTION("""COMPUTED_VALUE"""),118221.0) -> 118221 | B43: =IFERROR(__xludf.DUMMYFUNCTION("""COMPUTED_VALUE"""),1.0) -> 1 | C43: =IFERROR(__xludf.DUMMYFUNCTION("""COMPUTED_VALUE"""),99.0) -> 99 | D43: =IFERROR(__xludf.DUMMYFUNCTION("""COMPUTED_VALUE"""),99.0) -> 99
A44: =IFERROR(__xludf.DUMMYFUNCTION("""COMPUTED_VALUE"""),92900.0) -> 92900 | B44: =IFERROR(__xludf.DUMMYFUNCTION("""COMPUTED_VALUE"""),0.0) -> 0 | C44: =IFERROR(__xludf.DUMMYFUNCTION("""COMPUTED_VALUE"""),167.0) -> 167 | D44: =IFERROR(__xludf.DUMMYFUNCTION("""COMPUTED_VALUE"""),131.0) -> 131
A45: =IFERROR(__xludf.DUMMYFUNCTION("""COMPUTED_VALUE"""),118215.0) -> 118215 | B45: =IFERROR(__xludf.DUMMYFUNCTION("""COMPUTED_VALUE"""),1.0) -> 1 | C45: =IFERROR(__xludf.DUMMYFUNCTION("""COMPUTED_VALUE"""),100.0) -> 100 | D45: =IFERROR(__xludf.DUMMYFUNCTION("""COMPUTED_VALUE"""),46.0) -> 46
A46: =IFERROR(__xludf.DUMMYFUNCTION("""COMPUTED_VALUE"""),19832.0) -> 19832 | B46: =IFERROR(__xludf.DUMMYFUNCTION("""COMPUTED_VALUE"""),1.0) -> 1 | C46: =IFERROR(__xludf.DUMMYFUNCTION("""COMPUTED_VALUE"""),594.0) -> 594 | D46: =IFERROR(__xludf.DUMMYFUNCTION("""COMPUTED_VALUE"""),558.0) -> 558
A47: =IFERROR(__xludf.DUMMYFUNCTION("""COMPUTED_VALUE"""),93071.0) -> 93071 | B47: =IFERROR(__xludf.DUMMYFUNCTION("""COMPUTED_VALUE"""),1.0) -> 1 | C47: =IFERROR(__xludf.DUMMYFUNCTION("""COMPUTED_VALUE"""),199.0) -> 199 | D47: =IFERROR(__xludf.DUMMYFUNCTION("""COMPUTED_VALUE"""),19.0) -> 19
A48: =IFERROR(__xludf.DUMMYFUNCTION("""COMPUTED_VALUE"""),122395.0) -> 122395 | B48: =IFERROR(__xludf.DUMMYFUNCTION("""COMPUTED_VALUE"""),1.0) -> 1 | C48: =IFERROR(__xludf.DUMMYFUNCTION("""COMPUTED_VALUE"""),76.0) -> 76 | D48: =IFERROR(__xludf.DUMMYFUNCTION("""COMPUTED_VALUE"""),2.0) -> 2
A49: =IFERROR(__xludf.DUMMYFUNCTION("""COMPUTED_VALUE"""),116946.0) -> 116946 | B49: =IFERROR(__xludf.DUMMYFUNCTION("""COMPUTED_VALUE"""),1.0) -> 1 | C49: =IFERROR(__xludf.DUMMYFUNCTION("""COMPUTED_VALUE"""),144.0) -> 144 | D49: =IFERROR(__xludf.DUMMYFUNCTION("""COMPUTED_VALUE"""),85.0) -> 85
A50: =IFERROR(__xludf.DUMMYFUNCTION("""COMPUTED_VALUE"""),97538.0) -> 97538 | B50: =IFERROR(__xludf.DUMMYFUNCTION("""COMPUTED_VALUE"""),1.0) -> 1 | C50: =IFERROR(__xludf.DUMMYFUNCTION("""COMPUTED_VALUE"""),135.0) -> 135 | D50: =IFERROR(__xludf.DUMMYFUNCTION("""COMPUTED_VALUE"""),82.0) -> 82
A51: =IFERROR(__xludf.DUMMYFUNCTION("""COMPUTED_VALUE"""),127238.0) -> 127238 | B51: =IFERROR(__xludf.DUMMYFUNCTION("""COMPUTED_VALUE"""),1.0) -> 1 | C51: =IFERROR(__xludf.DUMMYFUNCTION("""COMPUTED_VALUE"""),147.0) -> 147 | D51: =IFERROR(__xludf.DUMMYFUNCTION("""COMPUTED_VALUE"""),88.0) -> 88
A52: =IFERROR(__xludf.DUMMYFUNCTION("""COMPUTED_VALUE"""),81646.0) -> 81646 | B52: =IFERROR(__xludf.DUMMYFUNCTION("""COMPUTED_VALUE"""),1.0) -> 1 | C52: =IFERROR(__xludf.DUMMYFUNCTION("""COMPUTED_VALUE"""),399.0) -> 399 | D52: =IFERROR(__xludf.DUMMYFUNCTION("""COMPUTED_VALUE"""),159.0) -> 159
A53: =IFERROR(__xludf.DUMMYFUNCTION("""COMPUTED_VALUE"""),81643.0) -> 81643 | B53: =IFERROR(__xludf.DUMMYFUNCTION("""COMPUTED_VALUE"""),1.0) -> 1 | C53: =IFERROR(__xludf.DUMMYFUNCTION("""COMPUTED_VALUE"""),927.0) -> 927 | D53: =IFERROR(__xludf.DUMMYFUNCTION("""COMPUTED_VALUE"""),301.0) -> 301
A54: =IFERROR(__xludf.DUMMYFUNCTION("""COMPUTED_VALUE"""),128215.0) -> 128215 | B54: =IFERROR(__xludf.DUMMYFUNCTION("""COMPUTED_VALUE"""),1.0) -> 1 | C54: =IFERROR(__xludf.DUMMYFUNCTION("""COMPUTED_VALUE"""),389.0) -> 389 | D54: =IFERROR(__xludf.DUMMYFUNCTION("""COMPUTED_VALUE"""),243.0) -> 243
A55: =IFERROR(__xludf.DUMMYFUNCTION("""COMPUTED_VALUE"""),108022.0) -> 108022 | B55: =IFERROR(__xludf.DUMMYFUNCTION("""COMPUTED_VALUE"""),1.0) -> 1 | C55: =IFERROR(__xludf.DUMMYFUNCTION("""COMPUTED_VALUE"""),455.0) -> 455 | D55: =IFERROR(__xludf.DUMMYFUNCTION("""COMPUTED_VALUE"""),285.0) -> 285
A56: =IFERROR(__xludf.DUMMYFUNCTION("""COMPUTED_VALUE"""),81647.0) -> 81647 | B56: =IFERROR(__xludf.DUMMYFUNCTION("""COMPUTED_VALUE"""),0.0) -> 0 | C56: =IFERROR(__xludf.DUMMYFUNCTION("""COMPUTED_VALUE"""),547.0) -> 547 | D56: =IFERROR(__xludf.DUMMYFUNCTION("""COMPUTED_VALUE"""),227.0) -> 227
A57: =IFERROR(__xludf.DUMMYFUNCTION("""COMPUTED_VALUE"""),83603.0) -> 83603 | B57: =IFERROR(__xludf.DUMMYFUNCTION("""COMPUTED_VALUE"""),1.0) -> 1 | C57: =IFERROR(__xludf.DUMMYFUNCTION("""COMPUTED_VALUE"""),870.0) -> 870 | D57: =IFERROR(__xludf.DUMMYFUNCTION("""COMPUTED_VALUE"""),105.0) -> 105
A58: =IFERROR(__xludf.DUMMYFUNCTION("""COMPUTED_VALUE"""),118219.0) -> 118219 | B58: =IFERROR(__xludf.DUMMYFUNCTION("""COMPUTED_VALUE"""),1.0) -> 1 | C58: =IFERROR(__xludf.DUMMYFUNCTION("""COMPUTED_VALUE"""),397.0) -> 397 | D58: =IFERROR(__xludf.DUMMYFUNCTION("""COMPUTED_VALUE"""),207.0) -> 207
A59: =IFERROR(__xludf.DUMMYFUNCTION("""COMPUTED_VALUE"""),120952.0) -> 120952 | B59: =IFERROR(__xludf.DUMMYFUNCTION("""COMPUTED_VALUE"""),1.0) -> 1 | C59: =IFERROR(__xludf.DUMMYFUNCTION("""COMPUTED_VALUE"""),134.0) -> 134 | D59: =IFERROR(__xludf.DUMMYFUNCTION("""COMPUTED_VALUE"""),78.0) -> 78
A60: =IFERROR(__xludf.DUMMYFUNCTION("""COMPUTED_VALUE"""),81658.0) -> 81658 | B60: =IFERROR(__xludf.DUMMYFUNCTION("""COMPUTED_VALUE"""),1.0) -> 1 | C60: =IFERROR(__xludf.DUMMYFUNCTION("""COMPUTED_VALUE"""),685.0) -> 685 | D60: =IFERROR(__xludf.DUMMYFUNCTION("""COMPUTED_VALUE"""),42.0) -> 42
A61: =IFERROR(__xludf.DUMMYFUNCTION("""COMPUTED_VALUE"""),93047.0) -> 93047 | B61: =IFERROR(__xludf.DUMMYFUNCTION("""COMPUTED_VALUE"""),0.0) -> 0 | C61: =IFERROR(__xludf.DUMMYFUNCTION("""COMPUTED_VALUE"""),525.0) -> 525 | D61: =IFERROR(__xludf.DUMMYFUNCTION("""COMPUTED_VALUE"""),306.0) -> 306
A62: =IFERROR(__xludf.DUMMYFUNCTION("""COMPUTED_VALUE"""),83807.0) -> 83807 | B62: =IFERROR(__xludf.DUMMYFUNCTION("""COMPUTED_VALUE"""),1.0) -> 1 | C62: =IFERROR(__xludf.DUMMYFUNCTION("""COMPUTED_VALUE"""),596.0) -> 596 | D62: =IFERROR(__xludf.DUMMYFUNCTION("""COMPUTED_VALUE"""),321.0) -> 321
A63: =IFERROR(__xludf.DUMMYFUNCTION("""COMPUTED_VALUE"""),92915.0) -> 92915 | B63: =IFERROR(__xludf.DUMMYFUNCTION("""COMPUTED_VALUE"""),0.0) -> 0 | C63: =IFERROR(__xludf.DUMMYFUNCTION("""COMPUTED_VALUE"""),861.0) -> 861 | D63: =IFERROR(__xludf.DUMMYFUNCTION("""COMPUTED_VALUE"""),576.0) -> 576
A64: =IFERROR(__xludf.DUMMYFUNCTION("""COMPUTED_VALUE"""),81653.0) -> 81653 | B64: =IFERROR(__xludf.DUMMYFUNCTION("""COMPUTED_VALUE"""),0.0) -> 0 | C64: =IFERROR(__xludf.DUMMYFUNCTION("""COMPUTED_VALUE"""),64.0) -> 64 | D64: =IFERROR(__xludf.DUMMYFUNCTION("""COMPUTED_VALUE"""),31.0) -> 31
A65: =IFERROR(__xludf.DUMMYFUNCTION("""COMPUTED_VALUE"""),81618.0) -> 81618 | B65: =IFERROR(__xludf.DUMMYFUNCTION("""COMPUTED_VALUE"""),1.0) -> 1 | C65: =IFERROR(__xludf.DUMMYFUNCTION("""COMPUTED_VALUE"""),124.0) -> 124 | D65: =IFERROR(__xludf.DUMMYFUNCTION("""COMPUTED_VALUE"""),37.0) -> 37
A66: =IFERROR(__xludf.DUMMYFUNCTION("""COMPUTED_VALUE"""),118241.0) -> 118241 | B66: =IFERROR(__xludf.DUMMYFUNCTION("""COMPUTED_VALUE"""),1.0) -> 1 | C66: =IFERROR(__xludf.DUMMYFUNCTION("""COMPUTED_VALUE"""),897.0) -> 897 | D66: =IFERROR(__xludf.DUMMYFUNCTION("""COMPUTED_VALUE"""),1.0) -> 1
A67: =IFERROR(__xludf.DUMMYFUNCTION("""COMPUTED_VALUE"""),48634.0) -> 48634 | B67: =IFERROR(__xludf.DUMMYFUNCTION("""COMPUTED_VALUE"""),1.0) -> 1 | C67: =IFERROR(__xludf.DUMMYFUNCTION("""COMPUTED_VALUE"""),832.0) -> 832 | D67: =IFERROR(__xludf.DUMMYFUNCTION("""COMPUTED_VALUE"""),180.0) -> 180
A68: =IFERROR(__xludf.DUMMYFUNCTION("""COMPUTED_VALUE"""),48636.0) -> 48636 | B68: =IFERROR(__xludf.DUMMYFUNCTION("""COMPUTED_VALUE"""),1.0) -> 1 | C68: =IFERROR(__xludf.DUMMYFUNCTION("""COMPUTED_VALUE"""),37.0) -> 37 | D68: =IFERROR(__xludf.DUMMYFUNCTION("""COMPUTED_VALUE"""),10.0) -> 10
A69: =IFERROR(__xludf.DUMMYFUNCTION("""COMPUTED_VALUE"""),48629.0) -> 48629 | B69: =IFERROR(__xludf.DUMMYFUNCTION("""COMPUTED_VALUE"""),1.0) -> 1 | C69: =IFERROR(__xludf.DUMMYFUNCTION("""COMPUTED_VALUE"""),935.0) -> 935 | D69: =IFERROR(__xludf.DUMMYFUNCTION("""COMPUTED_VALUE"""),635.0) -> 635
A70: =IFERROR(__xludf.DUMMYFUNCTION("""COMPUTED_VALUE"""),47400.0) -> 47400 | B70: =IFERROR(__xludf.DUMMYFUNCTION("""COMPUTED_VALUE"""),1.0) -> 1 | C70: =IFERROR(__xludf.DUMMYFUNCTION("""COMPUTED_VALUE"""),868.0) -> 868 | D70: =IFERROR(__xludf.DUMMYFUNCTION("""COMPUTED_VALUE"""),396.0) -> 396
A71: =IFERROR(__xludf.DUMMYFUNCTION("""COMPUTED_VALUE"""),111237.0) -> 111237 | B71: =IFERROR(__xludf.DUMMYFUNCTION("""COMPUTED_VALUE"""),0.0) -> 0 | C71: =IFERROR(__xludf.DUMMYFUNCTION("""COMPUTED_VALUE"""),445.0) -> 445 | D71: =IFERROR(__xludf.DUMMYFUNCTION("""COMPUTED_VALUE"""),128.0) -> 128
A72: =IFERROR(__xludf.DUMMYFUNCTION("""COMPUTED_VALUE"""),18042.0) -> 18042 | B72: =IFERROR(__xludf.DUMMYFUNCTION("""COMPUTED_VALUE"""),0.0) -> 0 | C72: =IFERROR(__xludf.DUMMYFUNCTION("""COMPUTED_VALUE"""),232.0) -> 232 | D72: =IFERROR(__xludf.DUMMYFUNCTION("""COMPUTED_VALUE"""),214.0) -> 214
A73: =IFERROR(__xludf.DUMMYFUNCTION("""COMPUTED_VALUE"""),114978.0) -> 114978 | B73: =IFERROR(__xludf.DUMMYFUNCTION("""COMPUTED_VALUE"""),0.0) -> 0 | C73: =IFERROR(__xludf.DUMMYFUNCTION("""COMPUTED_VALUE"""),315.0) -> 315 | D73: =IFERROR(__xludf.DUMMYFUNCTION("""COMPUTED_VALUE"""),278.0) -> 278
A74: =IFERROR(__xludf.DUMMYFUNCTION("""COMPUTED_VALUE"""),82980.0) -> 82980 | B74: =IFERROR(__xludf.DUMMYFUNCTION("""COMPUTED_VALUE"""),1.0) -> 1 | C74: =IFERROR(__xludf.DUMMYFUNCTION("""COMPUTED_VALUE"""),356.0) -> 356 | D74: =IFERROR(__xludf.DUMMYFUNCTION("""COMPUTED_VALUE"""),164.0) -> 164
A75: =IFERROR(__xludf.DUMMYFUNCTION("""COMPUTED_VALUE"""),83093.0) -> 83093 | B75: =IFERROR(__xludf.DUMMYFUNCTION("""COMPUTED_VALUE"""),0.0) -> 0 | C75: =IFERROR(__xludf.DUMMYFUNCTION("""COMPUTED_VALUE"""),442.0) -> 442 | D75: =IFERROR(__xludf.DUMMYFUNCTION("""COMPUTED_VALUE"""),385.0) -> 385
A76: =IFERROR(__xludf.DUMMYFUNCTION("""COMPUTED_VALUE"""),18134.0) -> 18134 | B76: =IFERROR(__xludf.DUMMYFUNCTION("""COMPUTED_VALUE"""),0.0) -> 0 | C76: =IFERROR(__xludf.DUMMYFUNCTION("""COMPUTED_VALUE"""),492.0) -> 492 | D76: =IFERROR(__xludf.DUMMYFUNCTION("""COMPUTED_VALUE"""),381.0) -> 381
A77: =IFERROR(__xludf.DUMMYFUNCTION("""COMPUTED_VALUE"""),107857.0) -> 107857 | B77: =IFERROR(__xludf.DUMMYFUNCTION("""COMPUTED_VALUE"""),0.0) -> 0 | C77: =IFERROR(__xludf.DUMMYFUNCTION("""COMPUTED_VALUE"""),645.0) -> 645 | D77: =IFERROR(__xludf.DUMMYFUNCTION("""COMPUTED_VALUE"""),327.0) -> 327
A78: =IFERROR(__xludf.DUMMYFUNCTION("""COMPUTED_VALUE"""),18136.0) -> 18136 | B78: =IFERROR(__xludf.DUMMYFUNCTION("""COMPUTED_VALUE"""),1.0) -> 1 | C78: =IFERROR(__xludf.DUMMYFUNCTION("""COMPUTED_VALUE"""),863.0) -> 863 | D78: =IFERROR(__xludf.DUMMYFUNCTION("""COMPUTED_VALUE"""),821.0) -> 821
A79: =IFERROR(__xludf.DUMMYFUNCTION("""COMPUTED_VALUE"""),69138.0) -> 69138 | B79: =IFERROR(__xludf.DUMMYFUNCTION("""COMPUTED_VALUE"""),1.0) -> 1 | C79: =IFERROR(__xludf.DUMMYFUNCTION("""COMPUTED_VALUE"""),43.0) -> 43 | D79: =IFERROR(__xludf.DUMMYFUNCTION("""COMPUTED_VALUE"""),27.0) -> 27
A80: =IFERROR(__xludf.DUMMYFUNCTION("""COMPUTED_VALUE"""),74828.0) -> 74828 | B80: =IFERROR(__xludf.DUMMYFUNCTION("""COMPUTED_VALUE"""),0.0) -> 0 | C80: =IFERROR(__xludf.DUMMYFUNCTION("""COMPUTED_VALUE"""),654.0) -> 654 | D80: =IFERROR(__xludf.DUMMYFUNCTION("""COMPUTED_VALUE"""),613.0) -> 613
A81: =IFERROR(__xludf.DUMMYFUNCTION("""COMPUTED_VALUE"""),74884.0) -> 74884 | B81: =IFERROR(__xludf.DUMMYFUNCTION("""COMPUTED_VALUE"""),1.0) -> 1 | C81: =IFERROR(__xludf.DUMMYFUNCTION("""COMPUTED_VALUE"""),2.0) -> 2 | D81: =IFERROR(__xludf.DUMMYFUNCTION("""COMPUTED_VALUE"""),2.0) -> 2
A82: =IFERROR(__xludf.DUMMYFUNCTION("""COMPUTED_VALUE"""),127232.0) -> 127232 | B82: =IFERROR(__xludf.DUMMYFUNCTION("""COMPUTED_VALUE"""),1.0) -> 1 | C82: =IFERROR(__xludf.DUMMYFUNCTION("""COMPUTED_VALUE"""),705.0) -> 705 | D82: =IFERROR(__xludf.DUMMYFUNCTION("""COMPUTED_VALUE"""),648.0) -> 648
A83: =IFERROR(__xludf.DUMMYFUNCTION("""COMPUTED_VALUE"""),82979.0) -> 82979 | B83: =IFERROR(__xludf.DUMMYFUNCTION("""COMPUTED_VALUE"""),1.0) -> 1 | C83: =IFERROR(__xludf.DUMMYFUNCTION("""COMPUTED_VALUE"""),774.0) -> 774 | D83: =IFERROR(__xludf.DUMMYFUNCTION("""COMPUTED_VALUE"""),723.0) -> 723
A84: =IFERROR(__xludf.DUMMYFUNCTION("""COMPUTED_VALUE"""),18138.0) -> 18138 | B84: =IFERROR(__xludf.DUMMYFUNCTION("""COMPUTED_VALUE"""),0.0) -> 0 | C84: =IFERROR(__xludf.DUMMYFUNCTION("""COMPUTED_VALUE"""),571.0) -> 571 | D84: =IFERROR(__xludf.DUMMYFUNCTION("""COMPUTED_VALUE"""),353.0) -> 353
A85: =IFERROR(__xludf.DUMMYFUNCTION("""COMPUTED_VALUE"""),127003.0) -> 127003 | B85: =IFERROR(__xludf.DUMMYFUNCTION("""COMPUTED_VALUE"""),0.0) -> 0 | C85: =IFERROR(__xludf.DUMMYFUNCTION("""COMPUTED_VALUE"""),735.0) -> 735 | D85: =IFERROR(__xludf.DUMMYFUNCTION("""COMPUTED_VALUE"""),384.0) -> 384
A86: =IFERROR(__xludf.DUMMYFUNCTION("""COMPUTED_VALUE"""),6036.0) -> 6036 | B86: =IFERROR(__xludf.DUMMYFUNCTION("""COMPUTED_VALUE"""),1.0) -> 1 | C86: =IFERROR(__xludf.DUMMYFUNCTION("""COMPUTED_VALUE"""),429.0) -> 429 | D86: =IFERROR(__xludf.DUMMYFUNCTION("""COMPUTED_VALUE"""),420.0) -> 420
A87: =IFERROR(__xludf.DUMMYFUNCTION("""COMPUTED_VALUE"""),6046.0) -> 6046 | B87: =IFERROR(__xludf.DUMMYFUNCTION("""COMPUTED_VALUE"""),0.0) -> 0 | C87: =IFERROR(__xludf.DUMMYFUNCTION("""COMPUTED_VALUE"""),732.0) -> 732 | D87: =IFERROR(__xludf.DUMMYFUNCTION("""COMPUTED_VALUE"""),319.0) -> 319
A88: =IFERROR(__xludf.DUMMYFUNCTION("""COMPUTED_VALUE"""),6037.0) -> 6037 | B88: =IFERROR(__xludf.DUMMYFUNCTION("""COMPUTED_VALUE"""),0.0) -> 0 | C88: =IFERROR(__xludf.DUMMYFUNCTION("""COMPUTED_VALUE"""),271.0) -> 271 | D88: =IFERROR(__xludf.DUMMYFUNCTION("""COMPUTED_VALUE"""),227.0) -> 227
A89: =IFERROR(__xludf.DUMMYFUNCTION("""COMPUTED_VALUE"""),6026.0) -> 6026 | B89: =IFERROR(__xludf.DUMMYFUNCTION("""COMPUTED_VALUE"""),1.0) -> 1 | C89: =IFERROR(__xludf.DUMMYFUNCTION("""COMPUTED_VALUE"""),111.0) -> 111 | D89: =IFERROR(__xludf.DUMMYFUNCTION("""COMPUTED_VALUE"""),23.0) -> 23
A90: =IFERROR(__xludf.DUMMYFUNCTION("""COMPUTED_VALUE"""),47431.0) -> 47431 | B90: =IFERROR(__xludf.DUMMYFUNCTION("""COMPUTED_VALUE"""),0.0) -> 0 | C90: =IFERROR(__xludf.DUMMYFUNCTION("""COMPUTED_VALUE"""),81.0) -> 81 | D90: =IFERROR(__xludf.DUMMYFUNCTION("""COMPUTED_VALUE"""),6.0) -> 6
A91: =IFERROR(__xludf.DUMMYFUNCTION("""COMPUTED_VALUE"""),82914.0) -> 82914 | B91: =IFERROR(__xludf.DUMMYFUNCTION("""COMPUTED_VALUE"""),1.0) -> 1 | C91: =IFERROR(__xludf.DUMMYFUNCTION("""COMPUTED_VALUE"""),486.0) -> 486 | D91: =IFERROR(__xludf.DUMMYFUNCTION("""COMPUTED_VALUE"""),345.0) -> 345
A92: =IFERROR(__xludf.DUMMYFUNCTION("""COMPUTED_VALUE"""),6044.0) -> 6044 | B92: =IFERROR(__xludf.DUMMYFUNCTION("""COMPUTED_VALUE"""),1.0) -> 1 | C92: =IFERROR(__xludf.DUMMYFUNCTION("""COMPUTED_VALUE"""),197.0) -> 197 | D92: =IFERROR(__xludf.DUMMYFUNCTION("""COMPUTED_VALUE"""),167.0) -> 167
A93: =IFERROR(__xludf.DUMMYFUNCTION("""COMPUTED_VALUE"""),82913.0) -> 82913 | B93: =IFERROR(__xludf.DUMMYFUNCTION("""COMPUTED_VALUE"""),1.0) -> 1 | C93: =IFERROR(__xludf.DUMMYFUNCTION("""COMPUTED_VALUE"""),196.0) -> 196 | D93: =IFERROR(__xludf.DUMMYFUNCTION("""COMPUTED_VALUE"""),116.0) -> 116
A94: =IFERROR(__xludf.DUMMYFUNCTION("""COMPUTED_VALUE"""),82922.0) -> 82922 | B94: =IFERROR(__xludf.DUMMYFUNCTION("""COMPUTED_VALUE"""),1.0) -> 1 | C94: =IFERROR(__xludf.DUMMYFUNCTION("""COMPUTED_VALUE"""),783.0) -> 783 | D94: =IFERROR(__xludf.DUMMYFUNCTION("""COMPUTED_VALUE"""),107.0) -> 107
A95: =IFERROR(__xludf.DUMMYFUNCTION("""COMPUTED_VALUE"""),6045.0) -> 6045 | B95: =IFERROR(__xludf.DUMMYFUNCTION("""COMPUTED_VALUE"""),1.0) -> 1 | C95: =IFERROR(__xludf.DUMMYFUNCTION("""COMPUTED_VALUE"""),0.0) -> 0 | D95: =IFERROR(__xludf.DUMMYFUNCTION("""COMPUTED_VALUE"""),0.0) -> 0
A96: =IFERROR(__xludf.DUMMYFUNCTION("""COMPUTED_VALUE"""),6027.0) -> 6027 | B96: =IFERROR(__xludf.DUMMYFUNCTION("""COMPUTED_VALUE"""),0.0) -> 0 | C96: =IFERROR(__xludf.DUMMYFUNCTION("""COMPUTED_VALUE"""),282.0) -> 282 | D96: =IFERROR(__xludf.DUMMYFUNCTION("""COMPUTED_VALUE"""),174.0) -> 174
A97: =IFERROR(__xludf.DUMMYFUNCTION("""COMPUTED_VALUE"""),97088.0) -> 97088 | B97: =IFERROR(__xludf.DUMMYFUNCTION("""COMPUTED_VALUE"""),1.0) -> 1 | C97: =IFERROR(__xludf.DUMMYFUNCTION("""COMPUTED_VALUE"""),356.0) -> 356 | D97: =IFERROR(__xludf.DUMMYFUNCTION("""COMPUTED_VALUE"""),290.0) -> 290
A98: =IFERROR(__xludf.DUMMYFUNCTION("""COMPUTED_VALUE"""),122235.0) -> 122235 | B98: =IFERROR(__xludf.DUMMYFUNCTION("""COMPUTED_VALUE"""),1.0) -> 1 | C98: =IFERROR(__xludf.DUMMYFUNCTION("""COMPUTED_VALUE"""),941.0) -> 941 | D98: =IFERROR(__xludf.DUMMYFUNCTION("""COMPUTED_VALUE"""),126.0) -> 126
A99: =IFERROR(__xludf.DUMMYFUNCTION("""COMPUTED_VALUE"""),119887.0) -> 119887 | B99: =IFERROR(__xludf.DUMMYFUNCTION("""COMPUTED_VALUE"""),1.0) -> 1 | C99: =IFERROR(__xludf.DUMMYFUNCTION("""COMPUTED_VALUE"""),732.0) -> 732 | D99: =IFERROR(__xludf.DUMMYFUNCTION("""COMPUTED_VALUE"""),498.0) -> 498
A100: =IFERROR(__xludf.DUMMYFUNCTION("""COMPUTED_VALUE"""),97980.0) -> 97980 | B100: =IFERROR(__xludf.DUMMYFUNCTION("""COMPUTED_VALUE"""),0.0) -> 0 | C100: =IFERROR(__xludf.DUMMYFUNCTION("""COMPUTED_VALUE"""),366.0) -> 366 | D100: =IFERROR(__xludf.DUMMYFUNCTION("""COMPUTED_VALUE"""),344.0) -> 344
...

Sheet Product
A1: =IFERROR(__xludf.DUMMYFUNCTION("IMPORTRANGE(""https://docs.google.com/spreadsheets/d/1n4Zg-vRlTZzP5FR21bautORUV5kNU7wGUHO1GM0ql3s/edit"",""product!A:Z"")"),"product_id") -> product_id | B1: =IFERROR(__xludf.DUMMYFUNCTION("""COMPUTED_VALUE"""),"category_1") -> category_1 | C1: =IFERROR(__xludf.DUMMYFUNCTION("""COMPUTED_VALUE"""),"category_2") -> category_2 | D1: =IFERROR(__xludf.DUMMYFUNCTION("""COMPUTED_VALUE"""),"category_3") -> category_3 | E1: =IFERROR(__xludf.DUMMYFUNCTION("""COMPUTED_VALUE"""),"pp_cat") -> pp_cat
A2: =IFERROR(__xludf.DUMMYFUNCTION("""COMPUTED_VALUE"""),112463.0) -> 112463 | B2: =IFERROR(__xludf.DUMMYFUNCTION("""COMPUTED_VALUE"""),"Fiction") -> Fiction | C2: =IFERROR(__xludf.DUMMYFUNCTION("""COMPUTED_VALUE"""),"Literary Fiction") -> Literary Fiction | D2: =IFERROR(__xludf.DUMMYFUNCTION("""COMPUTED_VALUE"""),"Blue Oak Publishing") -> Blue Oak Publishing | E2: =IFERROR(__xludf.DUMMYFUNCTION("""COMPUTED_VALUE"""),4.1) -> 4.1
A3: =IFERROR(__xludf.DUMMYFUNCTION("""COMPUTED_VALUE"""),112481.0) -> 112481 | B3: =IFERROR(__xludf.DUMMYFUNCTION("""COMPUTED_VALUE"""),"Fiction") -> Fiction | C3: =IFERROR(__xludf.DUMMYFUNCTION("""COMPUTED_VALUE"""),"Literary Fiction") -> Literary Fiction | D3: =IFERROR(__xludf.DUMMYFUNCTION("""COMPUTED_VALUE"""),"Blue Oak Publishing") -> Blue Oak Publishing | E3: =IFERROR(__xludf.DUMMYFUNCTION("""COMPUTED_VALUE"""),5.86) -> 5.86
A4: =IFERROR(__xludf.DUMMYFUNCTION("""COMPUTED_VALUE"""),13346.0) -> 13346 | B4: =IFERROR(__xludf.DUMMYFUNCTION("""COMPUTED_VALUE"""),"Fiction") -> Fiction | C4: =IFERROR(__xludf.DUMMYFUNCTION("""COMPUTED_VALUE"""),"Literary Fiction") -> Literary Fiction | D4: =IFERROR(__xludf.DUMMYFUNCTION("""COMPUTED_VALUE"""),"Blue Oak Publishing") -> Blue Oak Publishing | E4: =IFERROR(__xludf.DUMMYFUNCTION("""COMPUTED_VALUE"""),2.16) -> 2.16
A5: =IFERROR(__xludf.DUMMYFUNCTION("""COMPUTED_VALUE"""),112454.0) -> 112454 | B5: =IFERROR(__xludf.DUMMYFUNCTION("""COMPUTED_VALUE"""),"Fiction") -> Fiction | C5: =IFERROR(__xludf.DUMMYFUNCTION("""COMPUTED_VALUE"""),"Literary Fiction") -> Literary Fiction | D5: =IFERROR(__xludf.DUMMYFUNCTION("""COMPUTED_VALUE"""),"Blue Oak Publishing") -> Blue Oak Publishing | E5: =IFERROR(__xludf.DUMMYFUNCTION("""COMPUTED_VALUE"""),0.93) -> 0.93
A6: =IFERROR(__xludf.DUMMYFUNCTION("""COMPUTED_VALUE"""),112461.0) -> 112461 | B6: =IFERROR(__xludf.DUMMYFUNCTION("""COMPUTED_VALUE"""),"Fiction") -> Fiction | C6: =IFERROR(__xludf.DUMMYFUNCTION("""COMPUTED_VALUE"""),"Literary Fiction") -> Literary Fiction | D6: =IFERROR(__xludf.DUMMYFUNCTION("""COMPUTED_VALUE"""),"Blue Oak Publishing") -> Blue Oak Publishing | E6: =IFERROR(__xludf.DUMMYFUNCTION("""COMPUTED_VALUE"""),1.07) -> 1.07
A7: =IFERROR(__xludf.DUMMYFUNCTION("""COMPUTED_VALUE"""),106532.0) -> 106532 | B7: =IFERROR(__xludf.DUMMYFUNCTION("""COMPUTED_VALUE"""),"Fiction") -> Fiction | C7: =IFERROR(__xludf.DUMMYFUNCTION("""COMPUTED_VALUE"""),"Literary Fiction") -> Literary Fiction | D7: =IFERROR(__xludf.DUMMYFUNCTION("""COMPUTED_VALUE"""),"Silver Leaf Press") -> Silver Leaf Press | E7: =IFERROR(__xludf.DUMMYFUNCTION("""COMPUTED_VALUE"""),8.9) -> 8.9
A8: =IFERROR(__xludf.DUMMYFUNCTION("""COMPUTED_VALUE"""),121135.0) -> 121135 | B8: =IFERROR(__xludf.DUMMYFUNCTION("""COMPUTED_VALUE"""),"Fiction") -> Fiction | C8: =IFERROR(__xludf.DUMMYFUNCTION("""COMPUTED_VALUE"""),"Literary Fiction") -> Literary Fiction | D8: =IFERROR(__xludf.DUMMYFUNCTION("""COMPUTED_VALUE"""),"Silver Leaf Press") -> Silver Leaf Press | E8: =IFERROR(__xludf.DUMMYFUNCTION("""COMPUTED_VALUE"""),8.84) -> 8.84
A9: =IFERROR(__xludf.DUMMYFUNCTION("""COMPUTED_VALUE"""),128362.0) -> 128362 | B9: =IFERROR(__xludf.DUMMYFUNCTION("""COMPUTED_VALUE"""),"History") -> History | C9: =IFERROR(__xludf.DUMMYFUNCTION("""COMPUTED_VALUE"""),"Mystery") -> Mystery | D9: =IFERROR(__xludf.DUMMYFUNCTION("""COMPUTED_VALUE"""),"Northbridge Books") -> Northbridge Books | E9: =IFERROR(__xludf.DUMMYFUNCTION("""COMPUTED_VALUE"""),4.89) -> 4.89
A10: =IFERROR(__xludf.DUMMYFUNCTION("""COMPUTED_VALUE"""),71200.0) -> 71200 | B10: =IFERROR(__xludf.DUMMYFUNCTION("""COMPUTED_VALUE"""),"History") -> History | C10: =IFERROR(__xludf.DUMMYFUNCTION("""COMPUTED_VALUE"""),"Mystery") -> Mystery | D10: =IFERROR(__xludf.DUMMYFUNCTION("""COMPUTED_VALUE"""),"Riverstone Publishing") -> Riverstone Publishing | E10: =IFERROR(__xludf.DUMMYFUNCTION("""COMPUTED_VALUE"""),1.94) -> 1.94
A11: =IFERROR(__xludf.DUMMYFUNCTION("""COMPUTED_VALUE"""),19812.0) -> 19812 | B11: =IFERROR(__xludf.DUMMYFUNCTION("""COMPUTED_VALUE"""),"History") -> History | C11: =IFERROR(__xludf.DUMMYFUNCTION("""COMPUTED_VALUE"""),"Mystery") -> Mystery | D11: =IFERROR(__xludf.DUMMYFUNCTION("""COMPUTED_VALUE"""),"Riverstone Publishing") -> Riverstone Publishing | E11: =IFERROR(__xludf.DUMMYFUNCTION("""COMPUTED_VALUE"""),1.77) -> 1.77
A12: =IFERROR(__xludf.DUMMYFUNCTION("""COMPUTED_VALUE"""),122259.0) -> 122259 | B12: =IFERROR(__xludf.DUMMYFUNCTION("""COMPUTED_VALUE"""),"History") -> History | C12: =IFERROR(__xludf.DUMMYFUNCTION("""COMPUTED_VALUE"""),"Mystery") -> Mystery | D12: =IFERROR(__xludf.DUMMYFUNCTION("""COMPUTED_VALUE"""),"Golden Quill Press") -> Golden Quill Press | E12: =IFERROR(__xludf.DUMMYFUNCTION("""COMPUTED_VALUE"""),2.88) -> 2.88
A13: =IFERROR(__xludf.DUMMYFUNCTION("""COMPUTED_VALUE"""),199526.0) -> 199526 | B13: =IFERROR(__xludf.DUMMYFUNCTION("""COMPUTED_VALUE"""),"History") -> History | C13: =IFERROR(__xludf.DUMMYFUNCTION("""COMPUTED_VALUE"""),"Mystery") -> Mystery | D13: =IFERROR(__xludf.DUMMYFUNCTION("""COMPUTED_VALUE"""),"Golden Quill Press") -> Golden Quill Press | E13: =IFERROR(__xludf.DUMMYFUNCTION("""COMPUTED_VALUE"""),1.83) -> 1.83
A14: =IFERROR(__xludf.DUMMYFUNCTION("""COMPUTED_VALUE"""),140581.0) -> 140581 | B14: =IFERROR(__xludf.DUMMYFUNCTION("""COMPUTED_VALUE"""),"History") -> History | C14: =IFERROR(__xludf.DUMMYFUNCTION("""COMPUTED_VALUE"""),"Mystery") -> Mystery | D14: =IFERROR(__xludf.DUMMYFUNCTION("""COMPUTED_VALUE"""),"Golden Quill Press") -> Golden Quill Press | E14: =IFERROR(__xludf.DUMMYFUNCTION("""COMPUTED_VALUE"""),4.04) -> 4.04
A15: =IFERROR(__xludf.DUMMYFUNCTION("""COMPUTED_VALUE"""),118383.0) -> 118383 | B15: =IFERROR(__xludf.DUMMYFUNCTION("""COMPUTED_VALUE"""),"History") -> History | C15: =IFERROR(__xludf.DUMMYFUNCTION("""COMPUTED_VALUE"""),"Mystery") -> Mystery | D15: =IFERROR(__xludf.DUMMYFUNCTION("""COMPUTED_VALUE"""),"Golden Quill Press") -> Golden Quill Press | E15: =IFERROR(__xludf.DUMMYFUNCTION("""COMPUTED_VALUE"""),1.5) -> 1.5
A16: =IFERROR(__xludf.DUMMYFUNCTION("""COMPUTED_VALUE"""),122262.0) -> 122262 | B16: =IFERROR(__xludf.DUMMYFUNCTION("""COMPUTED_VALUE"""),"History") -> History | C16: =IFERROR(__xludf.DUMMYFUNCTION("""COMPUTED_VALUE"""),"Mystery") -> Mystery | D16: =IFERROR(__xludf.DUMMYFUNCTION("""COMPUTED_VALUE"""),"Golden Quill Press") -> Golden Quill Press | E16: =IFERROR(__xludf.DUMMYFUNCTION("""COMPUTED_VALUE"""),2.65) -> 2.65
A17: =IFERROR(__xludf.DUMMYFUNCTION("""COMPUTED_VALUE"""),141879.0) -> 141879 | B17: =IFERROR(__xludf.DUMMYFUNCTION("""COMPUTED_VALUE"""),"History") -> History | C17: =IFERROR(__xludf.DUMMYFUNCTION("""COMPUTED_VALUE"""),"Mystery") -> Mystery | D17: =IFERROR(__xludf.DUMMYFUNCTION("""COMPUTED_VALUE"""),"Golden Quill Press") -> Golden Quill Press | E17: =IFERROR(__xludf.DUMMYFUNCTION("""COMPUTED_VALUE"""),2.04) -> 2.04
A18: =IFERROR(__xludf.DUMMYFUNCTION("""COMPUTED_VALUE"""),19826.0) -> 19826 | B18: =IFERROR(__xludf.DUMMYFUNCTION("""COMPUTED_VALUE"""),"History") -> History | C18: =IFERROR(__xludf.DUMMYFUNCTION("""COMPUTED_VALUE"""),"Thriller") -> Thriller | D18: =IFERROR(__xludf.DUMMYFUNCTION("""COMPUTED_VALUE"""),"Harbor Light Books") -> Harbor Light Books | E18: =IFERROR(__xludf.DUMMYFUNCTION("""COMPUTED_VALUE"""),2.88) -> 2.88
A19: =IFERROR(__xludf.DUMMYFUNCTION("""COMPUTED_VALUE"""),93039.0) -> 93039 | B19: =IFERROR(__xludf.DUMMYFUNCTION("""COMPUTED_VALUE"""),"History") -> History | C19: =IFERROR(__xludf.DUMMYFUNCTION("""COMPUTED_VALUE"""),"Thriller") -> Thriller | D19: =IFERROR(__xludf.DUMMYFUNCTION("""COMPUTED_VALUE"""),"Harbor Light Books") -> Harbor Light Books | E19: =IFERROR(__xludf.DUMMYFUNCTION("""COMPUTED_VALUE"""),3.23) -> 3.23
A20: =IFERROR(__xludf.DUMMYFUNCTION("""COMPUTED_VALUE"""),128213.0) -> 128213 | B20: =IFERROR(__xludf.DUMMYFUNCTION("""COMPUTED_VALUE"""),"History") -> History | C20: =IFERROR(__xludf.DUMMYFUNCTION("""COMPUTED_VALUE"""),"Thriller") -> Thriller | D20: =IFERROR(__xludf.DUMMYFUNCTION("""COMPUTED_VALUE"""),"Harbor Light Books") -> Harbor Light Books | E20: =IFERROR(__xludf.DUMMYFUNCTION("""COMPUTED_VALUE"""),4.72) -> 4.72
A21: =IFERROR(__xludf.DUMMYFUNCTION("""COMPUTED_VALUE"""),83797.0) -> 83797 | B21: =IFERROR(__xludf.DUMMYFUNCTION("""COMPUTED_VALUE"""),"History") -> History | C21: =IFERROR(__xludf.DUMMYFUNCTION("""COMPUTED_VALUE"""),"Thriller") -> Thriller | D21: =IFERROR(__xludf.DUMMYFUNCTION("""COMPUTED_VALUE"""),"Harbor Light Books") -> Harbor Light Books | E21: =IFERROR(__xludf.DUMMYFUNCTION("""COMPUTED_VALUE"""),6.05) -> 6.05
A22: =IFERROR(__xludf.DUMMYFUNCTION("""COMPUTED_VALUE"""),19831.0) -> 19831 | B22: =IFERROR(__xludf.DUMMYFUNCTION("""COMPUTED_VALUE"""),"History") -> History | C22: =IFERROR(__xludf.DUMMYFUNCTION("""COMPUTED_VALUE"""),"Thriller") -> Thriller | D22: =IFERROR(__xludf.DUMMYFUNCTION("""COMPUTED_VALUE"""),"Harbor Light Books") -> Harbor Light Books | E22: =IFERROR(__xludf.DUMMYFUNCTION("""COMPUTED_VALUE"""),3.86) -> 3.86
A23: =IFERROR(__xludf.DUMMYFUNCTION("""COMPUTED_VALUE"""),93025.0) -> 93025 | B23: =IFERROR(__xludf.DUMMYFUNCTION("""COMPUTED_VALUE"""),"History") -> History | C23: =IFERROR(__xludf.DUMMYFUNCTION("""COMPUTED_VALUE"""),"Thriller") -> Thriller | D23: =IFERROR(__xludf.DUMMYFUNCTION("""COMPUTED_VALUE"""),"Harbor Light Books") -> Harbor Light Books | E23: =IFERROR(__xludf.DUMMYFUNCTION("""COMPUTED_VALUE"""),2.31) -> 2.31
A24: =IFERROR(__xludf.DUMMYFUNCTION("""COMPUTED_VALUE"""),81624.0) -> 81624 | B24: =IFERROR(__xludf.DUMMYFUNCTION("""COMPUTED_VALUE"""),"History") -> History | C24: =IFERROR(__xludf.DUMMYFUNCTION("""COMPUTED_VALUE"""),"Thriller") -> Thriller | D24: =IFERROR(__xludf.DUMMYFUNCTION("""COMPUTED_VALUE"""),"Harbor Light Books") -> Harbor Light Books | E24: =IFERROR(__xludf.DUMMYFUNCTION("""COMPUTED_VALUE"""),7.35) -> 7.35
A25: =IFERROR(__xludf.DUMMYFUNCTION("""COMPUTED_VALUE"""),92913.0) -> 92913 | B25: =IFERROR(__xludf.DUMMYFUNCTION("""COMPUTED_VALUE"""),"History") -> History | C25: =IFERROR(__xludf.DUMMYFUNCTION("""COMPUTED_VALUE"""),"Thriller") -> Thriller | D25: =IFERROR(__xludf.DUMMYFUNCTION("""COMPUTED_VALUE"""),"Harbor Light Books") -> Harbor Light Books | E25: =IFERROR(__xludf.DUMMYFUNCTION("""COMPUTED_VALUE"""),7.02) -> 7.02
A26: =IFERROR(__xludf.DUMMYFUNCTION("""COMPUTED_VALUE"""),126983.0) -> 126983 | B26: =IFERROR(__xludf.DUMMYFUNCTION("""COMPUTED_VALUE"""),"History") -> History | C26: =IFERROR(__xludf.DUMMYFUNCTION("""COMPUTED_VALUE"""),"Thriller") -> Thriller | D26: =IFERROR(__xludf.DUMMYFUNCTION("""COMPUTED_VALUE"""),"Harbor Light Books") -> Harbor Light Books | E26: =IFERROR(__xludf.DUMMYFUNCTION("""COMPUTED_VALUE"""),2.69) -> 2.69
A27: =IFERROR(__xludf.DUMMYFUNCTION("""COMPUTED_VALUE"""),118226.0) -> 118226 | B27: =IFERROR(__xludf.DUMMYFUNCTION("""COMPUTED_VALUE"""),"History") -> History | C27: =IFERROR(__xludf.DUMMYFUNCTION("""COMPUTED_VALUE"""),"Thriller") -> Thriller | D27: =IFERROR(__xludf.DUMMYFUNCTION("""COMPUTED_VALUE"""),"Harbor Light Books") -> Harbor Light Books | E27: =IFERROR(__xludf.DUMMYFUNCTION("""COMPUTED_VALUE"""),1.89) -> 1.89
A28: =IFERROR(__xludf.DUMMYFUNCTION("""COMPUTED_VALUE"""),48618.0) -> 48618 | B28: =IFERROR(__xludf.DUMMYFUNCTION("""COMPUTED_VALUE"""),"History") -> History | C28: =IFERROR(__xludf.DUMMYFUNCTION("""COMPUTED_VALUE"""),"Thriller") -> Thriller | D28: =IFERROR(__xludf.DUMMYFUNCTION("""COMPUTED_VALUE"""),"Harbor Light Books") -> Harbor Light Books | E28: =IFERROR(__xludf.DUMMYFUNCTION("""COMPUTED_VALUE"""),2.39) -> 2.39
A29: =IFERROR(__xludf.DUMMYFUNCTION("""COMPUTED_VALUE"""),93037.0) -> 93037 | B29: =IFERROR(__xludf.DUMMYFUNCTION("""COMPUTED_VALUE"""),"History") -> History | C29: =IFERROR(__xludf.DUMMYFUNCTION("""COMPUTED_VALUE"""),"Thriller") -> Thriller | D29: =IFERROR(__xludf.DUMMYFUNCTION("""COMPUTED_VALUE"""),"Harbor Light Books") -> Harbor Light Books | E29: =IFERROR(__xludf.DUMMYFUNCTION("""COMPUTED_VALUE"""),2.93) -> 2.93
A30: =IFERROR(__xludf.DUMMYFUNCTION("""COMPUTED_VALUE"""),126984.0) -> 126984 | B30: =IFERROR(__xludf.DUMMYFUNCTION("""COMPUTED_VALUE"""),"History") -> History | C30: =IFERROR(__xludf.DUMMYFUNCTION("""COMPUTED_VALUE"""),"Thriller") -> Thriller | D30: =IFERROR(__xludf.DUMMYFUNCTION("""COMPUTED_VALUE"""),"Harbor Light Books") -> Harbor Light Books | E30: =IFERROR(__xludf.DUMMYFUNCTION("""COMPUTED_VALUE"""),2.02) -> 2.02
A31: =IFERROR(__xludf.DUMMYFUNCTION("""COMPUTED_VALUE"""),47393.0) -> 47393 | B31: =IFERROR(__xludf.DUMMYFUNCTION("""COMPUTED_VALUE"""),"History") -> History | C31: =IFERROR(__xludf.DUMMYFUNCTION("""COMPUTED_VALUE"""),"Thriller") -> Thriller | D31: =IFERROR(__xludf.DUMMYFUNCTION("""COMPUTED_VALUE"""),"Harbor Light Books") -> Harbor Light Books | E31: =IFERROR(__xludf.DUMMYFUNCTION("""COMPUTED_VALUE"""),2.66) -> 2.66
A32: =IFERROR(__xludf.DUMMYFUNCTION("""COMPUTED_VALUE"""),128214.0) -> 128214 | B32: =IFERROR(__xludf.DUMMYFUNCTION("""COMPUTED_VALUE"""),"History") -> History | C32: =IFERROR(__xludf.DUMMYFUNCTION("""COMPUTED_VALUE"""),"Thriller") -> Thriller | D32: =IFERROR(__xludf.DUMMYFUNCTION("""COMPUTED_VALUE"""),"Harbor Light Books") -> Harbor Light Books | E32: =IFERROR(__xludf.DUMMYFUNCTION("""COMPUTED_VALUE"""),4.35) -> 4.35
A33: =IFERROR(__xludf.DUMMYFUNCTION("""COMPUTED_VALUE"""),83802.0) -> 83802 | B33: =IFERROR(__xludf.DUMMYFUNCTION("""COMPUTED_VALUE"""),"History") -> History | C33: =IFERROR(__xludf.DUMMYFUNCTION("""COMPUTED_VALUE"""),"Thriller") -> Thriller | D33: =IFERROR(__xludf.DUMMYFUNCTION("""COMPUTED_VALUE"""),"Harbor Light Books") -> Harbor Light Books | E33: =IFERROR(__xludf.DUMMYFUNCTION("""COMPUTED_VALUE"""),3.33) -> 3.33
A34: =IFERROR(__xludf.DUMMYFUNCTION("""COMPUTED_VALUE"""),48625.0) -> 48625 | B34: =IFERROR(__xludf.DUMMYFUNCTION("""COMPUTED_VALUE"""),"History") -> History | C34: =IFERROR(__xludf.DUMMYFUNCTION("""COMPUTED_VALUE"""),"Thriller") -> Thriller | D34: =IFERROR(__xludf.DUMMYFUNCTION("""COMPUTED_VALUE"""),"Harbor Light Books") -> Harbor Light Books | E34: =IFERROR(__xludf.DUMMYFUNCTION("""COMPUTED_VALUE"""),4.12) -> 4.12
A35: =IFERROR(__xludf.DUMMYFUNCTION("""COMPUTED_VALUE"""),83602.0) -> 83602 | B35: =IFERROR(__xludf.DUMMYFUNCTION("""COMPUTED_VALUE"""),"History") -> History | C35: =IFERROR(__xludf.DUMMYFUNCTION("""COMPUTED_VALUE"""),"Thriller") -> Thriller | D35: =IFERROR(__xludf.DUMMYFUNCTION("""COMPUTED_VALUE"""),"Harbor Light Books") -> Harbor Light Books | E35: =IFERROR(__xludf.DUMMYFUNCTION("""COMPUTED_VALUE"""),12.34) -> 12.34
A36: =IFERROR(__xludf.DUMMYFUNCTION("""COMPUTED_VALUE"""),98867.0) -> 98867 | B36: =IFERROR(__xludf.DUMMYFUNCTION("""COMPUTED_VALUE"""),"History") -> History | C36: =IFERROR(__xludf.DUMMYFUNCTION("""COMPUTED_VALUE"""),"Thriller") -> Thriller | D36: =IFERROR(__xludf.DUMMYFUNCTION("""COMPUTED_VALUE"""),"Ironwood Publishing") -> Ironwood Publishing | E36: =IFERROR(__xludf.DUMMYFUNCTION("""COMPUTED_VALUE"""),4.2) -> 4.2
A37: =IFERROR(__xludf.DUMMYFUNCTION("""COMPUTED_VALUE"""),127042.0) -> 127042 | B37: =IFERROR(__xludf.DUMMYFUNCTION("""COMPUTED_VALUE"""),"History") -> History | C37: =IFERROR(__xludf.DUMMYFUNCTION("""COMPUTED_VALUE"""),"Thriller") -> Thriller | D37: =IFERROR(__xludf.DUMMYFUNCTION("""COMPUTED_VALUE"""),"Ironwood Publishing") -> Ironwood Publishing | E37: =IFERROR(__xludf.DUMMYFUNCTION("""COMPUTED_VALUE"""),4.05) -> 4.05
A38: =IFERROR(__xludf.DUMMYFUNCTION("""COMPUTED_VALUE"""),127241.0) -> 127241 | B38: =IFERROR(__xludf.DUMMYFUNCTION("""COMPUTED_VALUE"""),"History") -> History | C38: =IFERROR(__xludf.DUMMYFUNCTION("""COMPUTED_VALUE"""),"Thriller") -> Thriller | D38: =IFERROR(__xludf.DUMMYFUNCTION("""COMPUTED_VALUE"""),"Maple Grove Press") -> Maple Grove Press | E38: =IFERROR(__xludf.DUMMYFUNCTION("""COMPUTED_VALUE"""),12.24) -> 12.24
A39: =IFERROR(__xludf.DUMMYFUNCTION("""COMPUTED_VALUE"""),118220.0) -> 118220 | B39: =IFERROR(__xludf.DUMMYFUNCTION("""COMPUTED_VALUE"""),"History") -> History | C39: =IFERROR(__xludf.DUMMYFUNCTION("""COMPUTED_VALUE"""),"Thriller") -> Thriller | D39: =IFERROR(__xludf.DUMMYFUNCTION("""COMPUTED_VALUE"""),"Maple Grove Press") -> Maple Grove Press | E39: =IFERROR(__xludf.DUMMYFUNCTION("""COMPUTED_VALUE"""),8.54) -> 8.54
A40: =IFERROR(__xludf.DUMMYFUNCTION("""COMPUTED_VALUE"""),128216.0) -> 128216 | B40: =IFERROR(__xludf.DUMMYFUNCTION("""COMPUTED_VALUE"""),"History") -> History | C40: =IFERROR(__xludf.DUMMYFUNCTION("""COMPUTED_VALUE"""),"Thriller") -> Thriller | D40: =IFERROR(__xludf.DUMMYFUNCTION("""COMPUTED_VALUE"""),"Maple Grove Press") -> Maple Grove Press | E40: =IFERROR(__xludf.DUMMYFUNCTION("""COMPUTED_VALUE"""),12.08) -> 12.08
A41: =IFERROR(__xludf.DUMMYFUNCTION("""COMPUTED_VALUE"""),93049.0) -> 93049 | B41: =IFERROR(__xludf.DUMMYFUNCTION("""COMPUTED_VALUE"""),"History") -> History | C41: =IFERROR(__xludf.DUMMYFUNCTION("""COMPUTED_VALUE"""),"Thriller") -> Thriller | D41: =IFERROR(__xludf.DUMMYFUNCTION("""COMPUTED_VALUE"""),"Maple Grove Press") -> Maple Grove Press | E41: =IFERROR(__xludf.DUMMYFUNCTION("""COMPUTED_VALUE"""),11.06) -> 11.06
A42: =IFERROR(__xludf.DUMMYFUNCTION("""COMPUTED_VALUE"""),118216.0) -> 118216 | B42: =IFERROR(__xludf.DUMMYFUNCTION("""COMPUTED_VALUE"""),"History") -> History | C42: =IFERROR(__xludf.DUMMYFUNCTION("""COMPUTED_VALUE"""),"Thriller") -> Thriller | D42: =IFERROR(__xludf.DUMMYFUNCTION("""COMPUTED_VALUE"""),"Maple Grove Press") -> Maple Grove Press | E42: =IFERROR(__xludf.DUMMYFUNCTION("""COMPUTED_VALUE"""),6.52) -> 6.52
A43: =IFERROR(__xludf.DUMMYFUNCTION("""COMPUTED_VALUE"""),118221.0) -> 118221 | B43: =IFERROR(__xludf.DUMMYFUNCTION("""COMPUTED_VALUE"""),"History") -> History | C43: =IFERROR(__xludf.DUMMYFUNCTION("""COMPUTED_VALUE"""),"Thriller") -> Thriller | D43: =IFERROR(__xludf.DUMMYFUNCTION("""COMPUTED_VALUE"""),"Maple Grove Press") -> Maple Grove Press | E43: =IFERROR(__xludf.DUMMYFUNCTION("""COMPUTED_VALUE"""),7.19) -> 7.19
A44: =IFERROR(__xludf.DUMMYFUNCTION("""COMPUTED_VALUE"""),92900.0) -> 92900 | B44: =IFERROR(__xludf.DUMMYFUNCTION("""COMPUTED_VALUE"""),"History") -> History | C44: =IFERROR(__xludf.DUMMYFUNCTION("""COMPUTED_VALUE"""),"Thriller") -> Thriller | D44: =IFERROR(__xludf.DUMMYFUNCTION("""COMPUTED_VALUE"""),"Maple Grove Press") -> Maple Grove Press | E44: =IFERROR(__xludf.DUMMYFUNCTION("""COMPUTED_VALUE"""),6.25) -> 6.25
A45: =IFERROR(__xludf.DUMMYFUNCTION("""COMPUTED_VALUE"""),118215.0) -> 118215 | B45: =IFERROR(__xludf.DUMMYFUNCTION("""COMPUTED_VALUE"""),"History") -> History | C45: =IFERROR(__xludf.DUMMYFUNCTION("""COMPUTED_VALUE"""),"Thriller") -> Thriller | D45: =IFERROR(__xludf.DUMMYFUNCTION("""COMPUTED_VALUE"""),"Maple Grove Press") -> Maple Grove Press | E45: =IFERROR(__xludf.DUMMYFUNCTION("""COMPUTED_VALUE"""),10.64) -> 10.64
A46: =IFERROR(__xludf.DUMMYFUNCTION("""COMPUTED_VALUE"""),19832.0) -> 19832 | B46: =IFERROR(__xludf.DUMMYFUNCTION("""COMPUTED_VALUE"""),"History") -> History | C46: =IFERROR(__xludf.DUMMYFUNCTION("""COMPUTED_VALUE"""),"Thriller") -> Thriller | D46: =IFERROR(__xludf.DUMMYFUNCTION("""COMPUTED_VALUE"""),"Maple Grove Press") -> Maple Grove Press | E46: =IFERROR(__xludf.DUMMYFUNCTION("""COMPUTED_VALUE"""),7.29) -> 7.29
A47: =IFERROR(__xludf.DUMMYFUNCTION("""COMPUTED_VALUE"""),93071.0) -> 93071 | B47: =IFERROR(__xludf.DUMMYFUNCTION("""COMPUTED_VALUE"""),"History") -> History | C47: =IFERROR(__xludf.DUMMYFUNCTION("""COMPUTED_VALUE"""),"Thriller") -> Thriller | D47: =IFERROR(__xludf.DUMMYFUNCTION("""COMPUTED_VALUE"""),"Maple Grove Press") -> Maple Grove Press | E47: =IFERROR(__xludf.DUMMYFUNCTION("""COMPUTED_VALUE"""),11.11) -> 11.11
A48: =IFERROR(__xludf.DUMMYFUNCTION("""COMPUTED_VALUE"""),122395.0) -> 122395 | B48: =IFERROR(__xludf.DUMMYFUNCTION("""COMPUTED_VALUE"""),"History") -> History | C48: =IFERROR(__xludf.DUMMYFUNCTION("""COMPUTED_VALUE"""),"Thriller") -> Thriller | D48: =IFERROR(__xludf.DUMMYFUNCTION("""COMPUTED_VALUE"""),"Maple Grove Press") -> Maple Grove Press | E48: =IFERROR(__xludf.DUMMYFUNCTION("""COMPUTED_VALUE"""),11.53) -> 11.53
A49: =IFERROR(__xludf.DUMMYFUNCTION("""COMPUTED_VALUE"""),116946.0) -> 116946 | B49: =IFERROR(__xludf.DUMMYFUNCTION("""COMPUTED_VALUE"""),"History") -> History | C49: =IFERROR(__xludf.DUMMYFUNCTION("""COMPUTED_VALUE"""),"Thriller") -> Thriller | D49: =IFERROR(__xludf.DUMMYFUNCTION("""COMPUTED_VALUE"""),"Maple Grove Press") -> Maple Grove Press | E49: =IFERROR(__xludf.DUMMYFUNCTION("""COMPUTED_VALUE"""),8.85) -> 8.85
A50: =IFERROR(__xludf.DUMMYFUNCTION("""COMPUTED_VALUE"""),97538.0) -> 97538 | B50: =IFERROR(__xludf.DUMMYFUNCTION("""COMPUTED_VALUE"""),"History") -> History | C50: =IFERROR(__xludf.DUMMYFUNCTION("""COMPUTED_VALUE"""),"Thriller") -> Thriller | D50: =IFERROR(__xludf.DUMMYFUNCTION("""COMPUTED_VALUE"""),"Maple Grove Press") -> Maple Grove Press | E50: =IFERROR(__xludf.DUMMYFUNCTION("""COMPUTED_VALUE"""),6.99) -> 6.99
A51: =IFERROR(__xludf.DUMMYFUNCTION("""COMPUTED_VALUE"""),127238.0) -> 127238 | B51: =IFERROR(__xludf.DUMMYFUNCTION("""COMPUTED_VALUE"""),"History") -> History | C51: =IFERROR(__xludf.DUMMYFUNCTION("""COMPUTED_VALUE"""),"Thriller") -> Thriller | D51: =IFERROR(__xludf.DUMMYFUNCTION("""COMPUTED_VALUE"""),"Maple Grove Press") -> Maple Grove Press | E51: =IFERROR(__xludf.DUMMYFUNCTION("""COMPUTED_VALUE"""),8.8) -> 8.8
A52: =IFERROR(__xludf.DUMMYFUNCTION("""COMPUTED_VALUE"""),81646.0) -> 81646 | B52: =IFERROR(__xludf.DUMMYFUNCTION("""COMPUTED_VALUE"""),"History") -> History | C52: =IFERROR(__xludf.DUMMYFUNCTION("""COMPUTED_VALUE"""),"Thriller") -> Thriller | D52: =IFERROR(__xludf.DUMMYFUNCTION("""COMPUTED_VALUE"""),"Maple Grove Press") -> Maple Grove Press | E52: =IFERROR(__xludf.DUMMYFUNCTION("""COMPUTED_VALUE"""),8.45) -> 8.45
A53: =IFERROR(__xludf.DUMMYFUNCTION("""COMPUTED_VALUE"""),81643.0) -> 81643 | B53: =IFERROR(__xludf.DUMMYFUNCTION("""COMPUTED_VALUE"""),"History") -> History | C53: =IFERROR(__xludf.DUMMYFUNCTION("""COMPUTED_VALUE"""),"Thriller") -> Thriller | D53: =IFERROR(__xludf.DUMMYFUNCTION("""COMPUTED_VALUE"""),"Maple Grove Press") -> Maple Grove Press | E53: =IFERROR(__xludf.DUMMYFUNCTION("""COMPUTED_VALUE"""),8.46) -> 8.46
A54: =IFERROR(__xludf.DUMMYFUNCTION("""COMPUTED_VALUE"""),128215.0) -> 128215 | B54: =IFERROR(__xludf.DUMMYFUNCTION("""COMPUTED_VALUE"""),"History") -> History | C54: =IFERROR(__xludf.DUMMYFUNCTION("""COMPUTED_VALUE"""),"Thriller") -> Thriller | D54: =IFERROR(__xludf.DUMMYFUNCTION("""COMPUTED_VALUE"""),"Maple Grove Press") -> Maple Grove Press | E54: =IFERROR(__xludf.DUMMYFUNCTION("""COMPUTED_VALUE"""),11.73) -> 11.73
A55: =IFERROR(__xludf.DUMMYFUNCTION("""COMPUTED_VALUE"""),108022.0) -> 108022 | B55: =IFERROR(__xludf.DUMMYFUNCTION("""COMPUTED_VALUE"""),"History") -> History | C55: =IFERROR(__xludf.DUMMYFUNCTION("""COMPUTED_VALUE"""),"Thriller") -> Thriller | D55: =IFERROR(__xludf.DUMMYFUNCTION("""COMPUTED_VALUE"""),"Maple Grove Press") -> Maple Grove Press | E55: =IFERROR(__xludf.DUMMYFUNCTION("""COMPUTED_VALUE"""),6.76) -> 6.76
A56: =IFERROR(__xludf.DUMMYFUNCTION("""COMPUTED_VALUE"""),81647.0) -> 81647 | B56: =IFERROR(__xludf.DUMMYFUNCTION("""COMPUTED_VALUE"""),"History") -> History | C56: =IFERROR(__xludf.DUMMYFUNCTION("""COMPUTED_VALUE"""),"Thriller") -> Thriller | D56: =IFERROR(__xludf.DUMMYFUNCTION("""COMPUTED_VALUE"""),"Maple Grove Press") -> Maple Grove Press | E56: =IFERROR(__xludf.DUMMYFUNCTION("""COMPUTED_VALUE"""),8.75) -> 8.75
A57: =IFERROR(__xludf.DUMMYFUNCTION("""COMPUTED_VALUE"""),83603.0) -> 83603 | B57: =IFERROR(__xludf.DUMMYFUNCTION("""COMPUTED_VALUE"""),"History") -> History | C57: =IFERROR(__xludf.DUMMYFUNCTION("""COMPUTED_VALUE"""),"Thriller") -> Thriller | D57: =IFERROR(__xludf.DUMMYFUNCTION("""COMPUTED_VALUE"""),"Maple Grove Press") -> Maple Grove Press | E57: =IFERROR(__xludf.DUMMYFUNCTION("""COMPUTED_VALUE"""),12.18) -> 12.18
A58: =IFERROR(__xludf.DUMMYFUNCTION("""COMPUTED_VALUE"""),118219.0) -> 118219 | B58: =IFERROR(__xludf.DUMMYFUNCTION("""COMPUTED_VALUE"""),"History") -> History | C58: =IFERROR(__xludf.DUMMYFUNCTION("""COMPUTED_VALUE"""),"Thriller") -> Thriller | D58: =IFERROR(__xludf.DUMMYFUNCTION("""COMPUTED_VALUE"""),"Maple Grove Press") -> Maple Grove Press | E58: =IFERROR(__xludf.DUMMYFUNCTION("""COMPUTED_VALUE"""),8.81) -> 8.81
A59: =IFERROR(__xludf.DUMMYFUNCTION("""COMPUTED_VALUE"""),120952.0) -> 120952 | B59: =IFERROR(__xludf.DUMMYFUNCTION("""COMPUTED_VALUE"""),"History") -> History | C59: =IFERROR(__xludf.DUMMYFUNCTION("""COMPUTED_VALUE"""),"Thriller") -> Thriller | D59: =IFERROR(__xludf.DUMMYFUNCTION("""COMPUTED_VALUE"""),"Cedar Hill Books") -> Cedar Hill Books | E59: =IFERROR(__xludf.DUMMYFUNCTION("""COMPUTED_VALUE"""),3.05) -> 3.05
A60: =IFERROR(__xludf.DUMMYFUNCTION("""COMPUTED_VALUE"""),81658.0) -> 81658 | B60: =IFERROR(__xludf.DUMMYFUNCTION("""COMPUTED_VALUE"""),"History") -> History | C60: =IFERROR(__xludf.DUMMYFUNCTION("""COMPUTED_VALUE"""),"Thriller") -> Thriller | D60: =IFERROR(__xludf.DUMMYFUNCTION("""COMPUTED_VALUE"""),"Cedar Hill Books") -> Cedar Hill Books | E60: =IFERROR(__xludf.DUMMYFUNCTION("""COMPUTED_VALUE"""),5.24) -> 5.24
A61: =IFERROR(__xludf.DUMMYFUNCTION("""COMPUTED_VALUE"""),93047.0) -> 93047 | B61: =IFERROR(__xludf.DUMMYFUNCTION("""COMPUTED_VALUE"""),"History") -> History | C61: =IFERROR(__xludf.DUMMYFUNCTION("""COMPUTED_VALUE"""),"Thriller") -> Thriller | D61: =IFERROR(__xludf.DUMMYFUNCTION("""COMPUTED_VALUE"""),"Cedar Hill Books") -> Cedar Hill Books | E61: =IFERROR(__xludf.DUMMYFUNCTION("""COMPUTED_VALUE"""),3.53) -> 3.53
A62: =IFERROR(__xludf.DUMMYFUNCTION("""COMPUTED_VALUE"""),83807.0) -> 83807 | B62: =IFERROR(__xludf.DUMMYFUNCTION("""COMPUTED_VALUE"""),"History") -> History | C62: =IFERROR(__xludf.DUMMYFUNCTION("""COMPUTED_VALUE"""),"Thriller") -> Thriller | D62: =IFERROR(__xludf.DUMMYFUNCTION("""COMPUTED_VALUE"""),"Cedar Hill Books") -> Cedar Hill Books | E62: =IFERROR(__xludf.DUMMYFUNCTION("""COMPUTED_VALUE"""),3.72) -> 3.72
A63: =IFERROR(__xludf.DUMMYFUNCTION("""COMPUTED_VALUE"""),92915.0) -> 92915 | B63: =IFERROR(__xludf.DUMMYFUNCTION("""COMPUTED_VALUE"""),"History") -> History | C63: =IFERROR(__xludf.DUMMYFUNCTION("""COMPUTED_VALUE"""),"Thriller") -> Thriller | D63: =IFERROR(__xludf.DUMMYFUNCTION("""COMPUTED_VALUE"""),"Cedar Hill Books") -> Cedar Hill Books | E63: =IFERROR(__xludf.DUMMYFUNCTION("""COMPUTED_VALUE"""),6.35) -> 6.35
A64: =IFERROR(__xludf.DUMMYFUNCTION("""COMPUTED_VALUE"""),81653.0) -> 81653 | B64: =IFERROR(__xludf.DUMMYFUNCTION("""COMPUTED_VALUE"""),"History") -> History | C64: =IFERROR(__xludf.DUMMYFUNCTION("""COMPUTED_VALUE"""),"Thriller") -> Thriller | D64: =IFERROR(__xludf.DUMMYFUNCTION("""COMPUTED_VALUE"""),"Cedar Hill Books") -> Cedar Hill Books | E64: =IFERROR(__xludf.DUMMYFUNCTION("""COMPUTED_VALUE"""),4.3) -> 4.3
A65: =IFERROR(__xludf.DUMMYFUNCTION("""COMPUTED_VALUE"""),81618.0) -> 81618 | B65: =IFERROR(__xludf.DUMMYFUNCTION("""COMPUTED_VALUE"""),"History") -> History | C65: =IFERROR(__xludf.DUMMYFUNCTION("""COMPUTED_VALUE"""),"Thriller") -> Thriller | D65: =IFERROR(__xludf.DUMMYFUNCTION("""COMPUTED_VALUE"""),"Cedar Hill Books") -> Cedar Hill Books | E65: =IFERROR(__xludf.DUMMYFUNCTION("""COMPUTED_VALUE"""),3.55) -> 3.55
A66: =IFERROR(__xludf.DUMMYFUNCTION("""COMPUTED_VALUE"""),118241.0) -> 118241 | B66: =IFERROR(__xludf.DUMMYFUNCTION("""COMPUTED_VALUE"""),"History") -> History | C66: =IFERROR(__xludf.DUMMYFUNCTION("""COMPUTED_VALUE"""),"Thriller") -> Thriller | D66: =IFERROR(__xludf.DUMMYFUNCTION("""COMPUTED_VALUE"""),"Willow Creek Publishing") -> Willow Creek Publishing | E66: =IFERROR(__xludf.DUMMYFUNCTION("""COMPUTED_VALUE"""),2.33) -> 2.33
A67: =IFERROR(__xludf.DUMMYFUNCTION("""COMPUTED_VALUE"""),48634.0) -> 48634 | B67: =IFERROR(__xludf.DUMMYFUNCTION("""COMPUTED_VALUE"""),"History") -> History | C67: =IFERROR(__xludf.DUMMYFUNCTION("""COMPUTED_VALUE"""),"Thriller") -> Thriller | D67: =IFERROR(__xludf.DUMMYFUNCTION("""COMPUTED_VALUE"""),"Willow Creek Publishing") -> Willow Creek Publishing | E67: =IFERROR(__xludf.DUMMYFUNCTION("""COMPUTED_VALUE"""),3.0) -> 3
A68: =IFERROR(__xludf.DUMMYFUNCTION("""COMPUTED_VALUE"""),48636.0) -> 48636 | B68: =IFERROR(__xludf.DUMMYFUNCTION("""COMPUTED_VALUE"""),"History") -> History | C68: =IFERROR(__xludf.DUMMYFUNCTION("""COMPUTED_VALUE"""),"Thriller") -> Thriller | D68: =IFERROR(__xludf.DUMMYFUNCTION("""COMPUTED_VALUE"""),"Willow Creek Publishing") -> Willow Creek Publishing | E68: =IFERROR(__xludf.DUMMYFUNCTION("""COMPUTED_VALUE"""),3.02) -> 3.02
A69: =IFERROR(__xludf.DUMMYFUNCTION("""COMPUTED_VALUE"""),48629.0) -> 48629 | B69: =IFERROR(__xludf.DUMMYFUNCTION("""COMPUTED_VALUE"""),"History") -> History | C69: =IFERROR(__xludf.DUMMYFUNCTION("""COMPUTED_VALUE"""),"Thriller") -> Thriller | D69: =IFERROR(__xludf.DUMMYFUNCTION("""COMPUTED_VALUE"""),"Willow Creek Publishing") -> Willow Creek Publishing | E69: =IFERROR(__xludf.DUMMYFUNCTION("""COMPUTED_VALUE"""),2.63) -> 2.63
A70: =IFERROR(__xludf.DUMMYFUNCTION("""COMPUTED_VALUE"""),47400.0) -> 47400 | B70: =IFERROR(__xludf.DUMMYFUNCTION("""COMPUTED_VALUE"""),"History") -> History | C70: =IFERROR(__xludf.DUMMYFUNCTION("""COMPUTED_VALUE"""),"Thriller") -> Thriller | D70: =IFERROR(__xludf.DUMMYFUNCTION("""COMPUTED_VALUE"""),"Willow Creek Publishing") -> Willow Creek Publishing | E70: =IFERROR(__xludf.DUMMYFUNCTION("""COMPUTED_VALUE"""),2.13) -> 2.13
A71: =IFERROR(__xludf.DUMMYFUNCTION("""COMPUTED_VALUE"""),111237.0) -> 111237 | B71: =IFERROR(__xludf.DUMMYFUNCTION("""COMPUTED_VALUE"""),"History") -> History | C71: =IFERROR(__xludf.DUMMYFUNCTION("""COMPUTED_VALUE"""),"Thriller") -> Thriller | D71: =IFERROR(__xludf.DUMMYFUNCTION("""COMPUTED_VALUE"""),"Willow Creek Publishing") -> Willow Creek Publishing | E71: =IFERROR(__xludf.DUMMYFUNCTION("""COMPUTED_VALUE"""),4.21) -> 4.21
A72: =IFERROR(__xludf.DUMMYFUNCTION("""COMPUTED_VALUE"""),18042.0) -> 18042 | B72: =IFERROR(__xludf.DUMMYFUNCTION("""COMPUTED_VALUE"""),"History") -> History | C72: =IFERROR(__xludf.DUMMYFUNCTION("""COMPUTED_VALUE"""),"Thriller") -> Thriller | D72: =IFERROR(__xludf.DUMMYFUNCTION("""COMPUTED_VALUE"""),"Bright Horizon Press") -> Bright Horizon Press | E72: =IFERROR(__xludf.DUMMYFUNCTION("""COMPUTED_VALUE"""),3.5) -> 3.5
A73: =IFERROR(__xludf.DUMMYFUNCTION("""COMPUTED_VALUE"""),114978.0) -> 114978 | B73: =IFERROR(__xludf.DUMMYFUNCTION("""COMPUTED_VALUE"""),"History") -> History | C73: =IFERROR(__xludf.DUMMYFUNCTION("""COMPUTED_VALUE"""),"Thriller") -> Thriller | D73: =IFERROR(__xludf.DUMMYFUNCTION("""COMPUTED_VALUE"""),"Bright Horizon Press") -> Bright Horizon Press | E73: =IFERROR(__xludf.DUMMYFUNCTION("""COMPUTED_VALUE"""),4.41) -> 4.41
A74: =IFERROR(__xludf.DUMMYFUNCTION("""COMPUTED_VALUE"""),82980.0) -> 82980 | B74: =IFERROR(__xludf.DUMMYFUNCTION("""COMPUTED_VALUE"""),"History") -> History | C74: =IFERROR(__xludf.DUMMYFUNCTION("""COMPUTED_VALUE"""),"Thriller") -> Thriller | D74: =IFERROR(__xludf.DUMMYFUNCTION("""COMPUTED_VALUE"""),"Bright Horizon Press") -> Bright Horizon Press | E74: =IFERROR(__xludf.DUMMYFUNCTION("""COMPUTED_VALUE"""),2.29) -> 2.29
A75: =IFERROR(__xludf.DUMMYFUNCTION("""COMPUTED_VALUE"""),83093.0) -> 83093 | B75: =IFERROR(__xludf.DUMMYFUNCTION("""COMPUTED_VALUE"""),"History") -> History | C75: =IFERROR(__xludf.DUMMYFUNCTION("""COMPUTED_VALUE"""),"Thriller") -> Thriller | D75: =IFERROR(__xludf.DUMMYFUNCTION("""COMPUTED_VALUE"""),"Bright Horizon Press") -> Bright Horizon Press | E75: =IFERROR(__xludf.DUMMYFUNCTION("""COMPUTED_VALUE"""),4.19) -> 4.19
A76: =IFERROR(__xludf.DUMMYFUNCTION("""COMPUTED_VALUE"""),18134.0) -> 18134 | B76: =IFERROR(__xludf.DUMMYFUNCTION("""COMPUTED_VALUE"""),"History") -> History | C76: =IFERROR(__xludf.DUMMYFUNCTION("""COMPUTED_VALUE"""),"Thriller") -> Thriller | D76: =IFERROR(__xludf.DUMMYFUNCTION("""COMPUTED_VALUE"""),"Bright Horizon Press") -> Bright Horizon Press | E76: =IFERROR(__xludf.DUMMYFUNCTION("""COMPUTED_VALUE"""),3.99) -> 3.99
A77: =IFERROR(__xludf.DUMMYFUNCTION("""COMPUTED_VALUE"""),107857.0) -> 107857 | B77: =IFERROR(__xludf.DUMMYFUNCTION("""COMPUTED_VALUE"""),"History") -> History | C77: =IFERROR(__xludf.DUMMYFUNCTION("""COMPUTED_VALUE"""),"Thriller") -> Thriller | D77: =IFERROR(__xludf.DUMMYFUNCTION("""COMPUTED_VALUE"""),"Bright Horizon Press") -> Bright Horizon Press | E77: =IFERROR(__xludf.DUMMYFUNCTION("""COMPUTED_VALUE"""),3.99) -> 3.99
A78: =IFERROR(__xludf.DUMMYFUNCTION("""COMPUTED_VALUE"""),18136.0) -> 18136 | B78: =IFERROR(__xludf.DUMMYFUNCTION("""COMPUTED_VALUE"""),"History") -> History | C78: =IFERROR(__xludf.DUMMYFUNCTION("""COMPUTED_VALUE"""),"Thriller") -> Thriller | D78: =IFERROR(__xludf.DUMMYFUNCTION("""COMPUTED_VALUE"""),"Bright Horizon Press") -> Bright Horizon Press | E78: =IFERROR(__xludf.DUMMYFUNCTION("""COMPUTED_VALUE"""),5.27) -> 5.27
A79: =IFERROR(__xludf.DUMMYFUNCTION("""COMPUTED_VALUE"""),69138.0) -> 69138 | B79: =IFERROR(__xludf.DUMMYFUNCTION("""COMPUTED_VALUE"""),"History") -> History | C79: =IFERROR(__xludf.DUMMYFUNCTION("""COMPUTED_VALUE"""),"Thriller") -> Thriller | D79: =IFERROR(__xludf.DUMMYFUNCTION("""COMPUTED_VALUE"""),"Bright Horizon Press") -> Bright Horizon Press | E79: =IFERROR(__xludf.DUMMYFUNCTION("""COMPUTED_VALUE"""),5.32) -> 5.32
A80: =IFERROR(__xludf.DUMMYFUNCTION("""COMPUTED_VALUE"""),74828.0) -> 74828 | B80: =IFERROR(__xludf.DUMMYFUNCTION("""COMPUTED_VALUE"""),"History") -> History | C80: =IFERROR(__xludf.DUMMYFUNCTION("""COMPUTED_VALUE"""),"Thriller") -> Thriller | D80: =IFERROR(__xludf.DUMMYFUNCTION("""COMPUTED_VALUE"""),"Bright Horizon Press") -> Bright Horizon Press | E80: =IFERROR(__xludf.DUMMYFUNCTION("""COMPUTED_VALUE"""),4.74) -> 4.74
A81: =IFERROR(__xludf.DUMMYFUNCTION("""COMPUTED_VALUE"""),74884.0) -> 74884 | B81: =IFERROR(__xludf.DUMMYFUNCTION("""COMPUTED_VALUE"""),"History") -> History | C81: =IFERROR(__xludf.DUMMYFUNCTION("""COMPUTED_VALUE"""),"Thriller") -> Thriller | D81: =IFERROR(__xludf.DUMMYFUNCTION("""COMPUTED_VALUE"""),"Bright Horizon Press") -> Bright Horizon Press | E81: =IFERROR(__xludf.DUMMYFUNCTION("""COMPUTED_VALUE"""),5.05) -> 5.05
A82: =IFERROR(__xludf.DUMMYFUNCTION("""COMPUTED_VALUE"""),127232.0) -> 127232 | B82: =IFERROR(__xludf.DUMMYFUNCTION("""COMPUTED_VALUE"""),"History") -> History | C82: =IFERROR(__xludf.DUMMYFUNCTION("""COMPUTED_VALUE"""),"Thriller") -> Thriller | D82: =IFERROR(__xludf.DUMMYFUNCTION("""COMPUTED_VALUE"""),"Bright Horizon Press") -> Bright Horizon Press | E82: =IFERROR(__xludf.DUMMYFUNCTION("""COMPUTED_VALUE"""),2.95) -> 2.95
A83: =IFERROR(__xludf.DUMMYFUNCTION("""COMPUTED_VALUE"""),82979.0) -> 82979 | B83: =IFERROR(__xludf.DUMMYFUNCTION("""COMPUTED_VALUE"""),"History") -> History | C83: =IFERROR(__xludf.DUMMYFUNCTION("""COMPUTED_VALUE"""),"Thriller") -> Thriller | D83: =IFERROR(__xludf.DUMMYFUNCTION("""COMPUTED_VALUE"""),"Bright Horizon Press") -> Bright Horizon Press | E83: =IFERROR(__xludf.DUMMYFUNCTION("""COMPUTED_VALUE"""),1.92) -> 1.92
A84: =IFERROR(__xludf.DUMMYFUNCTION("""COMPUTED_VALUE"""),18138.0) -> 18138 | B84: =IFERROR(__xludf.DUMMYFUNCTION("""COMPUTED_VALUE"""),"History") -> History | C84: =IFERROR(__xludf.DUMMYFUNCTION("""COMPUTED_VALUE"""),"Thriller") -> Thriller | D84: =IFERROR(__xludf.DUMMYFUNCTION("""COMPUTED_VALUE"""),"Bright Horizon Press") -> Bright Horizon Press | E84: =IFERROR(__xludf.DUMMYFUNCTION("""COMPUTED_VALUE"""),6.07) -> 6.07
A85: =IFERROR(__xludf.DUMMYFUNCTION("""COMPUTED_VALUE"""),127003.0) -> 127003 | B85: =IFERROR(__xludf.DUMMYFUNCTION("""COMPUTED_VALUE"""),"History") -> History | C85: =IFERROR(__xludf.DUMMYFUNCTION("""COMPUTED_VALUE"""),"Thriller") -> Thriller | D85: =IFERROR(__xludf.DUMMYFUNCTION("""COMPUTED_VALUE"""),"Evergreen House") -> Evergreen House | E85: =IFERROR(__xludf.DUMMYFUNCTION("""COMPUTED_VALUE"""),3.58) -> 3.58
A86: =IFERROR(__xludf.DUMMYFUNCTION("""COMPUTED_VALUE"""),6036.0) -> 6036 | B86: =IFERROR(__xludf.DUMMYFUNCTION("""COMPUTED_VALUE"""),"History") -> History | C86: =IFERROR(__xludf.DUMMYFUNCTION("""COMPUTED_VALUE"""),"Crime") -> Crime | E86: =IFERROR(__xludf.DUMMYFUNCTION("""COMPUTED_VALUE"""),3.72) -> 3.72
A87: =IFERROR(__xludf.DUMMYFUNCTION("""COMPUTED_VALUE"""),6046.0) -> 6046 | B87: =IFERROR(__xludf.DUMMYFUNCTION("""COMPUTED_VALUE"""),"History") -> History | C87: =IFERROR(__xludf.DUMMYFUNCTION("""COMPUTED_VALUE"""),"Crime") -> Crime | E87: =IFERROR(__xludf.DUMMYFUNCTION("""COMPUTED_VALUE"""),5.07) -> 5.07
A88: =IFERROR(__xludf.DUMMYFUNCTION("""COMPUTED_VALUE"""),6037.0) -> 6037 | B88: =IFERROR(__xludf.DUMMYFUNCTION("""COMPUTED_VALUE"""),"History") -> History | C88: =IFERROR(__xludf.DUMMYFUNCTION("""COMPUTED_VALUE"""),"Crime") -> Crime | E88: =IFERROR(__xludf.DUMMYFUNCTION("""COMPUTED_VALUE"""),4.47) -> 4.47
A89: =IFERROR(__xludf.DUMMYFUNCTION("""COMPUTED_VALUE"""),6026.0) -> 6026 | B89: =IFERROR(__xludf.DUMMYFUNCTION("""COMPUTED_VALUE"""),"History") -> History | C89: =IFERROR(__xludf.DUMMYFUNCTION("""COMPUTED_VALUE"""),"Crime") -> Crime | E89: =IFERROR(__xludf.DUMMYFUNCTION("""COMPUTED_VALUE"""),3.36) -> 3.36
A90: =IFERROR(__xludf.DUMMYFUNCTION("""COMPUTED_VALUE"""),47431.0) -> 47431 | B90: =IFERROR(__xludf.DUMMYFUNCTION("""COMPUTED_VALUE"""),"History") -> History | C90: =IFERROR(__xludf.DUMMYFUNCTION("""COMPUTED_VALUE"""),"Crime") -> Crime | E90: =IFERROR(__xludf.DUMMYFUNCTION("""COMPUTED_VALUE"""),3.16) -> 3.16
A91: =IFERROR(__xludf.DUMMYFUNCTION("""COMPUTED_VALUE"""),82914.0) -> 82914 | B91: =IFERROR(__xludf.DUMMYFUNCTION("""COMPUTED_VALUE"""),"History") -> History | C91: =IFERROR(__xludf.DUMMYFUNCTION("""COMPUTED_VALUE"""),"Crime") -> Crime | E91: =IFERROR(__xludf.DUMMYFUNCTION("""COMPUTED_VALUE"""),4.55) -> 4.55
A92: =IFERROR(__xludf.DUMMYFUNCTION("""COMPUTED_VALUE"""),6044.0) -> 6044 | B92: =IFERROR(__xludf.DUMMYFUNCTION("""COMPUTED_VALUE"""),"History") -> History | C92: =IFERROR(__xludf.DUMMYFUNCTION("""COMPUTED_VALUE"""),"Crime") -> Crime | E92: =IFERROR(__xludf.DUMMYFUNCTION("""COMPUTED_VALUE"""),5.48) -> 5.48
A93: =IFERROR(__xludf.DUMMYFUNCTION("""COMPUTED_VALUE"""),82913.0) -> 82913 | B93: =IFERROR(__xludf.DUMMYFUNCTION("""COMPUTED_VALUE"""),"History") -> History | C93: =IFERROR(__xludf.DUMMYFUNCTION("""COMPUTED_VALUE"""),"Crime") -> Crime | E93: =IFERROR(__xludf.DUMMYFUNCTION("""COMPUTED_VALUE"""),4.12) -> 4.12
A94: =IFERROR(__xludf.DUMMYFUNCTION("""COMPUTED_VALUE"""),82922.0) -> 82922 | B94: =IFERROR(__xludf.DUMMYFUNCTION("""COMPUTED_VALUE"""),"History") -> History | C94: =IFERROR(__xludf.DUMMYFUNCTION("""COMPUTED_VALUE"""),"Crime") -> Crime | E94: =IFERROR(__xludf.DUMMYFUNCTION("""COMPUTED_VALUE"""),4.66) -> 4.66
A95: =IFERROR(__xludf.DUMMYFUNCTION("""COMPUTED_VALUE"""),6045.0) -> 6045 | B95: =IFERROR(__xludf.DUMMYFUNCTION("""COMPUTED_VALUE"""),"History") -> History | C95: =IFERROR(__xludf.DUMMYFUNCTION("""COMPUTED_VALUE"""),"Crime") -> Crime | E95: =IFERROR(__xludf.DUMMYFUNCTION("""COMPUTED_VALUE"""),5.21) -> 5.21
A96: =IFERROR(__xludf.DUMMYFUNCTION("""COMPUTED_VALUE"""),6027.0) -> 6027 | B96: =IFERROR(__xludf.DUMMYFUNCTION("""COMPUTED_VALUE"""),"History") -> History | C96: =IFERROR(__xludf.DUMMYFUNCTION("""COMPUTED_VALUE"""),"Crime") -> Crime | E96: =IFERROR(__xludf.DUMMYFUNCTION("""COMPUTED_VALUE"""),3.3) -> 3.3
A97: =IFERROR(__xludf.DUMMYFUNCTION("""COMPUTED_VALUE"""),97088.0) -> 97088 | B97: =IFERROR(__xludf.DUMMYFUNCTION("""COMPUTED_VALUE"""),"History") -> History | C97: =IFERROR(__xludf.DUMMYFUNCTION("""COMPUTED_VALUE"""),"Fantasy") -> Fantasy | D97: =IFERROR(__xludf.DUMMYFUNCTION("""COMPUTED_VALUE"""),"Redwood Publishing") -> Redwood Publishing | E97: =IFERROR(__xludf.DUMMYFUNCTION("""COMPUTED_VALUE"""),2.49) -> 2.49
A98: =IFERROR(__xludf.DUMMYFUNCTION("""COMPUTED_VALUE"""),122235.0) -> 122235 | B98: =IFERROR(__xludf.DUMMYFUNCTION("""COMPUTED_VALUE"""),"History") -> History | C98: =IFERROR(__xludf.DUMMYFUNCTION("""COMPUTED_VALUE"""),"Fantasy") -> Fantasy | D98: =IFERROR(__xludf.DUMMYFUNCTION("""COMPUTED_VALUE"""),"Crown Gate Press") -> Crown Gate Press | E98: =IFERROR(__xludf.DUMMYFUNCTION("""COMPUTED_VALUE"""),12.97) -> 12.97
A99: =IFERROR(__xludf.DUMMYFUNCTION("""COMPUTED_VALUE"""),119887.0) -> 119887 | B99: =IFERROR(__xludf.DUMMYFUNCTION("""COMPUTED_VALUE"""),"History") -> History | C99: =IFERROR(__xludf.DUMMYFUNCTION("""COMPUTED_VALUE"""),"Fantasy") -> Fantasy | D99: =IFERROR(__xludf.DUMMYFUNCTION("""COMPUTED_VALUE"""),"Crown Gate Press") -> Crown Gate Press | E99: =IFERROR(__xludf.DUMMYFUNCTION("""COMPUTED_VALUE"""),18.29) -> 18.29
A100: =IFERROR(__xludf.DUMMYFUNCTION("""COMPUTED_VALUE"""),97980.0) -> 97980 | B100: =IFERROR(__xludf.DUMMYFUNCTION("""COMPUTED_VALUE"""),"History") -> History | C100: =IFERROR(__xludf.DUMMYFUNCTION("""COMPUTED_VALUE"""),"Fantasy") -> Fantasy | D100: =IFERROR(__xludf.DUMMYFUNCTION("""COMPUTED_VALUE"""),"Aurora Book House") -> Aurora Book House | E100: =IFERROR(__xludf.DUMMYFUNCTION("""COMPUTED_VALUE"""),13.46) -> 13.46
...

Sheet Exploration >>

Sheet Explo_Stock
A1: =IFERROR(__xludf.DUMMYFUNCTION("IMPORTRANGE(""https://docs.google.com/spreadsheets/d/1yOpZnyZ5ouw2C51zn4VNSNmNNrizgIE5YAyno7ltBiE/edit"",""stock!A:d"")"),"product_id") -> product_id | B1: =IFERROR(__xludf.DUMMYFUNCTION("""COMPUTED_VALUE"""),"new") -> new | C1: =IFERROR(__xludf.DUMMYFUNCTION("""COMPUTED_VALUE"""),"forecast_stock") -> forecast_stock | D1: =IFERROR(__xludf.DUMMYFUNCTION("""COMPUTED_VALUE"""),"stock") -> stock | E1: category_1 | F1: category_2 | G1: category_3 | H1: pp_cat | I1: product_name | J1: stok_value | K1: in_stock
A2: =IFERROR(__xludf.DUMMYFUNCTION("""COMPUTED_VALUE"""),112463.0) -> 112463 | B2: =IFERROR(__xludf.DUMMYFUNCTION("""COMPUTED_VALUE"""),0.0) -> 0 | C2: =IFERROR(__xludf.DUMMYFUNCTION("""COMPUTED_VALUE"""),320.0) -> 320 | D2: =IFERROR(__xludf.DUMMYFUNCTION("""COMPUTED_VALUE"""),320.0) -> 320 | E2: {=_xlfn.XLOOKUP(A2,Product!A:A,Product!B:B,"Bulunamadı")} -> Fiction | F2: {=_xlfn.XLOOKUP(A2,Product!A:A,Product!C:C,"Bulunamadı")} -> Literary Fiction | G2: {=_xlfn.XLOOKUP(A3,Product!A:A,Product!D:D,"Bulunamadı")} -> Blue Oak Publishing | H2: {=_xlfn.XLOOKUP(A4,Product!A:A,Product!E:E,"Bulunamadı")} -> 2.16 | I2: =A2&" - "&E2&" - "&F2 -> 112463 - Fiction - Literary Fiction | J2: =D2*H2 -> 691.2 | K2: =IF(D2>0,1,0) -> 1
A3: =IFERROR(__xludf.DUMMYFUNCTION("""COMPUTED_VALUE"""),112481.0) -> 112481 | B3: =IFERROR(__xludf.DUMMYFUNCTION("""COMPUTED_VALUE"""),0.0) -> 0 | C3: =IFERROR(__xludf.DUMMYFUNCTION("""COMPUTED_VALUE"""),0.0) -> 0 | D3: =IFERROR(__xludf.DUMMYFUNCTION("""COMPUTED_VALUE"""),0.0) -> 0 | E3: {=_xlfn.XLOOKUP(A3,Product!A:A,Product!B:B,"Bulunamadı")} -> Fiction | F3: {=_xlfn.XLOOKUP(A3,Product!A:A,Product!C:C,"Bulunamadı")} -> Literary Fiction | G3: {=_xlfn.XLOOKUP(A4,Product!A:A,Product!D:D,"Bulunamadı")} -> Blue Oak Publishing | H3: {=_xlfn.XLOOKUP(A5,Product!A:A,Product!E:E,"Bulunamadı")} -> 0.93 | I3: =A3&" - "&E3&" - "&F3 -> 112481 - Fiction - Literary Fiction | J3: =D3*H3 -> 0 | K3: =IF(D3>0,1,0) -> 0
A4: =IFERROR(__xludf.DUMMYFUNCTION("""COMPUTED_VALUE"""),13346.0) -> 13346 | B4: =IFERROR(__xludf.DUMMYFUNCTION("""COMPUTED_VALUE"""),1.0) -> 1 | C4: =IFERROR(__xludf.DUMMYFUNCTION("""COMPUTED_VALUE"""),100.0) -> 100 | D4: =IFERROR(__xludf.DUMMYFUNCTION("""COMPUTED_VALUE"""),100.0) -> 100 | E4: {=_xlfn.XLOOKUP(A4,Product!A:A,Product!B:B,"Bulunamadı")} -> Fiction | F4: {=_xlfn.XLOOKUP(A4,Product!A:A,Product!C:C,"Bulunamadı")} -> Literary Fiction | G4: {=_xlfn.XLOOKUP(A5,Product!A:A,Product!D:D,"Bulunamadı")} -> Blue Oak Publishing | H4: {=_xlfn.XLOOKUP(A6,Product!A:A,Product!E:E,"Bulunamadı")} -> 1.07 | I4: =A4&" - "&E4&" - "&F4 -> 13346 - Fiction - Literary Fiction | J4: =D4*H4 -> 107 | K4: =IF(D4>0,1,0) -> 1
A5: =IFERROR(__xludf.DUMMYFUNCTION("""COMPUTED_VALUE"""),112454.0) -> 112454 | B5: =IFERROR(__xludf.DUMMYFUNCTION("""COMPUTED_VALUE"""),0.0) -> 0 | C5: =IFERROR(__xludf.DUMMYFUNCTION("""COMPUTED_VALUE"""),277.0) -> 277 | D5: =IFERROR(__xludf.DUMMYFUNCTION("""COMPUTED_VALUE"""),268.0) -> 268 | E5: {=_xlfn.XLOOKUP(A5,Product!A:A,Product!B:B,"Bulunamadı")} -> Fiction | F5: {=_xlfn.XLOOKUP(A5,Product!A:A,Product!C:C,"Bulunamadı")} -> Literary Fiction | G5: {=_xlfn.XLOOKUP(A6,Product!A:A,Product!D:D,"Bulunamadı")} -> Blue Oak Publishing | H5: {=_xlfn.XLOOKUP(A7,Product!A:A,Product!E:E,"Bulunamadı")} -> 8.9 | I5: =A5&" - "&E5&" - "&F5 -> 112454 - Fiction - Literary Fiction | J5: =D5*H5 -> 2385.2 | K5: =IF(D5>0,1,0) -> 1
A6: =IFERROR(__xludf.DUMMYFUNCTION("""COMPUTED_VALUE"""),112461.0) -> 112461 | B6: =IFERROR(__xludf.DUMMYFUNCTION("""COMPUTED_VALUE"""),0.0) -> 0 | C6: =IFERROR(__xludf.DUMMYFUNCTION("""COMPUTED_VALUE"""),971.0) -> 971 | D6: =IFERROR(__xludf.DUMMYFUNCTION("""COMPUTED_VALUE"""),472.0) -> 472 | E6: {=_xlfn.XLOOKUP(A6,Product!A:A,Product!B:B,"Bulunamadı")} -> Fiction | F6: {=_xlfn.XLOOKUP(A6,Product!A:A,Product!C:C,"Bulunamadı")} -> Literary Fiction | G6: {=_xlfn.XLOOKUP(A7,Product!A:A,Product!D:D,"Bulunamadı")} -> Silver Leaf Press | H6: {=_xlfn.XLOOKUP(A8,Product!A:A,Product!E:E,"Bulunamadı")} -> 8.84 | I6: =A6&" - "&E6&" - "&F6 -> 112461 - Fiction - Literary Fiction | J6: =D6*H6 -> 4172.48 | K6: =IF(D6>0,1,0) -> 1
A7: =IFERROR(__xludf.DUMMYFUNCTION("""COMPUTED_VALUE"""),106532.0) -> 106532 | B7: =IFERROR(__xludf.DUMMYFUNCTION("""COMPUTED_VALUE"""),0.0) -> 0 | C7: =IFERROR(__xludf.DUMMYFUNCTION("""COMPUTED_VALUE"""),63.0) -> 63 | D7: =IFERROR(__xludf.DUMMYFUNCTION("""COMPUTED_VALUE"""),63.0) -> 63 | E7: {=_xlfn.XLOOKUP(A7,Product!A:A,Product!B:B,"Bulunamadı")} -> Fiction | F7: {=_xlfn.XLOOKUP(A7,Product!A:A,Product!C:C,"Bulunamadı")} -> Literary Fiction | G7: {=_xlfn.XLOOKUP(A8,Product!A:A,Product!D:D,"Bulunamadı")} -> Silver Leaf Press | H7: {=_xlfn.XLOOKUP(A9,Product!A:A,Product!E:E,"Bulunamadı")} -> 4.89 | I7: =A7&" - "&E7&" - "&F7 -> 106532 - Fiction - Literary Fiction | J7: =D7*H7 -> 308.07 | K7: =IF(D7>0,1,0) -> 1
A8: =IFERROR(__xludf.DUMMYFUNCTION("""COMPUTED_VALUE"""),121135.0) -> 121135 | B8: =IFERROR(__xludf.DUMMYFUNCTION("""COMPUTED_VALUE"""),1.0) -> 1 | C8: =IFERROR(__xludf.DUMMYFUNCTION("""COMPUTED_VALUE"""),40.0) -> 40 | D8: =IFERROR(__xludf.DUMMYFUNCTION("""COMPUTED_VALUE"""),33.0) -> 33 | E8: {=_xlfn.XLOOKUP(A8,Product!A:A,Product!B:B,"Bulunamadı")} -> Fiction | F8: {=_xlfn.XLOOKUP(A8,Product!A:A,Product!C:C,"Bulunamadı")} -> Literary Fiction | G8: {=_xlfn.XLOOKUP(A9,Product!A:A,Product!D:D,"Bulunamadı")} -> Northbridge Books | H8: {=_xlfn.XLOOKUP(A10,Product!A:A,Product!E:E,"Bulunamadı")} -> 1.94 | I8: =A8&" - "&E8&" - "&F8 -> 121135 - Fiction - Literary Fiction | J8: =D8*H8 -> 64.02 | K8: =IF(D8>0,1,0) -> 1
A9: =IFERROR(__xludf.DUMMYFUNCTION("""COMPUTED_VALUE"""),128362.0) -> 128362 | B9: =IFERROR(__xludf.DUMMYFUNCTION("""COMPUTED_VALUE"""),1.0) -> 1 | C9: =IFERROR(__xludf.DUMMYFUNCTION("""COMPUTED_VALUE"""),269.0) -> 269 | D9: =IFERROR(__xludf.DUMMYFUNCTION("""COMPUTED_VALUE"""),104.0) -> 104 | E9: {=_xlfn.XLOOKUP(A9,Product!A:A,Product!B:B,"Bulunamadı")} -> History | F9: {=_xlfn.XLOOKUP(A9,Product!A:A,Product!C:C,"Bulunamadı")} -> Mystery | G9: {=_xlfn.XLOOKUP(A10,Product!A:A,Product!D:D,"Bulunamadı")} -> Riverstone Publishing | H9: {=_xlfn.XLOOKUP(A11,Product!A:A,Product!E:E,"Bulunamadı")} -> 1.77 | I9: =A9&" - "&E9&" - "&F9 -> 128362 - History - Mystery | J9: =D9*H9 -> 184.08 | K9: =IF(D9>0,1,0) -> 1
A10: =IFERROR(__xludf.DUMMYFUNCTION("""COMPUTED_VALUE"""),71200.0) -> 71200 | B10: =IFERROR(__xludf.DUMMYFUNCTION("""COMPUTED_VALUE"""),0.0) -> 0 | C10: =IFERROR(__xludf.DUMMYFUNCTION("""COMPUTED_VALUE"""),164.0) -> 164 | D10: =IFERROR(__xludf.DUMMYFUNCTION("""COMPUTED_VALUE"""),152.0) -> 152 | E10: {=_xlfn.XLOOKUP(A10,Product!A:A,Product!B:B,"Bulunamadı")} -> History | F10: {=_xlfn.XLOOKUP(A10,Product!A:A,Product!C:C,"Bulunamadı")} -> Mystery | G10: {=_xlfn.XLOOKUP(A11,Product!A:A,Product!D:D,"Bulunamadı")} -> Riverstone Publishing | H10: {=_xlfn.XLOOKUP(A12,Product!A:A,Product!E:E,"Bulunamadı")} -> 2.88 | I10: =A10&" - "&E10&" - "&F10 -> 71200 - History - Mystery | J10: =D10*H10 -> 437.76 | K10: =IF(D10>0,1,0) -> 1
A11: =IFERROR(__xludf.DUMMYFUNCTION("""COMPUTED_VALUE"""),19812.0) -> 19812 | B11: =IFERROR(__xludf.DUMMYFUNCTION("""COMPUTED_VALUE"""),0.0) -> 0 | C11: =IFERROR(__xludf.DUMMYFUNCTION("""COMPUTED_VALUE"""),489.0) -> 489 | D11: =IFERROR(__xludf.DUMMYFUNCTION("""COMPUTED_VALUE"""),393.0) -> 393 | E11: {=_xlfn.XLOOKUP(A11,Product!A:A,Product!B:B,"Bulunamadı")} -> History | F11: {=_xlfn.XLOOKUP(A11,Product!A:A,Product!C:C,"Bulunamadı")} -> Mystery | G11: {=_xlfn.XLOOKUP(A12,Product!A:A,Product!D:D,"Bulunamadı")} -> Golden Quill Press | H11: {=_xlfn.XLOOKUP(A13,Product!A:A,Product!E:E,"Bulunamadı")} -> 1.83 | I11: =A11&" - "&E11&" - "&F11 -> 19812 - History - Mystery | J11: =D11*H11 -> 719.19 | K11: =IF(D11>0,1,0) -> 1
A12: =IFERROR(__xludf.DUMMYFUNCTION("""COMPUTED_VALUE"""),122259.0) -> 122259 | B12: =IFERROR(__xludf.DUMMYFUNCTION("""COMPUTED_VALUE"""),1.0) -> 1 | C12: =IFERROR(__xludf.DUMMYFUNCTION("""COMPUTED_VALUE"""),104.0) -> 104 | D12: =IFERROR(__xludf.DUMMYFUNCTION("""COMPUTED_VALUE"""),104.0) -> 104 | E12: {=_xlfn.XLOOKUP(A12,Product!A:A,Product!B:B,"Bulunamadı")} -> History | F12: {=_xlfn.XLOOKUP(A12,Product!A:A,Product!C:C,"Bulunamadı")} -> Mystery | G12: {=_xlfn.XLOOKUP(A13,Product!A:A,Product!D:D,"Bulunamadı")} -> Golden Quill Press | H12: {=_xlfn.XLOOKUP(A14,Product!A:A,Product!E:E,"Bulunamadı")} -> 4.04 | I12: =A12&" - "&E12&" - "&F12 -> 122259 - History - Mystery | J12: =D12*H12 -> 420.16 | K12: =IF(D12>0,1,0) -> 1
A13: =IFERROR(__xludf.DUMMYFUNCTION("""COMPUTED_VALUE"""),199526.0) -> 199526 | B13: =IFERROR(__xludf.DUMMYFUNCTION("""COMPUTED_VALUE"""),0.0) -> 0 | C13: =IFERROR(__xludf.DUMMYFUNCTION("""COMPUTED_VALUE"""),63.0) -> 63 | D13: =IFERROR(__xludf.DUMMYFUNCTION("""COMPUTED_VALUE"""),60.0) -> 60 | E13: {=_xlfn.XLOOKUP(A13,Product!A:A,Product!B:B,"Bulunamadı")} -> History | F13: {=_xlfn.XLOOKUP(A13,Product!A:A,Product!C:C,"Bulunamadı")} -> Mystery | G13: {=_xlfn.XLOOKUP(A14,Product!A:A,Product!D:D,"Bulunamadı")} -> Golden Quill Press | H13: {=_xlfn.XLOOKUP(A15,Product!A:A,Product!E:E,"Bulunamadı")} -> 1.5 | I13: =A13&" - "&E13&" - "&F13 -> 199526 - History - Mystery | J13: =D13*H13 -> 90 | K13: =IF(D13>0,1,0) -> 1
A14: =IFERROR(__xludf.DUMMYFUNCTION("""COMPUTED_VALUE"""),140581.0) -> 140581 | B14: =IFERROR(__xludf.DUMMYFUNCTION("""COMPUTED_VALUE"""),0.0) -> 0 | C14: =IFERROR(__xludf.DUMMYFUNCTION("""COMPUTED_VALUE"""),14.0) -> 14 | D14: =IFERROR(__xludf.DUMMYFUNCTION("""COMPUTED_VALUE"""),9.0) -> 9 | E14: {=_xlfn.XLOOKUP(A14,Product!A:A,Product!B:B,"Bulunamadı")} -> History | F14: {=_xlfn.XLOOKUP(A14,Product!A:A,Product!C:C,"Bulunamadı")} -> Mystery | G14: {=_xlfn.XLOOKUP(A15,Product!A:A,Product!D:D,"Bulunamadı")} -> Golden Quill Press | H14: {=_xlfn.XLOOKUP(A16,Product!A:A,Product!E:E,"Bulunamadı")} -> 2.65 | I14: =A14&" - "&E14&" - "&F14 -> 140581 - History - Mystery | J14: =D14*H14 -> 23.85 | K14: =IF(D14>0,1,0) -> 1
A15: =IFERROR(__xludf.DUMMYFUNCTION("""COMPUTED_VALUE"""),118383.0) -> 118383 | B15: =IFERROR(__xludf.DUMMYFUNCTION("""COMPUTED_VALUE"""),0.0) -> 0 | C15: =IFERROR(__xludf.DUMMYFUNCTION("""COMPUTED_VALUE"""),256.0) -> 256 | D15: =IFERROR(__xludf.DUMMYFUNCTION("""COMPUTED_VALUE"""),256.0) -> 256 | E15: {=_xlfn.XLOOKUP(A15,Product!A:A,Product!B:B,"Bulunamadı")} -> History | F15: {=_xlfn.XLOOKUP(A15,Product!A:A,Product!C:C,"Bulunamadı")} -> Mystery | G15: {=_xlfn.XLOOKUP(A16,Product!A:A,Product!D:D,"Bulunamadı")} -> Golden Quill Press | H15: {=_xlfn.XLOOKUP(A17,Product!A:A,Product!E:E,"Bulunamadı")} -> 2.04 | I15: =A15&" - "&E15&" - "&F15 -> 118383 - History - Mystery | J15: =D15*H15 -> 522.24 | K15: =IF(D15>0,1,0) -> 1
A16: =IFERROR(__xludf.DUMMYFUNCTION("""COMPUTED_VALUE"""),122262.0) -> 122262 | B16: =IFERROR(__xludf.DUMMYFUNCTION("""COMPUTED_VALUE"""),0.0) -> 0 | C16: =IFERROR(__xludf.DUMMYFUNCTION("""COMPUTED_VALUE"""),326.0) -> 326 | D16: =IFERROR(__xludf.DUMMYFUNCTION("""COMPUTED_VALUE"""),326.0) -> 326 | E16: {=_xlfn.XLOOKUP(A16,Product!A:A,Product!B:B,"Bulunamadı")} -> History | F16: {=_xlfn.XLOOKUP(A16,Product!A:A,Product!C:C,"Bulunamadı")} -> Mystery | G16: {=_xlfn.XLOOKUP(A17,Product!A:A,Product!D:D,"Bulunamadı")} -> Golden Quill Press | H16: {=_xlfn.XLOOKUP(A18,Product!A:A,Product!E:E,"Bulunamadı")} -> 2.88 | I16: =A16&" - "&E16&" - "&F16 -> 122262 - History - Mystery | J16: =D16*H16 -> 938.88 | K16: =IF(D16>0,1,0) -> 1
A17: =IFERROR(__xludf.DUMMYFUNCTION("""COMPUTED_VALUE"""),141879.0) -> 141879 | B17: =IFERROR(__xludf.DUMMYFUNCTION("""COMPUTED_VALUE"""),0.0) -> 0 | C17: =IFERROR(__xludf.DUMMYFUNCTION("""COMPUTED_VALUE"""),11.0) -> 11 | D17: =IFERROR(__xludf.DUMMYFUNCTION("""COMPUTED_VALUE"""),11.0) -> 11 | E17: {=_xlfn.XLOOKUP(A17,Product!A:A,Product!B:B,"Bulunamadı")} -> History | F17: {=_xlfn.XLOOKUP(A17,Product!A:A,Product!C:C,"Bulunamadı")} -> Mystery | G17: {=_xlfn.XLOOKUP(A18,Product!A:A,Product!D:D,"Bulunamadı")} -> Harbor Light Books | H17: {=_xlfn.XLOOKUP(A19,Product!A:A,Product!E:E,"Bulunamadı")} -> 3.23 | I17: =A17&" - "&E17&" - "&F17 -> 141879 - History - Mystery | J17: =D17*H17 -> 35.53 | K17: =IF(D17>0,1,0) -> 1
A18: =IFERROR(__xludf.DUMMYFUNCTION("""COMPUTED_VALUE"""),19826.0) -> 19826 | B18: =IFERROR(__xludf.DUMMYFUNCTION("""COMPUTED_VALUE"""),0.0) -> 0 | C18: =IFERROR(__xludf.DUMMYFUNCTION("""COMPUTED_VALUE"""),210.0) -> 210 | D18: =IFERROR(__xludf.DUMMYFUNCTION("""COMPUTED_VALUE"""),103.0) -> 103 | E18: {=_xlfn.XLOOKUP(A18,Product!A:A,Product!B:B,"Bulunamadı")} -> History | F18: {=_xlfn.XLOOKUP(A18,Product!A:A,Product!C:C,"Bulunamadı")} -> Thriller | G18: {=_xlfn.XLOOKUP(A19,Product!A:A,Product!D:D,"Bulunamadı")} -> Harbor Light Books | H18: {=_xlfn.XLOOKUP(A20,Product!A:A,Product!E:E,"Bulunamadı")} -> 4.72 | I18: =A18&" - "&E18&" - "&F18 -> 19826 - History - Thriller | J18: =D18*H18 -> 486.16 | K18: =IF(D18>0,1,0) -> 1
A19: =IFERROR(__xludf.DUMMYFUNCTION("""COMPUTED_VALUE"""),93039.0) -> 93039 | B19: =IFERROR(__xludf.DUMMYFUNCTION("""COMPUTED_VALUE"""),0.0) -> 0 | C19: =IFERROR(__xludf.DUMMYFUNCTION("""COMPUTED_VALUE"""),68.0) -> 68 | D19: =IFERROR(__xludf.DUMMYFUNCTION("""COMPUTED_VALUE"""),68.0) -> 68 | E19: {=_xlfn.XLOOKUP(A19,Product!A:A,Product!B:B,"Bulunamadı")} -> History | F19: {=_xlfn.XLOOKUP(A19,Product!A:A,Product!C:C,"Bulunamadı")} -> Thriller | G19: {=_xlfn.XLOOKUP(A20,Product!A:A,Product!D:D,"Bulunamadı")} -> Harbor Light Books | H19: {=_xlfn.XLOOKUP(A21,Product!A:A,Product!E:E,"Bulunamadı")} -> 6.05 | I19: =A19&" - "&E19&" - "&F19 -> 93039 - History - Thriller | J19: =D19*H19 -> 411.4 | K19: =IF(D19>0,1,0) -> 1
A20: =IFERROR(__xludf.DUMMYFUNCTION("""COMPUTED_VALUE"""),128213.0) -> 128213 | B20: =IFERROR(__xludf.DUMMYFUNCTION("""COMPUTED_VALUE"""),0.0) -> 0 | C20: =IFERROR(__xludf.DUMMYFUNCTION("""COMPUTED_VALUE"""),318.0) -> 318 | D20: =IFERROR(__xludf.DUMMYFUNCTION("""COMPUTED_VALUE"""),162.0) -> 162 | E20: {=_xlfn.XLOOKUP(A20,Product!A:A,Product!B:B,"Bulunamadı")} -> History | F20: {=_xlfn.XLOOKUP(A20,Product!A:A,Product!C:C,"Bulunamadı")} -> Thriller | G20: {=_xlfn.XLOOKUP(A21,Product!A:A,Product!D:D,"Bulunamadı")} -> Harbor Light Books | H20: {=_xlfn.XLOOKUP(A22,Product!A:A,Product!E:E,"Bulunamadı")} -> 3.86 | I20: =A20&" - "&E20&" - "&F20 -> 128213 - History - Thriller | J20: =D20*H20 -> 625.32 | K20: =IF(D20>0,1,0) -> 1
A21: =IFERROR(__xludf.DUMMYFUNCTION("""COMPUTED_VALUE"""),83797.0) -> 83797 | B21: =IFERROR(__xludf.DUMMYFUNCTION("""COMPUTED_VALUE"""),0.0) -> 0 | C21: =IFERROR(__xludf.DUMMYFUNCTION("""COMPUTED_VALUE"""),43.0) -> 43 | D21: =IFERROR(__xludf.DUMMYFUNCTION("""COMPUTED_VALUE"""),43.0) -> 43 | E21: {=_xlfn.XLOOKUP(A21,Product!A:A,Product!B:B,"Bulunamadı")} -> History | F21: {=_xlfn.XLOOKUP(A21,Product!A:A,Product!C:C,"Bulunamadı")} -> Thriller | G21: {=_xlfn.XLOOKUP(A22,Product!A:A,Product!D:D,"Bulunamadı")} -> Harbor Light Books | H21: {=_xlfn.XLOOKUP(A23,Product!A:A,Product!E:E,"Bulunamadı")} -> 2.31 | I21: =A21&" - "&E21&" - "&F21 -> 83797 - History - Thriller | J21: =D21*H21 -> 99.33 | K21: =IF(D21>0,1,0) -> 1
A22: =IFERROR(__xludf.DUMMYFUNCTION("""COMPUTED_VALUE"""),19831.0) -> 19831 | B22: =IFERROR(__xludf.DUMMYFUNCTION("""COMPUTED_VALUE"""),0.0) -> 0 | C22: =IFERROR(__xludf.DUMMYFUNCTION("""COMPUTED_VALUE"""),185.0) -> 185 | D22: =IFERROR(__xludf.DUMMYFUNCTION("""COMPUTED_VALUE"""),134.0) -> 134 | E22: {=_xlfn.XLOOKUP(A22,Product!A:A,Product!B:B,"Bulunamadı")} -> History | F22: {=_xlfn.XLOOKUP(A22,Product!A:A,Product!C:C,"Bulunamadı")} -> Thriller | G22: {=_xlfn.XLOOKUP(A23,Product!A:A,Product!D:D,"Bulunamadı")} -> Harbor Light Books | H22: {=_xlfn.XLOOKUP(A24,Product!A:A,Product!E:E,"Bulunamadı")} -> 7.35 | I22: =A22&" - "&E22&" - "&F22 -> 19831 - History - Thriller | J22: =D22*H22 -> 984.9 | K22: =IF(D22>0,1,0) -> 1
A23: =IFERROR(__xludf.DUMMYFUNCTION("""COMPUTED_VALUE"""),93025.0) -> 93025 | B23: =IFERROR(__xludf.DUMMYFUNCTION("""COMPUTED_VALUE"""),0.0) -> 0 | C23: =IFERROR(__xludf.DUMMYFUNCTION("""COMPUTED_VALUE"""),305.0) -> 305 | D23: =IFERROR(__xludf.DUMMYFUNCTION("""COMPUTED_VALUE"""),305.0) -> 305 | E23: {=_xlfn.XLOOKUP(A23,Product!A:A,Product!B:B,"Bulunamadı")} -> History | F23: {=_xlfn.XLOOKUP(A23,Product!A:A,Product!C:C,"Bulunamadı")} -> Thriller | G23: {=_xlfn.XLOOKUP(A24,Product!A:A,Product!D:D,"Bulunamadı")} -> Harbor Light Books | H23: {=_xlfn.XLOOKUP(A25,Product!A:A,Product!E:E,"Bulunamadı")} -> 7.02 | I23: =A23&" - "&E23&" - "&F23 -> 93025 - History - Thriller | J23: =D23*H23 -> 2141.1 | K23: =IF(D23>0,1,0) -> 1
A24: =IFERROR(__xludf.DUMMYFUNCTION("""COMPUTED_VALUE"""),81624.0) -> 81624 | B24: =IFERROR(__xludf.DUMMYFUNCTION("""COMPUTED_VALUE"""),1.0) -> 1 | C24: =IFERROR(__xludf.DUMMYFUNCTION("""COMPUTED_VALUE"""),84.0) -> 84 | D24: =IFERROR(__xludf.DUMMYFUNCTION("""COMPUTED_VALUE"""),84.0) -> 84 | E24: {=_xlfn.XLOOKUP(A24,Product!A:A,Product!B:B,"Bulunamadı")} -> History | F24: {=_xlfn.XLOOKUP(A24,Product!A:A,Product!C:C,"Bulunamadı")} -> Thriller | G24: {=_xlfn.XLOOKUP(A25,Product!A:A,Product!D:D,"Bulunamadı")} -> Harbor Light Books | H24: {=_xlfn.XLOOKUP(A26,Product!A:A,Product!E:E,"Bulunamadı")} -> 2.69 | I24: =A24&" - "&E24&" - "&F24 -> 81624 - History - Thriller | J24: =D24*H24 -> 225.96 | K24: =IF(D24>0,1,0) -> 1
A25: =IFERROR(__xludf.DUMMYFUNCTION("""COMPUTED_VALUE"""),92913.0) -> 92913 | B25: =IFERROR(__xludf.DUMMYFUNCTION("""COMPUTED_VALUE"""),0.0) -> 0 | C25: =IFERROR(__xludf.DUMMYFUNCTION("""COMPUTED_VALUE"""),96.0) -> 96 | D25: =IFERROR(__xludf.DUMMYFUNCTION("""COMPUTED_VALUE"""),96.0) -> 96 | E25: {=_xlfn.XLOOKUP(A25,Product!A:A,Product!B:B,"Bulunamadı")} -> History | F25: {=_xlfn.XLOOKUP(A25,Product!A:A,Product!C:C,"Bulunamadı")} -> Thriller | G25: {=_xlfn.XLOOKUP(A26,Product!A:A,Product!D:D,"Bulunamadı")} -> Harbor Light Books | H25: {=_xlfn.XLOOKUP(A27,Product!A:A,Product!E:E,"Bulunamadı")} -> 1.89 | I25: =A25&" - "&E25&" - "&F25 -> 92913 - History - Thriller | J25: =D25*H25 -> 181.44 | K25: =IF(D25>0,1,0) -> 1
A26: =IFERROR(__xludf.DUMMYFUNCTION("""COMPUTED_VALUE"""),126983.0) -> 126983 | B26: =IFERROR(__xludf.DUMMYFUNCTION("""COMPUTED_VALUE"""),0.0) -> 0 | C26: =IFERROR(__xludf.DUMMYFUNCTION("""COMPUTED_VALUE"""),176.0) -> 176 | D26: =IFERROR(__xludf.DUMMYFUNCTION("""COMPUTED_VALUE"""),71.0) -> 71 | E26: {=_xlfn.XLOOKUP(A26,Product!A:A,Product!B:B,"Bulunamadı")} -> History | F26: {=_xlfn.XLOOKUP(A26,Product!A:A,Product!C:C,"Bulunamadı")} -> Thriller | G26: {=_xlfn.XLOOKUP(A27,Product!A:A,Product!D:D,"Bulunamadı")} -> Harbor Light Books | H26: {=_xlfn.XLOOKUP(A28,Product!A:A,Product!E:E,"Bulunamadı")} -> 2.39 | I26: =A26&" - "&E26&" - "&F26 -> 126983 - History - Thriller | J26: =D26*H26 -> 169.69 | K26: =IF(D26>0,1,0) -> 1
A27: =IFERROR(__xludf.DUMMYFUNCTION("""COMPUTED_VALUE"""),118226.0) -> 118226 | B27: =IFERROR(__xludf.DUMMYFUNCTION("""COMPUTED_VALUE"""),0.0) -> 0 | C27: =IFERROR(__xludf.DUMMYFUNCTION("""COMPUTED_VALUE"""),130.0) -> 130 | D27: =IFERROR(__xludf.DUMMYFUNCTION("""COMPUTED_VALUE"""),130.0) -> 130 | E27: {=_xlfn.XLOOKUP(A27,Product!A:A,Product!B:B,"Bulunamadı")} -> History | F27: {=_xlfn.XLOOKUP(A27,Product!A:A,Product!C:C,"Bulunamadı")} -> Thriller | G27: {=_xlfn.XLOOKUP(A28,Product!A:A,Product!D:D,"Bulunamadı")} -> Harbor Light Books | H27: {=_xlfn.XLOOKUP(A29,Product!A:A,Product!E:E,"Bulunamadı")} -> 2.93 | I27: =A27&" - "&E27&" - "&F27 -> 118226 - History - Thriller | J27: =D27*H27 -> 380.9 | K27: =IF(D27>0,1,0) -> 1
A28: =IFERROR(__xludf.DUMMYFUNCTION("""COMPUTED_VALUE"""),48618.0) -> 48618 | B28: =IFERROR(__xludf.DUMMYFUNCTION("""COMPUTED_VALUE"""),1.0) -> 1 | C28: =IFERROR(__xludf.DUMMYFUNCTION("""COMPUTED_VALUE"""),84.0) -> 84 | D28: =IFERROR(__xludf.DUMMYFUNCTION("""COMPUTED_VALUE"""),84.0) -> 84 | E28: {=_xlfn.XLOOKUP(A28,Product!A:A,Product!B:B,"Bulunamadı")} -> History | F28: {=_xlfn.XLOOKUP(A28,Product!A:A,Product!C:C,"Bulunamadı")} -> Thriller | G28: {=_xlfn.XLOOKUP(A29,Product!A:A,Product!D:D,"Bulunamadı")} -> Harbor Light Books | H28: {=_xlfn.XLOOKUP(A30,Product!A:A,Product!E:E,"Bulunamadı")} -> 2.02 | I28: =A28&" - "&E28&" - "&F28 -> 48618 - History - Thriller | J28: =D28*H28 -> 169.68 | K28: =IF(D28>0,1,0) -> 1
A29: =IFERROR(__xludf.DUMMYFUNCTION("""COMPUTED_VALUE"""),93037.0) -> 93037 | B29: =IFERROR(__xludf.DUMMYFUNCTION("""COMPUTED_VALUE"""),0.0) -> 0 | C29: =IFERROR(__xludf.DUMMYFUNCTION("""COMPUTED_VALUE"""),604.0) -> 604 | D29: =IFERROR(__xludf.DUMMYFUNCTION("""COMPUTED_VALUE"""),604.0) -> 604 | E29: {=_xlfn.XLOOKUP(A29,Product!A:A,Product!B:B,"Bulunamadı")} -> History | F29: {=_xlfn.XLOOKUP(A29,Product!A:A,Product!C:C,"Bulunamadı")} -> Thriller | G29: {=_xlfn.XLOOKUP(A30,Product!A:A,Product!D:D,"Bulunamadı")} -> Harbor Light Books | H29: {=_xlfn.XLOOKUP(A31,Product!A:A,Product!E:E,"Bulunamadı")} -> 2.66 | I29: =A29&" - "&E29&" - "&F29 -> 93037 - History - Thriller | J29: =D29*H29 -> 1606.64 | K29: =IF(D29>0,1,0) -> 1
A30: =IFERROR(__xludf.DUMMYFUNCTION("""COMPUTED_VALUE"""),126984.0) -> 126984 | B30: =IFERROR(__xludf.DUMMYFUNCTION("""COMPUTED_VALUE"""),0.0) -> 0 | C30: =IFERROR(__xludf.DUMMYFUNCTION("""COMPUTED_VALUE"""),26.0) -> 26 | D30: =IFERROR(__xludf.DUMMYFUNCTION("""COMPUTED_VALUE"""),6.0) -> 6 | E30: {=_xlfn.XLOOKUP(A30,Product!A:A,Product!B:B,"Bulunamadı")} -> History | F30: {=_xlfn.XLOOKUP(A30,Product!A:A,Product!C:C,"Bulunamadı")} -> Thriller | G30: {=_xlfn.XLOOKUP(A31,Product!A:A,Product!D:D,"Bulunamadı")} -> Harbor Light Books | H30: {=_xlfn.XLOOKUP(A32,Product!A:A,Product!E:E,"Bulunamadı")} -> 4.35 | I30: =A30&" - "&E30&" - "&F30 -> 126984 - History - Thriller | J30: =D30*H30 -> 26.1 | K30: =IF(D30>0,1,0) -> 1
A31: =IFERROR(__xludf.DUMMYFUNCTION("""COMPUTED_VALUE"""),47393.0) -> 47393 | B31: =IFERROR(__xludf.DUMMYFUNCTION("""COMPUTED_VALUE"""),0.0) -> 0 | C31: =IFERROR(__xludf.DUMMYFUNCTION("""COMPUTED_VALUE"""),982.0) -> 982 | D31: =IFERROR(__xludf.DUMMYFUNCTION("""COMPUTED_VALUE"""),609.0) -> 609 | E31: {=_xlfn.XLOOKUP(A31,Product!A:A,Product!B:B,"Bulunamadı")} -> History | F31: {=_xlfn.XLOOKUP(A31,Product!A:A,Product!C:C,"Bulunamadı")} -> Thriller | G31: {=_xlfn.XLOOKUP(A32,Product!A:A,Product!D:D,"Bulunamadı")} -> Harbor Light Books | H31: {=_xlfn.XLOOKUP(A33,Product!A:A,Product!E:E,"Bulunamadı")} -> 3.33 | I31: =A31&" - "&E31&" - "&F31 -> 47393 - History - Thriller | J31: =D31*H31 -> 2027.97 | K31: =IF(D31>0,1,0) -> 1
A32: =IFERROR(__xludf.DUMMYFUNCTION("""COMPUTED_VALUE"""),128214.0) -> 128214 | B32: =IFERROR(__xludf.DUMMYFUNCTION("""COMPUTED_VALUE"""),0.0) -> 0 | C32: =IFERROR(__xludf.DUMMYFUNCTION("""COMPUTED_VALUE"""),79.0) -> 79 | D32: =IFERROR(__xludf.DUMMYFUNCTION("""COMPUTED_VALUE"""),79.0) -> 79 | E32: {=_xlfn.XLOOKUP(A32,Product!A:A,Product!B:B,"Bulunamadı")} -> History | F32: {=_xlfn.XLOOKUP(A32,Product!A:A,Product!C:C,"Bulunamadı")} -> Thriller | G32: {=_xlfn.XLOOKUP(A33,Product!A:A,Product!D:D,"Bulunamadı")} -> Harbor Light Books | H32: {=_xlfn.XLOOKUP(A34,Product!A:A,Product!E:E,"Bulunamadı")} -> 4.12 | I32: =A32&" - "&E32&" - "&F32 -> 128214 - History - Thriller | J32: =D32*H32 -> 325.48 | K32: =IF(D32>0,1,0) -> 1
A33: =IFERROR(__xludf.DUMMYFUNCTION("""COMPUTED_VALUE"""),83802.0) -> 83802 | B33: =IFERROR(__xludf.DUMMYFUNCTION("""COMPUTED_VALUE"""),0.0) -> 0 | C33: =IFERROR(__xludf.DUMMYFUNCTION("""COMPUTED_VALUE"""),31.0) -> 31 | D33: =IFERROR(__xludf.DUMMYFUNCTION("""COMPUTED_VALUE"""),23.0) -> 23 | E33: {=_xlfn.XLOOKUP(A33,Product!A:A,Product!B:B,"Bulunamadı")} -> History | F33: {=_xlfn.XLOOKUP(A33,Product!A:A,Product!C:C,"Bulunamadı")} -> Thriller | G33: {=_xlfn.XLOOKUP(A34,Product!A:A,Product!D:D,"Bulunamadı")} -> Harbor Light Books | H33: {=_xlfn.XLOOKUP(A35,Product!A:A,Product!E:E,"Bulunamadı")} -> 12.34 | I33: =A33&" - "&E33&" - "&F33 -> 83802 - History - Thriller | J33: =D33*H33 -> 283.82 | K33: =IF(D33>0,1,0) -> 1
A34: =IFERROR(__xludf.DUMMYFUNCTION("""COMPUTED_VALUE"""),48625.0) -> 48625 | B34: =IFERROR(__xludf.DUMMYFUNCTION("""COMPUTED_VALUE"""),1.0) -> 1 | C34: =IFERROR(__xludf.DUMMYFUNCTION("""COMPUTED_VALUE"""),96.0) -> 96 | D34: =IFERROR(__xludf.DUMMYFUNCTION("""COMPUTED_VALUE"""),96.0) -> 96 | E34: {=_xlfn.XLOOKUP(A34,Product!A:A,Product!B:B,"Bulunamadı")} -> History | F34: {=_xlfn.XLOOKUP(A34,Product!A:A,Product!C:C,"Bulunamadı")} -> Thriller | G34: {=_xlfn.XLOOKUP(A35,Product!A:A,Product!D:D,"Bulunamadı")} -> Harbor Light Books | H34: {=_xlfn.XLOOKUP(A36,Product!A:A,Product!E:E,"Bulunamadı")} -> 4.2 | I34: =A34&" - "&E34&" - "&F34 -> 48625 - History - Thriller | J34: =D34*H34 -> 403.2 | K34: =IF(D34>0,1,0) -> 1
A35: =IFERROR(__xludf.DUMMYFUNCTION("""COMPUTED_VALUE"""),83602.0) -> 83602 | B35: =IFERROR(__xludf.DUMMYFUNCTION("""COMPUTED_VALUE"""),0.0) -> 0 | C35: =IFERROR(__xludf.DUMMYFUNCTION("""COMPUTED_VALUE"""),79.0) -> 79 | D35: =IFERROR(__xludf.DUMMYFUNCTION("""COMPUTED_VALUE"""),79.0) -> 79 | E35: {=_xlfn.XLOOKUP(A35,Product!A:A,Product!B:B,"Bulunamadı")} -> History | F35: {=_xlfn.XLOOKUP(A35,Product!A:A,Product!C:C,"Bulunamadı")} -> Thriller | G35: {=_xlfn.XLOOKUP(A36,Product!A:A,Product!D:D,"Bulunamadı")} -> Ironwood Publishing | H35: {=_xlfn.XLOOKUP(A37,Product!A:A,Product!E:E,"Bulunamadı")} -> 4.05 | I35: =A35&" - "&E35&" - "&F35 -> 83602 - History - Thriller | J35: =D35*H35 -> 319.95 | K35: =IF(D35>0,1,0) -> 1
A36: =IFERROR(__xludf.DUMMYFUNCTION("""COMPUTED_VALUE"""),98867.0) -> 98867 | B36: =IFERROR(__xludf.DUMMYFUNCTION("""COMPUTED_VALUE"""),0.0) -> 0 | C36: =IFERROR(__xludf.DUMMYFUNCTION("""COMPUTED_VALUE"""),186.0) -> 186 | D36: =IFERROR(__xludf.DUMMYFUNCTION("""COMPUTED_VALUE"""),186.0) -> 186 | E36: {=_xlfn.XLOOKUP(A36,Product!A:A,Product!B:B,"Bulunamadı")} -> History | F36: {=_xlfn.XLOOKUP(A36,Product!A:A,Product!C:C,"Bulunamadı")} -> Thriller | G36: {=_xlfn.XLOOKUP(A37,Product!A:A,Product!D:D,"Bulunamadı")} -> Ironwood Publishing | H36: {=_xlfn.XLOOKUP(A38,Product!A:A,Product!E:E,"Bulunamadı")} -> 12.24 | I36: =A36&" - "&E36&" - "&F36 -> 98867 - History - Thriller | J36: =D36*H36 -> 2276.64 | K36: =IF(D36>0,1,0) -> 1
A37: =IFERROR(__xludf.DUMMYFUNCTION("""COMPUTED_VALUE"""),127042.0) -> 127042 | B37: =IFERROR(__xludf.DUMMYFUNCTION("""COMPUTED_VALUE"""),0.0) -> 0 | C37: =IFERROR(__xludf.DUMMYFUNCTION("""COMPUTED_VALUE"""),418.0) -> 418 | D37: =IFERROR(__xludf.DUMMYFUNCTION("""COMPUTED_VALUE"""),418.0) -> 418 | E37: {=_xlfn.XLOOKUP(A37,Product!A:A,Product!B:B,"Bulunamadı")} -> History | F37: {=_xlfn.XLOOKUP(A37,Product!A:A,Product!C:C,"Bulunamadı")} -> Thriller | G37: {=_xlfn.XLOOKUP(A38,Product!A:A,Product!D:D,"Bulunamadı")} -> Maple Grove Press | H37: {=_xlfn.XLOOKUP(A39,Product!A:A,Product!E:E,"Bulunamadı")} -> 8.54 | I37: =A37&" - "&E37&" - "&F37 -> 127042 - History - Thriller | J37: =D37*H37 -> 3569.72 | K37: =IF(D37>0,1,0) -> 1
A38: =IFERROR(__xludf.DUMMYFUNCTION("""COMPUTED_VALUE"""),127241.0) -> 127241 | B38: =IFERROR(__xludf.DUMMYFUNCTION("""COMPUTED_VALUE"""),0.0) -> 0 | C38: =IFERROR(__xludf.DUMMYFUNCTION("""COMPUTED_VALUE"""),98.0) -> 98 | D38: =IFERROR(__xludf.DUMMYFUNCTION("""COMPUTED_VALUE"""),98.0) -> 98 | E38: {=_xlfn.XLOOKUP(A38,Product!A:A,Product!B:B,"Bulunamadı")} -> History | F38: {=_xlfn.XLOOKUP(A38,Product!A:A,Product!C:C,"Bulunamadı")} -> Thriller | G38: {=_xlfn.XLOOKUP(A39,Product!A:A,Product!D:D,"Bulunamadı")} -> Maple Grove Press | H38: {=_xlfn.XLOOKUP(A40,Product!A:A,Product!E:E,"Bulunamadı")} -> 12.08 | I38: =A38&" - "&E38&" - "&F38 -> 127241 - History - Thriller | J38: =D38*H38 -> 1183.84 | K38: =IF(D38>0,1,0) -> 1
A39: =IFERROR(__xludf.DUMMYFUNCTION("""COMPUTED_VALUE"""),118220.0) -> 118220 | B39: =IFERROR(__xludf.DUMMYFUNCTION("""COMPUTED_VALUE"""),0.0) -> 0 | C39: =IFERROR(__xludf.DUMMYFUNCTION("""COMPUTED_VALUE"""),34.0) -> 34 | D39: =IFERROR(__xludf.DUMMYFUNCTION("""COMPUTED_VALUE"""),34.0) -> 34 | E39: {=_xlfn.XLOOKUP(A39,Product!A:A,Product!B:B,"Bulunamadı")} -> History | F39: {=_xlfn.XLOOKUP(A39,Product!A:A,Product!C:C,"Bulunamadı")} -> Thriller | G39: {=_xlfn.XLOOKUP(A40,Product!A:A,Product!D:D,"Bulunamadı")} -> Maple Grove Press | H39: {=_xlfn.XLOOKUP(A41,Product!A:A,Product!E:E,"Bulunamadı")} -> 11.06 | I39: =A39&" - "&E39&" - "&F39 -> 118220 - History - Thriller | J39: =D39*H39 -> 376.04 | K39: =IF(D39>0,1,0) -> 1
A40: =IFERROR(__xludf.DUMMYFUNCTION("""COMPUTED_VALUE"""),128216.0) -> 128216 | B40: =IFERROR(__xludf.DUMMYFUNCTION("""COMPUTED_VALUE"""),0.0) -> 0 | C40: =IFERROR(__xludf.DUMMYFUNCTION("""COMPUTED_VALUE"""),141.0) -> 141 | D40: =IFERROR(__xludf.DUMMYFUNCTION("""COMPUTED_VALUE"""),141.0) -> 141 | E40: {=_xlfn.XLOOKUP(A40,Product!A:A,Product!B:B,"Bulunamadı")} -> History | F40: {=_xlfn.XLOOKUP(A40,Product!A:A,Product!C:C,"Bulunamadı")} -> Thriller | G40: {=_xlfn.XLOOKUP(A41,Product!A:A,Product!D:D,"Bulunamadı")} -> Maple Grove Press | H40: {=_xlfn.XLOOKUP(A42,Product!A:A,Product!E:E,"Bulunamadı")} -> 6.52 | I40: =A40&" - "&E40&" - "&F40 -> 128216 - History - Thriller | J40: =D40*H40 -> 919.32 | K40: =IF(D40>0,1,0) -> 1
A41: =IFERROR(__xludf.DUMMYFUNCTION("""COMPUTED_VALUE"""),93049.0) -> 93049 | B41: =IFERROR(__xludf.DUMMYFUNCTION("""COMPUTED_VALUE"""),0.0) -> 0 | C41: =IFERROR(__xludf.DUMMYFUNCTION("""COMPUTED_VALUE"""),34.0) -> 34 | D41: =IFERROR(__xludf.DUMMYFUNCTION("""COMPUTED_VALUE"""),34.0) -> 34 | E41: {=_xlfn.XLOOKUP(A41,Product!A:A,Product!B:B,"Bulunamadı")} -> History | F41: {=_xlfn.XLOOKUP(A41,Product!A:A,Product!C:C,"Bulunamadı")} -> Thriller | G41: {=_xlfn.XLOOKUP(A42,Product!A:A,Product!D:D,"Bulunamadı")} -> Maple Grove Press | H41: {=_xlfn.XLOOKUP(A43,Product!A:A,Product!E:E,"Bulunamadı")} -> 7.19 | I41: =A41&" - "&E41&" - "&F41 -> 93049 - History - Thriller | J41: =D41*H41 -> 244.46 | K41: =IF(D41>0,1,0) -> 1
A42: =IFERROR(__xludf.DUMMYFUNCTION("""COMPUTED_VALUE"""),118216.0) -> 118216 | B42: =IFERROR(__xludf.DUMMYFUNCTION("""COMPUTED_VALUE"""),0.0) -> 0 | C42: =IFERROR(__xludf.DUMMYFUNCTION("""COMPUTED_VALUE"""),0.0) -> 0 | D42: =IFERROR(__xludf.DUMMYFUNCTION("""COMPUTED_VALUE"""),0.0) -> 0 | E42: {=_xlfn.XLOOKUP(A42,Product!A:A,Product!B:B,"Bulunamadı")} -> History | F42: {=_xlfn.XLOOKUP(A42,Product!A:A,Product!C:C,"Bulunamadı")} -> Thriller | G42: {=_xlfn.XLOOKUP(A43,Product!A:A,Product!D:D,"Bulunamadı")} -> Maple Grove Press | H42: {=_xlfn.XLOOKUP(A44,Product!A:A,Product!E:E,"Bulunamadı")} -> 6.25 | I42: =A42&" - "&E42&" - "&F42 -> 118216 - History - Thriller | J42: =D42*H42 -> 0 | K42: =IF(D42>0,1,0) -> 0
A43: =IFERROR(__xludf.DUMMYFUNCTION("""COMPUTED_VALUE"""),118221.0) -> 118221 | B43: =IFERROR(__xludf.DUMMYFUNCTION("""COMPUTED_VALUE"""),1.0) -> 1 | C43: =IFERROR(__xludf.DUMMYFUNCTION("""COMPUTED_VALUE"""),99.0) -> 99 | D43: =IFERROR(__xludf.DUMMYFUNCTION("""COMPUTED_VALUE"""),99.0) -> 99 | E43: {=_xlfn.XLOOKUP(A43,Product!A:A,Product!B:B,"Bulunamadı")} -> History | F43: {=_xlfn.XLOOKUP(A43,Product!A:A,Product!C:C,"Bulunamadı")} -> Thriller | G43: {=_xlfn.XLOOKUP(A44,Product!A:A,Product!D:D,"Bulunamadı")} -> Maple Grove Press | H43: {=_xlfn.XLOOKUP(A45,Product!A:A,Product!E:E,"Bulunamadı")} -> 10.64 | I43: =A43&" - "&E43&" - "&F43 -> 118221 - History - Thriller | J43: =D43*H43 -> 1053.36 | K43: =IF(D43>0,1,0) -> 1
A44: =IFERROR(__xludf.DUMMYFUNCTION("""COMPUTED_VALUE"""),92900.0) -> 92900 | B44: =IFERROR(__xludf.DUMMYFUNCTION("""COMPUTED_VALUE"""),0.0) -> 0 | C44: =IFERROR(__xludf.DUMMYFUNCTION("""COMPUTED_VALUE"""),167.0) -> 167 | D44: =IFERROR(__xludf.DUMMYFUNCTION("""COMPUTED_VALUE"""),131.0) -> 131 | E44: {=_xlfn.XLOOKUP(A44,Product!A:A,Product!B:B,"Bulunamadı")} -> History | F44: {=_xlfn.XLOOKUP(A44,Product!A:A,Product!C:C,"Bulunamadı")} -> Thriller | G44: {=_xlfn.XLOOKUP(A45,Product!A:A,Product!D:D,"Bulunamadı")} -> Maple Grove Press | H44: {=_xlfn.XLOOKUP(A46,Product!A:A,Product!E:E,"Bulunamadı")} -> 7.29 | I44: =A44&" - "&E44&" - "&F44 -> 92900 - History - Thriller | J44: =D44*H44 -> 954.99 | K44: =IF(D44>0,1,0) -> 1
A45: =IFERROR(__xludf.DUMMYFUNCTION("""COMPUTED_VALUE"""),118215.0) -> 118215 | B45: =IFERROR(__xludf.DUMMYFUNCTION("""COMPUTED_VALUE"""),1.0) -> 1 | C45: =IFERROR(__xludf.DUMMYFUNCTION("""COMPUTED_VALUE"""),100.0) -> 100 | D45: =IFERROR(__xludf.DUMMYFUNCTION("""COMPUTED_VALUE"""),46.0) -> 46 | E45: {=_xlfn.XLOOKUP(A45,Product!A:A,Product!B:B,"Bulunamadı")} -> History | F45: {=_xlfn.XLOOKUP(A45,Product!A:A,Product!C:C,"Bulunamadı")} -> Thriller | G45: {=_xlfn.XLOOKUP(A46,Product!A:A,Product!D:D,"Bulunamadı")} -> Maple Grove Press | H45: {=_xlfn.XLOOKUP(A47,Product!A:A,Product!E:E,"Bulunamadı")} -> 11.11 | I45: =A45&" - "&E45&" - "&F45 -> 118215 - History - Thriller | J45: =D45*H45 -> 511.06 | K45: =IF(D45>0,1,0) -> 1
A46: =IFERROR(__xludf.DUMMYFUNCTION("""COMPUTED_VALUE"""),19832.0) -> 19832 | B46: =IFERROR(__xludf.DUMMYFUNCTION("""COMPUTED_VALUE"""),1.0) -> 1 | C46: =IFERROR(__xludf.DUMMYFUNCTION("""COMPUTED_VALUE"""),594.0) -> 594 | D46: =IFERROR(__xludf.DUMMYFUNCTION("""COMPUTED_VALUE"""),558.0) -> 558 | E46: {=_xlfn.XLOOKUP(A46,Product!A:A,Product!B:B,"Bulunamadı")} -> History | F46: {=_xlfn.XLOOKUP(A46,Product!A:A,Product!C:C,"Bulunamadı")} -> Thriller | G46: {=_xlfn.XLOOKUP(A47,Product!A:A,Product!D:D,"Bulunamadı")} -> Maple Grove Press | H46: {=_xlfn.XLOOKUP(A48,Product!A:A,Product!E:E,"Bulunamadı")} -> 11.53 | I46: =A46&" - "&E46&" - "&F46 -> 19832 - History - Thriller | J46: =D46*H46 -> 6433.74 | K46: =IF(D46>0,1,0) -> 1
A47: =IFERROR(__xludf.DUMMYFUNCTION("""COMPUTED_VALUE"""),93071.0) -> 93071 | B47: =IFERROR(__xludf.DUMMYFUNCTION("""COMPUTED_VALUE"""),1.0) -> 1 | C47: =IFERROR(__xludf.DUMMYFUNCTION("""COMPUTED_VALUE"""),199.0) -> 199 | D47: =IFERROR(__xludf.DUMMYFUNCTION("""COMPUTED_VALUE"""),19.0) -> 19 | E47: {=_xlfn.XLOOKUP(A47,Product!A:A,Product!B:B,"Bulunamadı")} -> History | F47: {=_xlfn.XLOOKUP(A47,Product!A:A,Product!C:C,"Bulunamadı")} -> Thriller | G47: {=_xlfn.XLOOKUP(A48,Product!A:A,Product!D:D,"Bulunamadı")} -> Maple Grove Press | H47: {=_xlfn.XLOOKUP(A49,Product!A:A,Product!E:E,"Bulunamadı")} -> 8.85 | I47: =A47&" - "&E47&" - "&F47 -> 93071 - History - Thriller | J47: =D47*H47 -> 168.15 | K47: =IF(D47>0,1,0) -> 1
A48: =IFERROR(__xludf.DUMMYFUNCTION("""COMPUTED_VALUE"""),122395.0) -> 122395 | B48: =IFERROR(__xludf.DUMMYFUNCTION("""COMPUTED_VALUE"""),1.0) -> 1 | C48: =IFERROR(__xludf.DUMMYFUNCTION("""COMPUTED_VALUE"""),76.0) -> 76 | D48: =IFERROR(__xludf.DUMMYFUNCTION("""COMPUTED_VALUE"""),2.0) -> 2 | E48: {=_xlfn.XLOOKUP(A48,Product!A:A,Product!B:B,"Bulunamadı")} -> History | F48: {=_xlfn.XLOOKUP(A48,Product!A:A,Product!C:C,"Bulunamadı")} -> Thriller | G48: {=_xlfn.XLOOKUP(A49,Product!A:A,Product!D:D,"Bulunamadı")} -> Maple Grove Press | H48: {=_xlfn.XLOOKUP(A50,Product!A:A,Product!E:E,"Bulunamadı")} -> 6.99 | I48: =A48&" - "&E48&" - "&F48 -> 122395 - History - Thriller | J48: =D48*H48 -> 13.98 | K48: =IF(D48>0,1,0) -> 1
A49: =IFERROR(__xludf.DUMMYFUNCTION("""COMPUTED_VALUE"""),116946.0) -> 116946 | B49: =IFERROR(__xludf.DUMMYFUNCTION("""COMPUTED_VALUE"""),1.0) -> 1 | C49: =IFERROR(__xludf.DUMMYFUNCTION("""COMPUTED_VALUE"""),144.0) -> 144 | D49: =IFERROR(__xludf.DUMMYFUNCTION("""COMPUTED_VALUE"""),85.0) -> 85 | E49: {=_xlfn.XLOOKUP(A49,Product!A:A,Product!B:B,"Bulunamadı")} -> History | F49: {=_xlfn.XLOOKUP(A49,Product!A:A,Product!C:C,"Bulunamadı")} -> Thriller | G49: {=_xlfn.XLOOKUP(A50,Product!A:A,Product!D:D,"Bulunamadı")} -> Maple Grove Press | H49: {=_xlfn.XLOOKUP(A51,Product!A:A,Product!E:E,"Bulunamadı")} -> 8.8 | I49: =A49&" - "&E49&" - "&F49 -> 116946 - History - Thriller | J49: =D49*H49 -> 748 | K49: =IF(D49>0,1,0) -> 1
A50: =IFERROR(__xludf.DUMMYFUNCTION("""COMPUTED_VALUE"""),97538.0) -> 97538 | B50: =IFERROR(__xludf.DUMMYFUNCTION("""COMPUTED_VALUE"""),1.0) -> 1 | C50: =IFERROR(__xludf.DUMMYFUNCTION("""COMPUTED_VALUE"""),135.0) -> 135 | D50: =IFERROR(__xludf.DUMMYFUNCTION("""COMPUTED_VALUE"""),82.0) -> 82 | E50: {=_xlfn.XLOOKUP(A50,Product!A:A,Product!B:B,"Bulunamadı")} -> History | F50: {=_xlfn.XLOOKUP(A50,Product!A:A,Product!C:C,"Bulunamadı")} -> Thriller | G50: {=_xlfn.XLOOKUP(A51,Product!A:A,Product!D:D,"Bulunamadı")} -> Maple Grove Press | H50: {=_xlfn.XLOOKUP(A52,Product!A:A,Product!E:E,"Bulunamadı")} -> 8.45 | I50: =A50&" - "&E50&" - "&F50 -> 97538 - History - Thriller | J50: =D50*H50 -> 692.9 | K50: =IF(D50>0,1,0) -> 1
A51: =IFERROR(__xludf.DUMMYFUNCTION("""COMPUTED_VALUE"""),127238.0) -> 127238 | B51: =IFERROR(__xludf.DUMMYFUNCTION("""COMPUTED_VALUE"""),1.0) -> 1 | C51: =IFERROR(__xludf.DUMMYFUNCTION("""COMPUTED_VALUE"""),147.0) -> 147 | D51: =IFERROR(__xludf.DUMMYFUNCTION("""COMPUTED_VALUE"""),88.0) -> 88 | E51: {=_xlfn.XLOOKUP(A51,Product!A:A,Product!B:B,"Bulunamadı")} -> History | F51: {=_xlfn.XLOOKUP(A51,Product!A:A,Product!C:C,"Bulunamadı")} -> Thriller | G51: {=_xlfn.XLOOKUP(A52,Product!A:A,Product!D:D,"Bulunamadı")} -> Maple Grove Press | H51: {=_xlfn.XLOOKUP(A53,Product!A:A,Product!E:E,"Bulunamadı")} -> 8.46 | I51: =A51&" - "&E51&" - "&F51 -> 127238 - History - Thriller | J51: =D51*H51 -> 744.48 | K51: =IF(D51>0,1,0) -> 1
A52: =IFERROR(__xludf.DUMMYFUNCTION("""COMPUTED_VALUE"""),81646.0) -> 81646 | B52: =IFERROR(__xludf.DUMMYFUNCTION("""COMPUTED_VALUE"""),1.0) -> 1 | C52: =IFERROR(__xludf.DUMMYFUNCTION("""COMPUTED_VALUE"""),399.0) -> 399 | D52: =IFERROR(__xludf.DUMMYFUNCTION("""COMPUTED_VALUE"""),159.0) -> 159 | E52: {=_xlfn.XLOOKUP(A52,Product!A:A,Product!B:B,"Bulunamadı")} -> History | F52: {=_xlfn.XLOOKUP(A52,Product!A:A,Product!C:C,"Bulunamadı")} -> Thriller | G52: {=_xlfn.XLOOKUP(A53,Product!A:A,Product!D:D,"Bulunamadı")} -> Maple Grove Press | H52: {=_xlfn.XLOOKUP(A54,Product!A:A,Product!E:E,"Bulunamadı")} -> 11.73 | I52: =A52&" - "&E52&" - "&F52 -> 81646 - History - Thriller | J52: =D52*H52 -> 1865.07 | K52: =IF(D52>0,1,0) -> 1
A53: =IFERROR(__xludf.DUMMYFUNCTION("""COMPUTED_VALUE"""),81643.0) -> 81643 | B53: =IFERROR(__xludf.DUMMYFUNCTION("""COMPUTED_VALUE"""),1.0) -> 1 | C53: =IFERROR(__xludf.DUMMYFUNCTION("""COMPUTED_VALUE"""),927.0) -> 927 | D53: =IFERROR(__xludf.DUMMYFUNCTION("""COMPUTED_VALUE"""),301.0) -> 301 | E53: {=_xlfn.XLOOKUP(A53,Product!A:A,Product!B:B,"Bulunamadı")} -> History | F53: {=_xlfn.XLOOKUP(A53,Product!A:A,Product!C:C,"Bulunamadı")} -> Thriller | G53: {=_xlfn.XLOOKUP(A54,Product!A:A,Product!D:D,"Bulunamadı")} -> Maple Grove Press | H53: {=_xlfn.XLOOKUP(A55,Product!A:A,Product!E:E,"Bulunamadı")} -> 6.76 | I53: =A53&" - "&E53&" - "&F53 -> 81643 - History - Thriller | J53: =D53*H53 -> 2034.76 | K53: =IF(D53>0,1,0) -> 1
A54: =IFERROR(__xludf.DUMMYFUNCTION("""COMPUTED_VALUE"""),128215.0) -> 128215 | B54: =IFERROR(__xludf.DUMMYFUNCTION("""COMPUTED_VALUE"""),1.0) -> 1 | C54: =IFERROR(__xludf.DUMMYFUNCTION("""COMPUTED_VALUE"""),389.0) -> 389 | D54: =IFERROR(__xludf.DUMMYFUNCTION("""COMPUTED_VALUE"""),243.0) -> 243 | E54: {=_xlfn.XLOOKUP(A54,Product!A:A,Product!B:B,"Bulunamadı")} -> History | F54: {=_xlfn.XLOOKUP(A54,Product!A:A,Product!C:C,"Bulunamadı")} -> Thriller | G54: {=_xlfn.XLOOKUP(A55,Product!A:A,Product!D:D,"Bulunamadı")} -> Maple Grove Press | H54: {=_xlfn.XLOOKUP(A56,Product!A:A,Product!E:E,"Bulunamadı")} -> 8.75 | I54: =A54&" - "&E54&" - "&F54 -> 128215 - History - Thriller | J54: =D54*H54 -> 2126.25 | K54: =IF(D54>0,1,0) -> 1
A55: =IFERROR(__xludf.DUMMYFUNCTION("""COMPUTED_VALUE"""),108022.0) -> 108022 | B55: =IFERROR(__xludf.DUMMYFUNCTION("""COMPUTED_VALUE"""),1.0) -> 1 | C55: =IFERROR(__xludf.DUMMYFUNCTION("""COMPUTED_VALUE"""),455.0) -> 455 | D55: =IFERROR(__xludf.DUMMYFUNCTION("""COMPUTED_VALUE"""),285.0) -> 285 | E55: {=_xlfn.XLOOKUP(A55,Product!A:A,Product!B:B,"Bulunamadı")} -> History | F55: {=_xlfn.XLOOKUP(A55,Product!A:A,Product!C:C,"Bulunamadı")} -> Thriller | G55: {=_xlfn.XLOOKUP(A56,Product!A:A,Product!D:D,"Bulunamadı")} -> Maple Grove Press | H55: {=_xlfn.XLOOKUP(A57,Product!A:A,Product!E:E,"Bulunamadı")} -> 12.18 | I55: =A55&" - "&E55&" - "&F55 -> 108022 - History - Thriller | J55: =D55*H55 -> 3471.3 | K55: =IF(D55>0,1,0) -> 1
A56: =IFERROR(__xludf.DUMMYFUNCTION("""COMPUTED_VALUE"""),81647.0) -> 81647 | B56: =IFERROR(__xludf.DUMMYFUNCTION("""COMPUTED_VALUE"""),0.0) -> 0 | C56: =IFERROR(__xludf.DUMMYFUNCTION("""COMPUTED_VALUE"""),547.0) -> 547 | D56: =IFERROR(__xludf.DUMMYFUNCTION("""COMPUTED_VALUE"""),227.0) -> 227 | E56: {=_xlfn.XLOOKUP(A56,Product!A:A,Product!B:B,"Bulunamadı")} -> History | F56: {=_xlfn.XLOOKUP(A56,Product!A:A,Product!C:C,"Bulunamadı")} -> Thriller | G56: {=_xlfn.XLOOKUP(A57,Product!A:A,Product!D:D,"Bulunamadı")} -> Maple Grove Press | H56: {=_xlfn.XLOOKUP(A58,Product!A:A,Product!E:E,"Bulunamadı")} -> 8.81 | I56: =A56&" - "&E56&" - "&F56 -> 81647 - History - Thriller | J56: =D56*H56 -> 1999.87 | K56: =IF(D56>0,1,0) -> 1
A57: =IFERROR(__xludf.DUMMYFUNCTION("""COMPUTED_VALUE"""),83603.0) -> 83603 | B57: =IFERROR(__xludf.DUMMYFUNCTION("""COMPUTED_VALUE"""),1.0) -> 1 | C57: =IFERROR(__xludf.DUMMYFUNCTION("""COMPUTED_VALUE"""),870.0) -> 870 | D57: =IFERROR(__xludf.DUMMYFUNCTION("""COMPUTED_VALUE"""),105.0) -> 105 | E57: {=_xlfn.XLOOKUP(A57,Product!A:A,Product!B:B,"Bulunamadı")} -> History | F57: {=_xlfn.XLOOKUP(A57,Product!A:A,Product!C:C,"Bulunamadı")} -> Thriller | G57: {=_xlfn.XLOOKUP(A58,Product!A:A,Product!D:D,"Bulunamadı")} -> Maple Grove Press | H57: {=_xlfn.XLOOKUP(A59,Product!A:A,Product!E:E,"Bulunamadı")} -> 3.05 | I57: =A57&" - "&E57&" - "&F57 -> 83603 - History - Thriller | J57: =D57*H57 -> 320.25 | K57: =IF(D57>0,1,0) -> 1
A58: =IFERROR(__xludf.DUMMYFUNCTION("""COMPUTED_VALUE"""),118219.0) -> 118219 | B58: =IFERROR(__xludf.DUMMYFUNCTION("""COMPUTED_VALUE"""),1.0) -> 1 | C58: =IFERROR(__xludf.DUMMYFUNCTION("""COMPUTED_VALUE"""),397.0) -> 397 | D58: =IFERROR(__xludf.DUMMYFUNCTION("""COMPUTED_VALUE"""),207.0) -> 207 | E58: {=_xlfn.XLOOKUP(A58,Product!A:A,Product!B:B,"Bulunamadı")} -> History | F58: {=_xlfn.XLOOKUP(A58,Product!A:A,Product!C:C,"Bulunamadı")} -> Thriller | G58: {=_xlfn.XLOOKUP(A59,Product!A:A,Product!D:D,"Bulunamadı")} -> Cedar Hill Books | H58: {=_xlfn.XLOOKUP(A60,Product!A:A,Product!E:E,"Bulunamadı")} -> 5.24 | I58: =A58&" - "&E58&" - "&F58 -> 118219 - History - Thriller | J58: =D58*H58 -> 1084.68 | K58: =IF(D58>0,1,0) -> 1
A59: =IFERROR(__xludf.DUMMYFUNCTION("""COMPUTED_VALUE"""),120952.0) -> 120952 | B59: =IFERROR(__xludf.DUMMYFUNCTION("""COMPUTED_VALUE"""),1.0) -> 1 | C59: =IFERROR(__xludf.DUMMYFUNCTION("""COMPUTED_VALUE"""),134.0) -> 134 | D59: =IFERROR(__xludf.DUMMYFUNCTION("""COMPUTED_VALUE"""),78.0) -> 78 | E59: {=_xlfn.XLOOKUP(A59,Product!A:A,Product!B:B,"Bulunamadı")} -> History | F59: {=_xlfn.XLOOKUP(A59,Product!A:A,Product!C:C,"Bulunamadı")} -> Thriller | G59: {=_xlfn.XLOOKUP(A60,Product!A:A,Product!D:D,"Bulunamadı")} -> Cedar Hill Books | H59: {=_xlfn.XLOOKUP(A61,Product!A:A,Product!E:E,"Bulunamadı")} -> 3.53 | I59: =A59&" - "&E59&" - "&F59 -> 120952 - History - Thriller | J59: =D59*H59 -> 275.34 | K59: =IF(D59>0,1,0) -> 1
A60: =IFERROR(__xludf.DUMMYFUNCTION("""COMPUTED_VALUE"""),81658.0) -> 81658 | B60: =IFERROR(__xludf.DUMMYFUNCTION("""COMPUTED_VALUE"""),1.0) -> 1 | C60: =IFERROR(__xludf.DUMMYFUNCTION("""COMPUTED_VALUE"""),685.0) -> 685 | D60: =IFERROR(__xludf.DUMMYFUNCTION("""COMPUTED_VALUE"""),42.0) -> 42 | E60: {=_xlfn.XLOOKUP(A60,Product!A:A,Product!B:B,"Bulunamadı")} -> History | F60: {=_xlfn.XLOOKUP(A60,Product!A:A,Product!C:C,"Bulunamadı")} -> Thriller | G60: {=_xlfn.XLOOKUP(A61,Product!A:A,Product!D:D,"Bulunamadı")} -> Cedar Hill Books | H60: {=_xlfn.XLOOKUP(A62,Product!A:A,Product!E:E,"Bulunamadı")} -> 3.72 | I60: =A60&" - "&E60&" - "&F60 -> 81658 - History - Thriller | J60: =D60*H60 -> 156.24 | K60: =IF(D60>0,1,0) -> 1
A61: =IFERROR(__xludf.DUMMYFUNCTION("""COMPUTED_VALUE"""),93047.0) -> 93047 | B61: =IFERROR(__xludf.DUMMYFUNCTION("""COMPUTED_VALUE"""),0.0) -> 0 | C61: =IFERROR(__xludf.DUMMYFUNCTION("""COMPUTED_VALUE"""),525.0) -> 525 | D61: =IFERROR(__xludf.DUMMYFUNCTION("""COMPUTED_VALUE"""),306.0) -> 306 | E61: {=_xlfn.XLOOKUP(A61,Product!A:A,Product!B:B,"Bulunamadı")} -> History | F61: {=_xlfn.XLOOKUP(A61,Product!A:A,Product!C:C,"Bulunamadı")} -> Thriller | G61: {=_xlfn.XLOOKUP(A62,Product!A:A,Product!D:D,"Bulunamadı")} -> Cedar Hill Books | H61: {=_xlfn.XLOOKUP(A63,Product!A:A,Product!E:E,"Bulunamadı")} -> 6.35 | I61: =A61&" - "&E61&" - "&F61 -> 93047 - History - Thriller | J61: =D61*H61 -> 1943.1 | K61: =IF(D61>0,1,0) -> 1
A62: =IFERROR(__xludf.DUMMYFUNCTION("""COMPUTED_VALUE"""),83807.0) -> 83807 | B62: =IFERROR(__xludf.DUMMYFUNCTION("""COMPUTED_VALUE"""),1.0) -> 1 | C62: =IFERROR(__xludf.DUMMYFUNCTION("""COMPUTED_VALUE"""),596.0) -> 596 | D62: =IFERROR(__xludf.DUMMYFUNCTION("""COMPUTED_VALUE"""),321.0) -> 321 | E62: {=_xlfn.XLOOKUP(A62,Product!A:A,Product!B:B,"Bulunamadı")} -> History | F62: {=_xlfn.XLOOKUP(A62,Product!A:A,Product!C:C,"Bulunamadı")} -> Thriller | G62: {=_xlfn.XLOOKUP(A63,Product!A:A,Product!D:D,"Bulunamadı")} -> Cedar Hill Books | H62: {=_xlfn.XLOOKUP(A64,Product!A:A,Product!E:E,"Bulunamadı")} -> 4.3 | I62: =A62&" - "&E62&" - "&F62 -> 83807 - History - Thriller | J62: =D62*H62 -> 1380.3 | K62: =IF(D62>0,1,0) -> 1
A63: =IFERROR(__xludf.DUMMYFUNCTION("""COMPUTED_VALUE"""),92915.0) -> 92915 | B63: =IFERROR(__xludf.DUMMYFUNCTION("""COMPUTED_VALUE"""),0.0) -> 0 | C63: =IFERROR(__xludf.DUMMYFUNCTION("""COMPUTED_VALUE"""),861.0) -> 861 | D63: =IFERROR(__xludf.DUMMYFUNCTION("""COMPUTED_VALUE"""),576.0) -> 576 | E63: {=_xlfn.XLOOKUP(A63,Product!A:A,Product!B:B,"Bulunamadı")} -> History | F63: {=_xlfn.XLOOKUP(A63,Product!A:A,Product!C:C,"Bulunamadı")} -> Thriller | G63: {=_xlfn.XLOOKUP(A64,Product!A:A,Product!D:D,"Bulunamadı")} -> Cedar Hill Books | H63: {=_xlfn.XLOOKUP(A65,Product!A:A,Product!E:E,"Bulunamadı")} -> 3.55 | I63: =A63&" - "&E63&" - "&F63 -> 92915 - History - Thriller | J63: =D63*H63 -> 2044.8 | K63: =IF(D63>0,1,0) -> 1
A64: =IFERROR(__xludf.DUMMYFUNCTION("""COMPUTED_VALUE"""),81653.0) -> 81653 | B64: =IFERROR(__xludf.DUMMYFUNCTION("""COMPUTED_VALUE"""),0.0) -> 0 | C64: =IFERROR(__xludf.DUMMYFUNCTION("""COMPUTED_VALUE"""),64.0) -> 64 | D64: =IFERROR(__xludf.DUMMYFUNCTION("""COMPUTED_VALUE"""),31.0) -> 31 | E64: {=_xlfn.XLOOKUP(A64,Product!A:A,Product!B:B,"Bulunamadı")} -> History | F64: {=_xlfn.XLOOKUP(A64,Product!A:A,Product!C:C,"Bulunamadı")} -> Thriller | G64: {=_xlfn.XLOOKUP(A65,Product!A:A,Product!D:D,"Bulunamadı")} -> Cedar Hill Books | H64: {=_xlfn.XLOOKUP(A66,Product!A:A,Product!E:E,"Bulunamadı")} -> 2.33 | I64: =A64&" - "&E64&" - "&F64 -> 81653 - History - Thriller | J64: =D64*H64 -> 72.23 | K64: =IF(D64>0,1,0) -> 1
A65: =IFERROR(__xludf.DUMMYFUNCTION("""COMPUTED_VALUE"""),81618.0) -> 81618 | B65: =IFERROR(__xludf.DUMMYFUNCTION("""COMPUTED_VALUE"""),1.0) -> 1 | C65: =IFERROR(__xludf.DUMMYFUNCTION("""COMPUTED_VALUE"""),124.0) -> 124 | D65: =IFERROR(__xludf.DUMMYFUNCTION("""COMPUTED_VALUE"""),37.0) -> 37 | E65: {=_xlfn.XLOOKUP(A65,Product!A:A,Product!B:B,"Bulunamadı")} -> History | F65: {=_xlfn.XLOOKUP(A65,Product!A:A,Product!C:C,"Bulunamadı")} -> Thriller | G65: {=_xlfn.XLOOKUP(A66,Product!A:A,Product!D:D,"Bulunamadı")} -> Willow Creek Publishing | H65: {=_xlfn.XLOOKUP(A67,Product!A:A,Product!E:E,"Bulunamadı")} -> 3 | I65: =A65&" - "&E65&" - "&F65 -> 81618 - History - Thriller | J65: =D65*H65 -> 111 | K65: =IF(D65>0,1,0) -> 1
A66: =IFERROR(__xludf.DUMMYFUNCTION("""COMPUTED_VALUE"""),118241.0) -> 118241 | B66: =IFERROR(__xludf.DUMMYFUNCTION("""COMPUTED_VALUE"""),1.0) -> 1 | C66: =IFERROR(__xludf.DUMMYFUNCTION("""COMPUTED_VALUE"""),897.0) -> 897 | D66: =IFERROR(__xludf.DUMMYFUNCTION("""COMPUTED_VALUE"""),1.0) -> 1 | E66: {=_xlfn.XLOOKUP(A66,Product!A:A,Product!B:B,"Bulunamadı")} -> History | F66: {=_xlfn.XLOOKUP(A66,Product!A:A,Product!C:C,"Bulunamadı")} -> Thriller | G66: {=_xlfn.XLOOKUP(A67,Product!A:A,Product!D:D,"Bulunamadı")} -> Willow Creek Publishing | H66: {=_xlfn.XLOOKUP(A68,Product!A:A,Product!E:E,"Bulunamadı")} -> 3.02 | I66: =A66&" - "&E66&" - "&F66 -> 118241 - History - Thriller | J66: =D66*H66 -> 3.02 | K66: =IF(D66>0,1,0) -> 1
A67: =IFERROR(__xludf.DUMMYFUNCTION("""COMPUTED_VALUE"""),48634.0) -> 48634 | B67: =IFERROR(__xludf.DUMMYFUNCTION("""COMPUTED_VALUE"""),1.0) -> 1 | C67: =IFERROR(__xludf.DUMMYFUNCTION("""COMPUTED_VALUE"""),832.0) -> 832 | D67: =IFERROR(__xludf.DUMMYFUNCTION("""COMPUTED_VALUE"""),180.0) -> 180 | E67: {=_xlfn.XLOOKUP(A67,Product!A:A,Product!B:B,"Bulunamadı")} -> History | F67: {=_xlfn.XLOOKUP(A67,Product!A:A,Product!C:C,"Bulunamadı")} -> Thriller | G67: {=_xlfn.XLOOKUP(A68,Product!A:A,Product!D:D,"Bulunamadı")} -> Willow Creek Publishing | H67: {=_xlfn.XLOOKUP(A69,Product!A:A,Product!E:E,"Bulunamadı")} -> 2.63 | I67: =A67&" - "&E67&" - "&F67 -> 48634 - History - Thriller | J67: =D67*H67 -> 473.4 | K67: =IF(D67>0,1,0) -> 1
A68: =IFERROR(__xludf.DUMMYFUNCTION("""COMPUTED_VALUE"""),48636.0) -> 48636 | B68: =IFERROR(__xludf.DUMMYFUNCTION("""COMPUTED_VALUE"""),1.0) -> 1 | C68: =IFERROR(__xludf.DUMMYFUNCTION("""COMPUTED_VALUE"""),37.0) -> 37 | D68: =IFERROR(__xludf.DUMMYFUNCTION("""COMPUTED_VALUE"""),10.0) -> 10 | E68: {=_xlfn.XLOOKUP(A68,Product!A:A,Product!B:B,"Bulunamadı")} -> History | F68: {=_xlfn.XLOOKUP(A68,Product!A:A,Product!C:C,"Bulunamadı")} -> Thriller | G68: {=_xlfn.XLOOKUP(A69,Product!A:A,Product!D:D,"Bulunamadı")} -> Willow Creek Publishing | H68: {=_xlfn.XLOOKUP(A70,Product!A:A,Product!E:E,"Bulunamadı")} -> 2.13 | I68: =A68&" - "&E68&" - "&F68 -> 48636 - History - Thriller | J68: =D68*H68 -> 21.3 | K68: =IF(D68>0,1,0) -> 1
A69: =IFERROR(__xludf.DUMMYFUNCTION("""COMPUTED_VALUE"""),48629.0) -> 48629 | B69: =IFERROR(__xludf.DUMMYFUNCTION("""COMPUTED_VALUE"""),1.0) -> 1 | C69: =IFERROR(__xludf.DUMMYFUNCTION("""COMPUTED_VALUE"""),935.0) -> 935 | D69: =IFERROR(__xludf.DUMMYFUNCTION("""COMPUTED_VALUE"""),635.0) -> 635 | E69: {=_xlfn.XLOOKUP(A69,Product!A:A,Product!B:B,"Bulunamadı")} -> History | F69: {=_xlfn.XLOOKUP(A69,Product!A:A,Product!C:C,"Bulunamadı")} -> Thriller | G69: {=_xlfn.XLOOKUP(A70,Product!A:A,Product!D:D,"Bulunamadı")} -> Willow Creek Publishing | H69: {=_xlfn.XLOOKUP(A71,Product!A:A,Product!E:E,"Bulunamadı")} -> 4.21 | I69: =A69&" - "&E69&" - "&F69 -> 48629 - History - Thriller | J69: =D69*H69 -> 2673.35 | K69: =IF(D69>0,1,0) -> 1
A70: =IFERROR(__xludf.DUMMYFUNCTION("""COMPUTED_VALUE"""),47400.0) -> 47400 | B70: =IFERROR(__xludf.DUMMYFUNCTION("""COMPUTED_VALUE"""),1.0) -> 1 | C70: =IFERROR(__xludf.DUMMYFUNCTION("""COMPUTED_VALUE"""),868.0) -> 868 | D70: =IFERROR(__xludf.DUMMYFUNCTION("""COMPUTED_VALUE"""),396.0) -> 396 | E70: {=_xlfn.XLOOKUP(A70,Product!A:A,Product!B:B,"Bulunamadı")} -> History | F70: {=_xlfn.XLOOKUP(A70,Product!A:A,Product!C:C,"Bulunamadı")} -> Thriller | G70: {=_xlfn.XLOOKUP(A71,Product!A:A,Product!D:D,"Bulunamadı")} -> Willow Creek Publishing | H70: {=_xlfn.XLOOKUP(A72,Product!A:A,Product!E:E,"Bulunamadı")} -> 3.5 | I70: =A70&" - "&E70&" - "&F70 -> 47400 - History - Thriller | J70: =D70*H70 -> 1386 | K70: =IF(D70>0,1,0) -> 1
A71: =IFERROR(__xludf.DUMMYFUNCTION("""COMPUTED_VALUE"""),111237.0) -> 111237 | B71: =IFERROR(__xludf.DUMMYFUNCTION("""COMPUTED_VALUE"""),0.0) -> 0 | C71: =IFERROR(__xludf.DUMMYFUNCTION("""COMPUTED_VALUE"""),445.0) -> 445 | D71: =IFERROR(__xludf.DUMMYFUNCTION("""COMPUTED_VALUE"""),128.0) -> 128 | E71: {=_xlfn.XLOOKUP(A71,Product!A:A,Product!B:B,"Bulunamadı")} -> History | F71: {=_xlfn.XLOOKUP(A71,Product!A:A,Product!C:C,"Bulunamadı")} -> Thriller | G71: {=_xlfn.XLOOKUP(A72,Product!A:A,Product!D:D,"Bulunamadı")} -> Bright Horizon Press | H71: {=_xlfn.XLOOKUP(A73,Product!A:A,Product!E:E,"Bulunamadı")} -> 4.41 | I71: =A71&" - "&E71&" - "&F71 -> 111237 - History - Thriller | J71: =D71*H71 -> 564.48 | K71: =IF(D71>0,1,0) -> 1
A72: =IFERROR(__xludf.DUMMYFUNCTION("""COMPUTED_VALUE"""),18042.0) -> 18042 | B72: =IFERROR(__xludf.DUMMYFUNCTION("""COMPUTED_VALUE"""),0.0) -> 0 | C72: =IFERROR(__xludf.DUMMYFUNCTION("""COMPUTED_VALUE"""),232.0) -> 232 | D72: =IFERROR(__xludf.DUMMYFUNCTION("""COMPUTED_VALUE"""),214.0) -> 214 | E72: {=_xlfn.XLOOKUP(A72,Product!A:A,Product!B:B,"Bulunamadı")} -> History | F72: {=_xlfn.XLOOKUP(A72,Product!A:A,Product!C:C,"Bulunamadı")} -> Thriller | G72: {=_xlfn.XLOOKUP(A73,Product!A:A,Product!D:D,"Bulunamadı")} -> Bright Horizon Press | H72: {=_xlfn.XLOOKUP(A74,Product!A:A,Product!E:E,"Bulunamadı")} -> 2.29 | I72: =A72&" - "&E72&" - "&F72 -> 18042 - History - Thriller | J72: =D72*H72 -> 490.06 | K72: =IF(D72>0,1,0) -> 1
A73: =IFERROR(__xludf.DUMMYFUNCTION("""COMPUTED_VALUE"""),114978.0) -> 114978 | B73: =IFERROR(__xludf.DUMMYFUNCTION("""COMPUTED_VALUE"""),0.0) -> 0 | C73: =IFERROR(__xludf.DUMMYFUNCTION("""COMPUTED_VALUE"""),315.0) -> 315 | D73: =IFERROR(__xludf.DUMMYFUNCTION("""COMPUTED_VALUE"""),278.0) -> 278 | E73: {=_xlfn.XLOOKUP(A73,Product!A:A,Product!B:B,"Bulunamadı")} -> History | F73: {=_xlfn.XLOOKUP(A73,Product!A:A,Product!C:C,"Bulunamadı")} -> Thriller | G73: {=_xlfn.XLOOKUP(A74,Product!A:A,Product!D:D,"Bulunamadı")} -> Bright Horizon Press | H73: {=_xlfn.XLOOKUP(A75,Product!A:A,Product!E:E,"Bulunamadı")} -> 4.19 | I73: =A73&" - "&E73&" - "&F73 -> 114978 - History - Thriller | J73: =D73*H73 -> 1164.82 | K73: =IF(D73>0,1,0) -> 1
A74: =IFERROR(__xludf.DUMMYFUNCTION("""COMPUTED_VALUE"""),82980.0) -> 82980 | B74: =IFERROR(__xludf.DUMMYFUNCTION("""COMPUTED_VALUE"""),1.0) -> 1 | C74: =IFERROR(__xludf.DUMMYFUNCTION("""COMPUTED_VALUE"""),356.0) -> 356 | D74: =IFERROR(__xludf.DUMMYFUNCTION("""COMPUTED_VALUE"""),164.0) -> 164 | E74: {=_xlfn.XLOOKUP(A74,Product!A:A,Product!B:B,"Bulunamadı")} -> History | F74: {=_xlfn.XLOOKUP(A74,Product!A:A,Product!C:C,"Bulunamadı")} -> Thriller | G74: {=_xlfn.XLOOKUP(A75,Product!A:A,Product!D:D,"Bulunamadı")} -> Bright Horizon Press | H74: {=_xlfn.XLOOKUP(A76,Product!A:A,Product!E:E,"Bulunamadı")} -> 3.99 | I74: =A74&" - "&E74&" - "&F74 -> 82980 - History - Thriller | J74: =D74*H74 -> 654.36 | K74: =IF(D74>0,1,0) -> 1
A75: =IFERROR(__xludf.DUMMYFUNCTION("""COMPUTED_VALUE"""),83093.0) -> 83093 | B75: =IFERROR(__xludf.DUMMYFUNCTION("""COMPUTED_VALUE"""),0.0) -> 0 | C75: =IFERROR(__xludf.DUMMYFUNCTION("""COMPUTED_VALUE"""),442.0) -> 442 | D75: =IFERROR(__xludf.DUMMYFUNCTION("""COMPUTED_VALUE"""),385.0) -> 385 | E75: {=_xlfn.XLOOKUP(A75,Product!A:A,Product!B:B,"Bulunamadı")} -> History | F75: {=_xlfn.XLOOKUP(A75,Product!A:A,Product!C:C,"Bulunamadı")} -> Thriller | G75: {=_xlfn.XLOOKUP(A76,Product!A:A,Product!D:D,"Bulunamadı")} -> Bright Horizon Press | H75: {=_xlfn.XLOOKUP(A77,Product!A:A,Product!E:E,"Bulunamadı")} -> 3.99 | I75: =A75&" - "&E75&" - "&F75 -> 83093 - History - Thriller | J75: =D75*H75 -> 1536.15 | K75: =IF(D75>0,1,0) -> 1
A76: =IFERROR(__xludf.DUMMYFUNCTION("""COMPUTED_VALUE"""),18134.0) -> 18134 | B76: =IFERROR(__xludf.DUMMYFUNCTION("""COMPUTED_VALUE"""),0.0) -> 0 | C76: =IFERROR(__xludf.DUMMYFUNCTION("""COMPUTED_VALUE"""),492.0) -> 492 | D76: =IFERROR(__xludf.DUMMYFUNCTION("""COMPUTED_VALUE"""),381.0) -> 381 | E76: {=_xlfn.XLOOKUP(A76,Product!A:A,Product!B:B,"Bulunamadı")} -> History | F76: {=_xlfn.XLOOKUP(A76,Product!A:A,Product!C:C,"Bulunamadı")} -> Thriller | G76: {=_xlfn.XLOOKUP(A77,Product!A:A,Product!D:D,"Bulunamadı")} -> Bright Horizon Press | H76: {=_xlfn.XLOOKUP(A78,Product!A:A,Product!E:E,"Bulunamadı")} -> 5.27 | I76: =A76&" - "&E76&" - "&F76 -> 18134 - History - Thriller | J76: =D76*H76 -> 2007.87 | K76: =IF(D76>0,1,0) -> 1
A77: =IFERROR(__xludf.DUMMYFUNCTION("""COMPUTED_VALUE"""),107857.0) -> 107857 | B77: =IFERROR(__xludf.DUMMYFUNCTION("""COMPUTED_VALUE"""),0.0) -> 0 | C77: =IFERROR(__xludf.DUMMYFUNCTION("""COMPUTED_VALUE"""),645.0) -> 645 | D77: =IFERROR(__xludf.DUMMYFUNCTION("""COMPUTED_VALUE"""),327.0) -> 327 | E77: {=_xlfn.XLOOKUP(A77,Product!A:A,Product!B:B,"Bulunamadı")} -> History | F77: {=_xlfn.XLOOKUP(A77,Product!A:A,Product!C:C,"Bulunamadı")} -> Thriller | G77: {=_xlfn.XLOOKUP(A78,Product!A:A,Product!D:D,"Bulunamadı")} -> Bright Horizon Press | H77: {=_xlfn.XLOOKUP(A79,Product!A:A,Product!E:E,"Bulunamadı")} -> 5.32 | I77: =A77&" - "&E77&" - "&F77 -> 107857 - History - Thriller | J77: =D77*H77 -> 1739.64 | K77: =IF(D77>0,1,0) -> 1
A78: =IFERROR(__xludf.DUMMYFUNCTION("""COMPUTED_VALUE"""),18136.0) -> 18136 | B78: =IFERROR(__xludf.DUMMYFUNCTION("""COMPUTED_VALUE"""),1.0) -> 1 | C78: =IFERROR(__xludf.DUMMYFUNCTION("""COMPUTED_VALUE"""),863.0) -> 863 | D78: =IFERROR(__xludf.DUMMYFUNCTION("""COMPUTED_VALUE"""),821.0) -> 821 | E78: {=_xlfn.XLOOKUP(A78,Product!A:A,Product!B:B,"Bulunamadı")} -> History | F78: {=_xlfn.XLOOKUP(A78,Product!A:A,Product!C:C,"Bulunamadı")} -> Thriller | G78: {=_xlfn.XLOOKUP(A79,Product!A:A,Product!D:D,"Bulunamadı")} -> Bright Horizon Press | H78: {=_xlfn.XLOOKUP(A80,Product!A:A,Product!E:E,"Bulunamadı")} -> 4.74 | I78: =A78&" - "&E78&" - "&F78 -> 18136 - History - Thriller | J78: =D78*H78 -> 3891.54 | K78: =IF(D78>0,1,0) -> 1
A79: =IFERROR(__xludf.DUMMYFUNCTION("""COMPUTED_VALUE"""),69138.0) -> 69138 | B79: =IFERROR(__xludf.DUMMYFUNCTION("""COMPUTED_VALUE"""),1.0) -> 1 | C79: =IFERROR(__xludf.DUMMYFUNCTION("""COMPUTED_VALUE"""),43.0) -> 43 | D79: =IFERROR(__xludf.DUMMYFUNCTION("""COMPUTED_VALUE"""),27.0) -> 27 | E79: {=_xlfn.XLOOKUP(A79,Product!A:A,Product!B:B,"Bulunamadı")} -> History | F79: {=_xlfn.XLOOKUP(A79,Product!A:A,Product!C:C,"Bulunamadı")} -> Thriller | G79: {=_xlfn.XLOOKUP(A80,Product!A:A,Product!D:D,"Bulunamadı")} -> Bright Horizon Press | H79: {=_xlfn.XLOOKUP(A81,Product!A:A,Product!E:E,"Bulunamadı")} -> 5.05 | I79: =A79&" - "&E79&" - "&F79 -> 69138 - History - Thriller | J79: =D79*H79 -> 136.35 | K79: =IF(D79>0,1,0) -> 1
A80: =IFERROR(__xludf.DUMMYFUNCTION("""COMPUTED_VALUE"""),74828.0) -> 74828 | B80: =IFERROR(__xludf.DUMMYFUNCTION("""COMPUTED_VALUE"""),0.0) -> 0 | C80: =IFERROR(__xludf.DUMMYFUNCTION("""COMPUTED_VALUE"""),654.0) -> 654 | D80: =IFERROR(__xludf.DUMMYFUNCTION("""COMPUTED_VALUE"""),613.0) -> 613 | E80: {=_xlfn.XLOOKUP(A80,Product!A:A,Product!B:B,"Bulunamadı")} -> History | F80: {=_xlfn.XLOOKUP(A80,Product!A:A,Product!C:C,"Bulunamadı")} -> Thriller | G80: {=_xlfn.XLOOKUP(A81,Product!A:A,Product!D:D,"Bulunamadı")} -> Bright Horizon Press | H80: {=_xlfn.XLOOKUP(A82,Product!A:A,Product!E:E,"Bulunamadı")} -> 2.95 | I80: =A80&" - "&E80&" - "&F80 -> 74828 - History - Thriller | J80: =D80*H80 -> 1808.35 | K80: =IF(D80>0,1,0) -> 1
A81: =IFERROR(__xludf.DUMMYFUNCTION("""COMPUTED_VALUE"""),74884.0) -> 74884 | B81: =IFERROR(__xludf.DUMMYFUNCTION("""COMPUTED_VALUE"""),1.0) -> 1 | C81: =IFERROR(__xludf.DUMMYFUNCTION("""COMPUTED_VALUE"""),2.0) -> 2 | D81: =IFERROR(__xludf.DUMMYFUNCTION("""COMPUTED_VALUE"""),2.0) -> 2 | E81: {=_xlfn.XLOOKUP(A81,Product!A:A,Product!B:B,"Bulunamadı")} -> History | F81: {=_xlfn.XLOOKUP(A81,Product!A:A,Product!C:C,"Bulunamadı")} -> Thriller | G81: {=_xlfn.XLOOKUP(A82,Product!A:A,Product!D:D,"Bulunamadı")} -> Bright Horizon Press | H81: {=_xlfn.XLOOKUP(A83,Product!A:A,Product!E:E,"Bulunamadı")} -> 1.92 | I81: =A81&" - "&E81&" - "&F81 -> 74884 - History - Thriller | J81: =D81*H81 -> 3.84 | K81: =IF(D81>0,1,0) -> 1
A82: =IFERROR(__xludf.DUMMYFUNCTION("""COMPUTED_VALUE"""),127232.0) -> 127232 | B82: =IFERROR(__xludf.DUMMYFUNCTION("""COMPUTED_VALUE"""),1.0) -> 1 | C82: =IFERROR(__xludf.DUMMYFUNCTION("""COMPUTED_VALUE"""),705.0) -> 705 | D82: =IFERROR(__xludf.DUMMYFUNCTION("""COMPUTED_VALUE"""),648.0) -> 648 | E82: {=_xlfn.XLOOKUP(A82,Product!A:A,Product!B:B,"Bulunamadı")} -> History | F82: {=_xlfn.XLOOKUP(A82,Product!A:A,Product!C:C,"Bulunamadı")} -> Thriller | G82: {=_xlfn.XLOOKUP(A83,Product!A:A,Product!D:D,"Bulunamadı")} -> Bright Horizon Press | H82: {=_xlfn.XLOOKUP(A84,Product!A:A,Product!E:E,"Bulunamadı")} -> 6.07 | I82: =A82&" - "&E82&" - "&F82 -> 127232 - History - Thriller | J82: =D82*H82 -> 3933.36 | K82: =IF(D82>0,1,0) -> 1
A83: =IFERROR(__xludf.DUMMYFUNCTION("""COMPUTED_VALUE"""),82979.0) -> 82979 | B83: =IFERROR(__xludf.DUMMYFUNCTION("""COMPUTED_VALUE"""),1.0) -> 1 | C83: =IFERROR(__xludf.DUMMYFUNCTION("""COMPUTED_VALUE"""),774.0) -> 774 | D83: =IFERROR(__xludf.DUMMYFUNCTION("""COMPUTED_VALUE"""),723.0) -> 723 | E83: {=_xlfn.XLOOKUP(A83,Product!A:A,Product!B:B,"Bulunamadı")} -> History | F83: {=_xlfn.XLOOKUP(A83,Product!A:A,Product!C:C,"Bulunamadı")} -> Thriller | G83: {=_xlfn.XLOOKUP(A84,Product!A:A,Product!D:D,"Bulunamadı")} -> Bright Horizon Press | H83: {=_xlfn.XLOOKUP(A85,Product!A:A,Product!E:E,"Bulunamadı")} -> 3.58 | I83: =A83&" - "&E83&" - "&F83 -> 82979 - History - Thriller | J83: =D83*H83 -> 2588.34 | K83: =IF(D83>0,1,0) -> 1
A84: =IFERROR(__xludf.DUMMYFUNCTION("""COMPUTED_VALUE"""),18138.0) -> 18138 | B84: =IFERROR(__xludf.DUMMYFUNCTION("""COMPUTED_VALUE"""),0.0) -> 0 | C84: =IFERROR(__xludf.DUMMYFUNCTION("""COMPUTED_VALUE"""),571.0) -> 571 | D84: =IFERROR(__xludf.DUMMYFUNCTION("""COMPUTED_VALUE"""),353.0) -> 353 | E84: {=_xlfn.XLOOKUP(A84,Product!A:A,Product!B:B,"Bulunamadı")} -> History | F84: {=_xlfn.XLOOKUP(A84,Product!A:A,Product!C:C,"Bulunamadı")} -> Thriller | G84: {=_xlfn.XLOOKUP(A85,Product!A:A,Product!D:D,"Bulunamadı")} -> Evergreen House | H84: {=_xlfn.XLOOKUP(A86,Product!A:A,Product!E:E,"Bulunamadı")} -> 3.72 | I84: =A84&" - "&E84&" - "&F84 -> 18138 - History - Thriller | J84: =D84*H84 -> 1313.16 | K84: =IF(D84>0,1,0) -> 1
A85: =IFERROR(__xludf.DUMMYFUNCTION("""COMPUTED_VALUE"""),127003.0) -> 127003 | B85: =IFERROR(__xludf.DUMMYFUNCTION("""COMPUTED_VALUE"""),0.0) -> 0 | C85: =IFERROR(__xludf.DUMMYFUNCTION("""COMPUTED_VALUE"""),735.0) -> 735 | D85: =IFERROR(__xludf.DUMMYFUNCTION("""COMPUTED_VALUE"""),384.0) -> 384 | E85: {=_xlfn.XLOOKUP(A85,Product!A:A,Product!B:B,"Bulunamadı")} -> History | F85: {=_xlfn.XLOOKUP(A85,Product!A:A,Product!C:C,"Bulunamadı")} -> Thriller | G85: {=_xlfn.XLOOKUP(A86,Product!A:A,Product!D:D,"Bulunamadı")} | H85: {=_xlfn.XLOOKUP(A87,Product!A:A,Product!E:E,"Bulunamadı")} -> 5.07 | I85: =A85&" - "&E85&" - "&F85 -> 127003 - History - Thriller | J85: =D85*H85 -> 1946.88 | K85: =IF(D85>0,1,0) -> 1
A86: =IFERROR(__xludf.DUMMYFUNCTION("""COMPUTED_VALUE"""),6036.0) -> 6036 | B86: =IFERROR(__xludf.DUMMYFUNCTION("""COMPUTED_VALUE"""),1.0) -> 1 | C86: =IFERROR(__xludf.DUMMYFUNCTION("""COMPUTED_VALUE"""),429.0) -> 429 | D86: =IFERROR(__xludf.DUMMYFUNCTION("""COMPUTED_VALUE"""),420.0) -> 420 | E86: {=_xlfn.XLOOKUP(A86,Product!A:A,Product!B:B,"Bulunamadı")} -> History | F86: {=_xlfn.XLOOKUP(A86,Product!A:A,Product!C:C,"Bulunamadı")} -> Crime | G86: {=_xlfn.XLOOKUP(A87,Product!A:A,Product!D:D,"Bulunamadı")} | H86: {=_xlfn.XLOOKUP(A88,Product!A:A,Product!E:E,"Bulunamadı")} -> 4.47 | I86: =A86&" - "&E86&" - "&F86 -> 6036 - History - Crime | J86: =D86*H86 -> 1877.4 | K86: =IF(D86>0,1,0) -> 1
A87: =IFERROR(__xludf.DUMMYFUNCTION("""COMPUTED_VALUE"""),6046.0) -> 6046 | B87: =IFERROR(__xludf.DUMMYFUNCTION("""COMPUTED_VALUE"""),0.0) -> 0 | C87: =IFERROR(__xludf.DUMMYFUNCTION("""COMPUTED_VALUE"""),732.0) -> 732 | D87: =IFERROR(__xludf.DUMMYFUNCTION("""COMPUTED_VALUE"""),319.0) -> 319 | E87: {=_xlfn.XLOOKUP(A87,Product!A:A,Product!B:B,"Bulunamadı")} -> History | F87: {=_xlfn.XLOOKUP(A87,Product!A:A,Product!C:C,"Bulunamadı")} -> Crime | G87: {=_xlfn.XLOOKUP(A88,Product!A:A,Product!D:D,"Bulunamadı")} | H87: {=_xlfn.XLOOKUP(A89,Product!A:A,Product!E:E,"Bulunamadı")} -> 3.36 | I87: =A87&" - "&E87&" - "&F87 -> 6046 - History - Crime | J87: =D87*H87 -> 1071.84 | K87: =IF(D87>0,1,0) -> 1
A88: =IFERROR(__xludf.DUMMYFUNCTION("""COMPUTED_VALUE"""),6037.0) -> 6037 | B88: =IFERROR(__xludf.DUMMYFUNCTION("""COMPUTED_VALUE"""),0.0) -> 0 | C88: =IFERROR(__xludf.DUMMYFUNCTION("""COMPUTED_VALUE"""),271.0) -> 271 | D88: =IFERROR(__xludf.DUMMYFUNCTION("""COMPUTED_VALUE"""),227.0) -> 227 | E88: {=_xlfn.XLOOKUP(A88,Product!A:A,Product!B:B,"Bulunamadı")} -> History | F88: {=_xlfn.XLOOKUP(A88,Product!A:A,Product!C:C,"Bulunamadı")} -> Crime | G88: {=_xlfn.XLOOKUP(A89,Product!A:A,Product!D:D,"Bulunamadı")} | H88: {=_xlfn.XLOOKUP(A90,Product!A:A,Product!E:E,"Bulunamadı")} -> 3.16 | I88: =A88&" - "&E88&" - "&F88 -> 6037 - History - Crime | J88: =D88*H88 -> 717.32 | K88: =IF(D88>0,1,0) -> 1
A89: =IFERROR(__xludf.DUMMYFUNCTION("""COMPUTED_VALUE"""),6026.0) -> 6026 | B89: =IFERROR(__xludf.DUMMYFUNCTION("""COMPUTED_VALUE"""),1.0) -> 1 | C89: =IFERROR(__xludf.DUMMYFUNCTION("""COMPUTED_VALUE"""),111.0) -> 111 | D89: =IFERROR(__xludf.DUMMYFUNCTION("""COMPUTED_VALUE"""),23.0) -> 23 | E89: {=_xlfn.XLOOKUP(A89,Product!A:A,Product!B:B,"Bulunamadı")} -> History | F89: {=_xlfn.XLOOKUP(A89,Product!A:A,Product!C:C,"Bulunamadı")} -> Crime | G89: {=_xlfn.XLOOKUP(A90,Product!A:A,Product!D:D,"Bulunamadı")} | H89: {=_xlfn.XLOOKUP(A91,Product!A:A,Product!E:E,"Bulunamadı")} -> 4.55 | I89: =A89&" - "&E89&" - "&F89 -> 6026 - History - Crime | J89: =D89*H89 -> 104.65 | K89: =IF(D89>0,1,0) -> 1
A90: =IFERROR(__xludf.DUMMYFUNCTION("""COMPUTED_VALUE"""),47431.0) -> 47431 | B90: =IFERROR(__xludf.DUMMYFUNCTION("""COMPUTED_VALUE"""),0.0) -> 0 | C90: =IFERROR(__xludf.DUMMYFUNCTION("""COMPUTED_VALUE"""),81.0) -> 81 | D90: =IFERROR(__xludf.DUMMYFUNCTION("""COMPUTED_VALUE"""),6.0) -> 6 | E90: {=_xlfn.XLOOKUP(A90,Product!A:A,Product!B:B,"Bulunamadı")} -> History | F90: {=_xlfn.XLOOKUP(A90,Product!A:A,Product!C:C,"Bulunamadı")} -> Crime | G90: {=_xlfn.XLOOKUP(A91,Product!A:A,Product!D:D,"Bulunamadı")} | H90: {=_xlfn.XLOOKUP(A92,Product!A:A,Product!E:E,"Bulunamadı")} -> 5.48 | I90: =A90&" - "&E90&" - "&F90 -> 47431 - History - Crime | J90: =D90*H90 -> 32.88 | K90: =IF(D90>0,1,0) -> 1
A91: =IFERROR(__xludf.DUMMYFUNCTION("""COMPUTED_VALUE"""),82914.0) -> 82914 | B91: =IFERROR(__xludf.DUMMYFUNCTION("""COMPUTED_VALUE"""),1.0) -> 1 | C91: =IFERROR(__xludf.DUMMYFUNCTION("""COMPUTED_VALUE"""),486.0) -> 486 | D91: =IFERROR(__xludf.DUMMYFUNCTION("""COMPUTED_VALUE"""),345.0) -> 345 | E91: {=_xlfn.XLOOKUP(A91,Product!A:A,Product!B:B,"Bulunamadı")} -> History | F91: {=_xlfn.XLOOKUP(A91,Product!A:A,Product!C:C,"Bulunamadı")} -> Crime | G91: {=_xlfn.XLOOKUP(A92,Product!A:A,Product!D:D,"Bulunamadı")} | H91: {=_xlfn.XLOOKUP(A93,Product!A:A,Product!E:E,"Bulunamadı")} -> 4.12 | I91: =A91&" - "&E91&" - "&F91 -> 82914 - History - Crime | J91: =D91*H91 -> 1421.4 | K91: =IF(D91>0,1,0) -> 1
A92: =IFERROR(__xludf.DUMMYFUNCTION("""COMPUTED_VALUE"""),6044.0) -> 6044 | B92: =IFERROR(__xludf.DUMMYFUNCTION("""COMPUTED_VALUE"""),1.0) -> 1 | C92: =IFERROR(__xludf.DUMMYFUNCTION("""COMPUTED_VALUE"""),197.0) -> 197 | D92: =IFERROR(__xludf.DUMMYFUNCTION("""COMPUTED_VALUE"""),167.0) -> 167 | E92: {=_xlfn.XLOOKUP(A92,Product!A:A,Product!B:B,"Bulunamadı")} -> History | F92: {=_xlfn.XLOOKUP(A92,Product!A:A,Product!C:C,"Bulunamadı")} -> Crime | G92: {=_xlfn.XLOOKUP(A93,Product!A:A,Product!D:D,"Bulunamadı")} | H92: {=_xlfn.XLOOKUP(A94,Product!A:A,Product!E:E,"Bulunamadı")} -> 4.66 | I92: =A92&" - "&E92&" - "&F92 -> 6044 - History - Crime | J92: =D92*H92 -> 778.22 | K92: =IF(D92>0,1,0) -> 1
A93: =IFERROR(__xludf.DUMMYFUNCTION("""COMPUTED_VALUE"""),82913.0) -> 82913 | B93: =IFERROR(__xludf.DUMMYFUNCTION("""COMPUTED_VALUE"""),1.0) -> 1 | C93: =IFERROR(__xludf.DUMMYFUNCTION("""COMPUTED_VALUE"""),196.0) -> 196 | D93: =IFERROR(__xludf.DUMMYFUNCTION("""COMPUTED_VALUE"""),116.0) -> 116 | E93: {=_xlfn.XLOOKUP(A93,Product!A:A,Product!B:B,"Bulunamadı")} -> History | F93: {=_xlfn.XLOOKUP(A93,Product!A:A,Product!C:C,"Bulunamadı")} -> Crime | G93: {=_xlfn.XLOOKUP(A94,Product!A:A,Product!D:D,"Bulunamadı")} | H93: {=_xlfn.XLOOKUP(A95,Product!A:A,Product!E:E,"Bulunamadı")} -> 5.21 | I93: =A93&" - "&E93&" - "&F93 -> 82913 - History - Crime | J93: =D93*H93 -> 604.36 | K93: =IF(D93>0,1,0) -> 1
A94: =IFERROR(__xludf.DUMMYFUNCTION("""COMPUTED_VALUE"""),82922.0) -> 82922 | B94: =IFERROR(__xludf.DUMMYFUNCTION("""COMPUTED_VALUE"""),1.0) -> 1 | C94: =IFERROR(__xludf.DUMMYFUNCTION("""COMPUTED_VALUE"""),783.0) -> 783 | D94: =IFERROR(__xludf.DUMMYFUNCTION("""COMPUTED_VALUE"""),107.0) -> 107 | E94: {=_xlfn.XLOOKUP(A94,Product!A:A,Product!B:B,"Bulunamadı")} -> History | F94: {=_xlfn.XLOOKUP(A94,Product!A:A,Product!C:C,"Bulunamadı")} -> Crime | G94: {=_xlfn.XLOOKUP(A95,Product!A:A,Product!D:D,"Bulunamadı")} | H94: {=_xlfn.XLOOKUP(A96,Product!A:A,Product!E:E,"Bulunamadı")} -> 3.3 | I94: =A94&" - "&E94&" - "&F94 -> 82922 - History - Crime | J94: =D94*H94 -> 353.1 | K94: =IF(D94>0,1,0) -> 1
A95: =IFERROR(__xludf.DUMMYFUNCTION("""COMPUTED_VALUE"""),6045.0) -> 6045 | B95: =IFERROR(__xludf.DUMMYFUNCTION("""COMPUTED_VALUE"""),1.0) -> 1 | C95: =IFERROR(__xludf.DUMMYFUNCTION("""COMPUTED_VALUE"""),0.0) -> 0 | D95: =IFERROR(__xludf.DUMMYFUNCTION("""COMPUTED_VALUE"""),0.0) -> 0 | E95: {=_xlfn.XLOOKUP(A95,Product!A:A,Product!B:B,"Bulunamadı")} -> History | F95: {=_xlfn.XLOOKUP(A95,Product!A:A,Product!C:C,"Bulunamadı")} -> Crime | G95: {=_xlfn.XLOOKUP(A96,Product!A:A,Product!D:D,"Bulunamadı")} | H95: {=_xlfn.XLOOKUP(A97,Product!A:A,Product!E:E,"Bulunamadı")} -> 2.49 | I95: =A95&" - "&E95&" - "&F95 -> 6045 - History - Crime | J95: =D95*H95 -> 0 | K95: =IF(D95>0,1,0) -> 0
A96: =IFERROR(__xludf.DUMMYFUNCTION("""COMPUTED_VALUE"""),6027.0) -> 6027 | B96: =IFERROR(__xludf.DUMMYFUNCTION("""COMPUTED_VALUE"""),0.0) -> 0 | C96: =IFERROR(__xludf.DUMMYFUNCTION("""COMPUTED_VALUE"""),282.0) -> 282 | D96: =IFERROR(__xludf.DUMMYFUNCTION("""COMPUTED_VALUE"""),174.0) -> 174 | E96: {=_xlfn.XLOOKUP(A96,Product!A:A,Product!B:B,"Bulunamadı")} -> History | F96: {=_xlfn.XLOOKUP(A96,Product!A:A,Product!C:C,"Bulunamadı")} -> Crime | G96: {=_xlfn.XLOOKUP(A97,Product!A:A,Product!D:D,"Bulunamadı")} -> Redwood Publishing | H96: {=_xlfn.XLOOKUP(A98,Product!A:A,Product!E:E,"Bulunamadı")} -> 12.97 | I96: =A96&" - "&E96&" - "&F96 -> 6027 - History - Crime | J96: =D96*H96 -> 2256.78 | K96: =IF(D96>0,1,0) -> 1
A97: =IFERROR(__xludf.DUMMYFUNCTION("""COMPUTED_VALUE"""),97088.0) -> 97088 | B97: =IFERROR(__xludf.DUMMYFUNCTION("""COMPUTED_VALUE"""),1.0) -> 1 | C97: =IFERROR(__xludf.DUMMYFUNCTION("""COMPUTED_VALUE"""),356.0) -> 356 | D97: =IFERROR(__xludf.DUMMYFUNCTION("""COMPUTED_VALUE"""),290.0) -> 290 | E97: {=_xlfn.XLOOKUP(A97,Product!A:A,Product!B:B,"Bulunamadı")} -> History | F97: {=_xlfn.XLOOKUP(A97,Product!A:A,Product!C:C,"Bulunamadı")} -> Fantasy | G97: {=_xlfn.XLOOKUP(A98,Product!A:A,Product!D:D,"Bulunamadı")} -> Crown Gate Press | H97: {=_xlfn.XLOOKUP(A99,Product!A:A,Product!E:E,"Bulunamadı")} -> 18.29 | I97: =A97&" - "&E97&" - "&F97 -> 97088 - History - Fantasy | J97: =D97*H97 -> 5304.1 | K97: =IF(D97>0,1,0) -> 1
A98: =IFERROR(__xludf.DUMMYFUNCTION("""COMPUTED_VALUE"""),122235.0) -> 122235 | B98: =IFERROR(__xludf.DUMMYFUNCTION("""COMPUTED_VALUE"""),1.0) -> 1 | C98: =IFERROR(__xludf.DUMMYFUNCTION("""COMPUTED_VALUE"""),941.0) -> 941 | D98: =IFERROR(__xludf.DUMMYFUNCTION("""COMPUTED_VALUE"""),126.0) -> 126 | E98: {=_xlfn.XLOOKUP(A98,Product!A:A,Product!B:B,"Bulunamadı")} -> History | F98: {=_xlfn.XLOOKUP(A98,Product!A:A,Product!C:C,"Bulunamadı")} -> Fantasy | G98: {=_xlfn.XLOOKUP(A99,Product!A:A,Product!D:D,"Bulunamadı")} -> Crown Gate Press | H98: {=_xlfn.XLOOKUP(A100,Product!A:A,Product!E:E,"Bulunamadı")} -> 13.46 | I98: =A98&" - "&E98&" - "&F98 -> 122235 - History - Fantasy | J98: =D98*H98 -> 1695.96 | K98: =IF(D98>0,1,0) -> 1
A99: =IFERROR(__xludf.DUMMYFUNCTION("""COMPUTED_VALUE"""),119887.0) -> 119887 | B99: =IFERROR(__xludf.DUMMYFUNCTION("""COMPUTED_VALUE"""),1.0) -> 1 | C99: =IFERROR(__xludf.DUMMYFUNCTION("""COMPUTED_VALUE"""),732.0) -> 732 | D99: =IFERROR(__xludf.DUMMYFUNCTION("""COMPUTED_VALUE"""),498.0) -> 498 | E99: {=_xlfn.XLOOKUP(A99,Product!A:A,Product!B:B,"Bulunamadı")} -> History | F99: {=_xlfn.XLOOKUP(A99,Product!A:A,Product!C:C,"Bulunamadı")} -> Fantasy | G99: {=_xlfn.XLOOKUP(A100,Product!A:A,Product!D:D,"Bulunamadı")} -> Aurora Book House | H99: {=_xlfn.XLOOKUP(A101,Product!A:A,Product!E:E,"Bulunamadı")} -> 14.78 | I99: =A99&" - "&E99&" - "&F99 -> 119887 - History - Fantasy | J99: =D99*H99 -> 7360.44 | K99: =IF(D99>0,1,0) -> 1
A100: =IFERROR(__xludf.DUMMYFUNCTION("""COMPUTED_VALUE"""),97980.0) -> 97980 | B100: =IFERROR(__xludf.DUMMYFUNCTION("""COMPUTED_VALUE"""),0.0) -> 0 | C100: =IFERROR(__xludf.DUMMYFUNCTION("""COMPUTED_VALUE"""),366.0) -> 366 | D100: =IFERROR(__xludf.DUMMYFUNCTION("""COMPUTED_VALUE"""),344.0) -> 344 | E100: {=_xlfn.XLOOKUP(A100,Product!A:A,Product!B:B,"Bulunamadı")} -> History | F100: {=_xlfn.XLOOKUP(A100,Product!A:A,Product!C:C,"Bulunamadı")} -> Fantasy | G100: {=_xlfn.XLOOKUP(A101,Product!A:A,Product!D:D,"Bulunamadı")} -> Aurora Book House | H100: {=_xlfn.XLOOKUP(A102,Product!A:A,Product!E:E,"Bulunamadı")} -> 14.14 | I100: =A100&" - "&E100&" - "&F100 -> 97980 - History - Fantasy | J100: =D100*H100 -> 4864.16 | K100: =IF(D100>0,1,0) -> 1
...

Sheet Shortage_analysis
E1: Stokta olan ürün sayısı | F1: Ortalama stok | G1: Stok değeri | I1: category_1 | J1: Average stock | K1: Shortage Rate
E3: =COUNTIF(Explo_Stock!K2:K1000,1) -> 5819 | F3: =AVERAGE(Explo_Stock!D2:D1000) -> 243.08356 | G3: =SUM(Explo_Stock!J2:J1000) -> 6267378 | I3: Arts | J3: 237.7617 | K3: =C3 -> 0.010486177
E4: =COUNTIF(Explo_Stock!K3:K1000,1) -> 5818 | F4: =AVERAGE(Explo_Stock!D3:D1000) -> 243.07052 | G4: =SUM(Explo_Stock!J3:J1000) -> 6266686.8 | I4: Fiction | J4: =IFERROR(AVERAGEIF(Explo_Stock!E$2:E$6401,I3,Explo_Stock!D$2:D$6401),0) -> 237.76168 | K4: =C4 -> 0.013435701
E5: =COUNTIF(Explo_Stock!K4:K1000,1) -> 5818 | F5: =AVERAGE(Explo_Stock!D4:D1000) -> 243.11173 | G5: =SUM(Explo_Stock!J4:J1000) -> 6266686.8 | I5: Finance | J5: =IFERROR(AVERAGEIF(Explo_Stock!E$2:E$6401,I4,Explo_Stock!D$2:D$6401),0) -> 258.23033 | K5: =C5 -> 0.0093896714
E6: =COUNTIF(Explo_Stock!K5:K1000,1) -> 5817 | F6: =AVERAGE(Explo_Stock!D5:D1000) -> 243.136 | G6: =SUM(Explo_Stock!J5:J1000) -> 6266579.8 | I6: History | J6: =IFERROR(AVERAGEIF(Explo_Stock!E$2:E$6401,I5,Explo_Stock!D$2:D$6401),0) -> 257.93427 | K6: =C6 -> 0.010615711
E7: =COUNTIF(Explo_Stock!K6:K1000,1) -> 5816 | F7: =AVERAGE(Explo_Stock!D6:D1000) -> 243.13178 | G7: =SUM(Explo_Stock!J6:J1000) -> 6264194.6 | I7: Law | J7: =IFERROR(AVERAGEIF(Explo_Stock!E$2:E$6401,I6,Explo_Stock!D$2:D$6401),0) -> 220.14437 | K7: =C7 -> 0.018469657
E8: =COUNTIF(Explo_Stock!K7:K1000,1) -> 5815 | F8: =AVERAGE(Explo_Stock!D7:D1000) -> 243.09296 | G8: =SUM(Explo_Stock!J7:J1000) -> 6260022.1 | I8: Medical | J8: =IFERROR(AVERAGEIF(Explo_Stock!E$2:E$6401,I7,Explo_Stock!D$2:D$6401),0) -> 240.44195 | K8: =C8 -> 0.014778325
E9: =COUNTIF(Explo_Stock!K8:K1000,1) -> 5814 | F9: =AVERAGE(Explo_Stock!D8:D1000) -> 243.12352 | G9: =SUM(Explo_Stock!J8:J1000) -> 6259714 | I9: Self-Help | J9: =IFERROR(AVERAGEIF(Explo_Stock!E$2:E$6401,I8,Explo_Stock!D$2:D$6401),0) -> 253.4803 | K9: =C9 -> 0.012820513
E10: =COUNTIF(Explo_Stock!K9:K1000,1) -> 5813 | F10: =AVERAGE(Explo_Stock!D9:D1000) -> 243.15917 | G10: =SUM(Explo_Stock!J9:J1000) -> 6259650 | I10: Sports | J10: =IFERROR(AVERAGEIF(Explo_Stock!E$2:E$6401,I9,Explo_Stock!D$2:D$6401),0) -> 226.98718 | K10: =C10 -> 0.0091324201
E11: =COUNTIF(Explo_Stock!K10:K1000,1) -> 5812 | F11: =AVERAGE(Explo_Stock!D10:D1000) -> 243.18279 | G11: =SUM(Explo_Stock!J10:J1000) -> 6259465.9 | I11: Tech | J11: =IFERROR(AVERAGEIF(Explo_Stock!E$2:E$6401,I10,Explo_Stock!D$2:D$6401),0) -> 245.58676 | K11: =C11 -> 0.014072848

Sheet stok_analysis

Sheet Pivot Table 2

Sheet Deliverables >>

Sheet Stock_Categories_Dashboard

Sheet RESULTS
A1: 📦 INVENTORY TEAM
A3: Team Objective
A4: Optimize inventory availability by identifying stock shortages early, monitoring inventory value, and forecasting replenishment needs to minimize stockouts and excess inventory.
A7: Primary KPIs
A9: KPI name | B9: Description | D9: Why it matters?
A10: Team Priorities | B10: Prevent stockouts, identify low-stock books and prioritize replenishment. | D10: Ensures books are available when customers need them.
A11: Data-Driven Decisions | B11: Use inventory levels and sales data to forecast demand and replenishment needs. | D11: Helps the team make timely and accurate purchasing decisions.
A12: Inventory KPIs | B12: Inventory units, inventory value, stockout rate, stock availability, sales velocity, and reorder quantity. | D12: Measures inventory health and identifies products requiring immediate action.
A14: Inventory Stock Analysis — Results & Insights 1. Overall Shortage Rate The overall stock shortage rate is 1.37%. This represents the percentage of products that are currently out of stock. 2. Highest-Risk Product Categories The Law category has the highest shortage rate at 1.85%, followed by Medical (1.48%), Tech (1.41%), Fiction (1.34%), and Self-Help (1.28%). These categories should receive priority in stock monitoring and replenishment planning. 3. Recommendations for the Inventory Team Prioritize stock checks for Law, Medical, and Tech products. Identify individual products that are out of stock and need urgent replenishment. Compare current stock levels with forecast demand to prevent future shortages. Monitor shortage rates regularly and adjust replenishment priorities when needed. 4. Procurement Meeting Summary The overall stock shortage rate is 1.37%, with Law showing the highest rate at 1.85%. We recommend prioritizing replenishment for high-risk categories and reviewing supplier availability and delivery times. Procurement decisions should consider forecast demand to prevent stockouts while avoiding unnecessary overstocking.
